Workbook

Sheet Introduction
B2: Introduction
B4: The examples provided in this file were scenarios performed during User Acceptance Testing in S4 HANA Q40. The scenario results have been copied from SAP HANA Q40 to the SAP training system.
B5: As Lease Accounting is a centralised process managed in BSC Manchester by the Lease Accounting Team and postings are initiated by Nakisa, there are no testing scenarios that can be reperformed end-to-end locally by markets.
B6: Entities may however use the data in this file to extract and recheck the results of UAT to understand how postings were made under each scenario and accounting approach.
B7: If you have questions, please consult your S4 Power User to understand what was performed and validated during testing
B8: For an explanation of the changes to the Lease Accounting Process under S4 (e.g. accounting approach treatment in STAT and TAX ledgers, Tax Perm Tagging for Leasing etc., please refer to the powerpoint training presentation.
B10: Please find details below explaining the data content on each tab and how to use it:
B12: SOURCE DATA
B13: Entity Accounting Approach:
B14: On this tab you can check the applicable accounting approach for the IFRS, STAT and TAX ledgers for each entity
B15: Scenarios:
B16: This tab provides you with information for all the scenarios by stages. You can check the sceanrio inputs (such as dates, currencies, contract terms etc.) for PR/PO creation, invoice/invoice plan creation and Nakisa Contract data.
... B47: On this tab you can explore different GL accounts used for leasing. This tab also includes the P&L accounts where TPT IDs will posted if applicable

Sheet Entity Accounting Approach
B2: Final Entity Configuration - S4 P40
A3: Entity number | B3: IFRS Ledger Approach | C3: Statutory Ledger Approach | D3: Tax Ledger Approach | E3: Country
A4: 1011 | B4: IFRS 16 | C4: IFRS 16 | D4: Accrual | E4: USA
A5: 1100 | B5: IFRS 16 | C5: IFRS 16 | D5: IFRS 16 | E5: Switzerland
A6: 1104 | B6: IFRS 16 | C6: IFRS 16 | D6: Accrual | E6: Cyprus
A7: 1106 | B7: IFRS 16 | C7: Accrual | D7: Accrual | E7: Germany
A8: 1107 | B8: IFRS 16 | C8: Accrual | D8: Accrual | E8: France
A9: 1114 | B9: IFRS 16 | C9: Accrual | D9: Accrual | E9: Netherlands
A10: 1116 | B10: IFRS 16 | C10: Accrual | D10: Accrual | E10: Greece
A11: 1118 | B11: IFRS 16 | C11: IFRS 16 | D11: Accrual | E11: Canada
A12: 1129 | B12: IFRS 16 | C12: IFRS 16 | D12: Accrual | E12: Malaysia
A13: 1143 | B13: IFRS 16 | C13: IFRS 16 | D13: IFRS 16 | E13: Hong Kong
A14: 1159 | B14: IFRS 16 | C14: Accrual | D14: Accrual | E14: Italy
A15: 1169 | B15: IFRS 16 | C15: Accrual | D15: Accrual | E15: Czech Republic
... A77: 2345 | B77: IFRS 16 | C77: Accrual | D77: Accrual | E77: Austria

Sheet Scenarios
B1: Nakisa Purchase Order / Invoice Creation Details
B3: 1 - Capitalised Contract | E3: 2 - Low Value Contract | H3: 3 - Short Term Contract
B5: PR/PO Creation | E5: PR/PO Creation (Framework Order / Invoice Plan) | H5: PR/PO Creation (Non-recoverable VAT)
B6: Material Group Name: | C6: =VLOOKUP(C7,'Material Groups'!$B:$C,2,0) -> LeaseBuild FixedCost | E6: Material Group Name: | F6: =VLOOKUP(F7,'Material Groups'!$B:$C,2,0) -> LeaseFrnFixt FixCost | H6: Material Group Name: | I6: LeaseVehicleFixCo/ND
B7: Material Group No: | C7: 95101111 | E7: Material Group No: | F7: 95101119 | H7: Material Group No: | I7: 95101117
B8: Vendor: | C8: Any related to Leasing | E8: Vendor: | F8: Any related to Leasing | H8: Vendor: | I8: Any related to Leasing
B9: Cost center: | C9: Any related to Leasing | E9: Cost center: | F9: Any related to Leasing | H9: Cost center: | I9: Any related to Leasing
B10: Tax code: | C10: Any fully recoverable VAT tax code | E10: Tax code: | F10: Any fully recoverable VAT tax code | H10: Tax code: | I10: Any non-recoverable VAT tax code
B11: Currency: | C11: Local currency (LC1) | E11: Currency: | F11: Local currency (LC1) | H11: Currency: | I11: Local currency (LC1)
B12: Quantity: | C12: 120 | E12: Quantity: | F12: 24 months | H12: Quantity: | I12: 9
B13: Price (ex. VAT): | C13: 7500 | E13: Price (ex. VAT): | F13: 250 | H13: Price (ex. VAT): | I13: 5000
B15: Invoice Creation (AP) | E15: Invoice Plan - No AP invoicing | H15: Invoice Creation (AP)
B16: Invoice 1 Date: | C16: 43647 | E16: Invoice 1 Date: | F16: 43647 | H16: Invoice 1 Date: | I16: 43647
B17: Invoice 1 Qty: | C17: 1 | E17: Invoice 1 Qty: | F17: 1 | H17: Invoice 1 Qty: | I17: 1
B18: Invoice 1 Price (ex. VAT): | C18: 7500 | E18: Invoice 1 Price (ex. VAT): | F18: 250 | H18: Invoice 1 Price (ex. VAT): | I18: 5000
B19: Invoice 1 PO: | C19: See PO numbers tab | E19: Invoice 1 PO: | F19: N/A | H19: Invoice 1 PO: | I19: See PO numbers tab
B20: Invoice 2 Date: | C20: 43678 | E20: Invoice 2 Date: | F20: 43678 | H20: Invoice 2 Date: | I20: 43678
B21: Invoice 2 Qty: | C21: 1 | E21: Invoice 2 Qty: | F21: 1 | H21: Invoice 2 Qty: | I21: 1
B22: Invoice 2 Price (ex. VAT): | C22: 7500 | E22: Invoice 2 Price (ex. VAT): | F22: 250 | H22: Invoice 2 Price (ex. VAT): | I22: 5000
B23: Invoice 2 PO: | C23: See PO numbers tab | E23: Invoice 2 PO: | F23: N/A | H23: Invoice 2 PO: | I23: See PO numbers tab
B25: Nakisa Contract Data | E25: Nakisa Contract Data | H25: Nakisa Contract Data
B26: Annual interest rate | C26: 0.05 | E26: Annual interest rate | F26: N/A | H26: Annual interest rate | I26: N/A
B27: Lease payment per period | C27: 7500 | E27: Lease payment per period | F27: 250 | H27: Lease payment per period | I27: 5000 + non-recoverable VAT
B28: Payment frequency | C28: Monthly | E28: Payment frequency | F28: Monthly | H28: Payment frequency | I28: Monthly
B29: Payment timing | C29: Advance | E29: Payment timing | F29: Advance | H29: Payment timing | I29: Advance
B30: First payment Date | C30: 43647 | E30: First payment Date | F30: 43647 | H30: First payment Date | I30: 43647
B31: Lease term (months) | C31: 120 | E31: Lease term (months) | F31: 24 | H31: Lease term (months) | I31: 9
B32: Lease start date | C32: 43647 | E32: Lease start date | F32: 43647 | H32: Lease start date | I32: 43647
B33: Lease end date | C33: 47299 | E33: Lease end date | F33: 44377 | H33: Lease end date | I33: 43921
B36: 4 - Prepaid Contract | E36: 5 - Contract Extension | H36: 6 - Contract Termination
B38: PR/PO Creation | E38: PR/PO Creation | H38: PR/PO Creation
B39: Material Group Name: | C39: =VLOOKUP(C40,'Material Groups'!$B:$C,2,0) -> LeaseLand FixedCost | E39: Material Group Name: | F39: =VLOOKUP(F40,'Material Groups'!$B:$C,2,0) -> LeaseVehicle FixCost | H39: Material Group Name: | I39: =VLOOKUP(I40,'Material Groups'!$B:$C,2,0) -> Lease HW Fixed Cost
B40: Material Group No: | C40: 95101113 | E40: Material Group No: | F40: 95101110 | H40: Material Group No: | I40: 95101116
B41: Vendor: | C41: Any related to Leasing | E41: Vendor: | F41: Any related to Leasing | H41: Vendor: | I41: Any related to Leasing
B42: Cost center: | C42: Any related to Leasing | E42: Cost center: | F42: Any related to Leasing | H42: Cost center: | I42: Any related to Leasing
B43: Tax code: | C43: Any fully recoverable VAT tax code | E43: Tax code: | F43: Any fully recoverable VAT tax code | H43: Tax code: | I43: Any fully recoverable VAT tax code
B44: Currency: | C44: Local currency (LC1) | E44: Currency: | F44: Local currency (LC1) | H44: Currency: | I44: Local currency (LC1)
B45: Quantity: | C45: 1 | E45: Quantity: | F45: 72 | H45: Quantity: | I45: 48
B46: Price (ex. VAT): | C46: 60000 | E46: Price (ex. VAT): | F46: 2000 | H46: Price (ex. VAT): | I46: 4000
B48: Invoice Creation (AP) | E48: Invoice Creation (AP) | H48: Invoice Creation (AP)
B49: Invoice 1 Date: | C49: 43647 | E49: Invoice 1 Date: | F49: 43682 | H49: Invoice 1 Date: | I49: 43647
B50: Invoice 1 Qty: | C50: 1 | E50: Invoice 1 Qty: | F50: 1 | H50: Invoice 1 Qty: | I50: 1
B51: Invoice 1 Price (ex. VAT): | C51: 60000 | E51: Invoice 1 Price (ex. VAT): | F51: 2000 | H51: Invoice 1 Price (ex. VAT): | I51: 4000
B52: Invoice 1 PO: | C52: See PO numbers tab | E52: Invoice 1 PO: | F52: See PO numbers tab | H52: Invoice 1 PO: | I52: See PO numbers tab
B53: Invoice 2 Date: | C53: N/A | E53: Invoice 2 Date: | F53: 43708 | H53: Invoice 2 Date: | I53: N/A
B54: Invoice 2 Qty: | C54: N/A | E54: Invoice 2 Qty: | F54: 1 | H54: Invoice 2 Qty: | I54: N/A
B55: Invoice 2 Price (ex. VAT): | C55: N/A | E55: Invoice 2 Price (ex. VAT): | F55: 2000 | H55: Invoice 2 Price (ex. VAT): | I55: N/A
B56: Invoice 2 PO: | C56: N/A | E56: Invoice 2 PO: | F56: See PO numbers tab | H56: Invoice 2 PO: | I56: N/A
B58: Nakisa Contract Data | E58: Nakisa Contract Data | H58: Nakisa Contract Data
B59: Annual interest rate | C59: 0.03 | E59: Annual interest rate | F59: 0.09 | H59: Annual interest rate | I59: 0.07
B60: Lease payment per period | C60: 60000 | E60: Lease payment per period | F60: 2000 | H60: Lease payment per period | I60: 4000
B61: Payment frequency | C61: Fully Prepaid | E61: Payment frequency | F61: Monthly | H61: Payment frequency | I61: Monthly
B62: Payment timing | C62: Advance | E62: Payment timing | F62: Arrears | H62: Payment timing | I62: Advance
B63: First payment Date | C63: 43647 | E63: First payment Date | F63: 43677 | H63: First payment Date | I63: 43647
B64: Lease term (months) | C64: 14 | E64: Lease term (months) | F64: 84 + 12 (extension) | H64: Lease term (months) | I64: 48
B65: Lease start date | C65: 43647 | E65: Lease start date | F65: 43647 | H65: Lease start date | I65: 43647
B66: Lease end date | C66: 44074 | E66: Lease end date | F66: 46203 | H66: Lease end date | I66: 45107
E67: End date after extension | F67: 46568 | H67: Termination date | I67: 43678
B70: 7 - Capitalised contract - foreign currency
B72: PR/PO Creation
B73: Material Group Name: | C73: =VLOOKUP(C74,'Material Groups'!$B:$C,2,0) -> LeaseEquip FixedCost
B74: Material Group No: | C74: 95101114
B75: Vendor: | C75: Any Foreign Currency Vendor related to Leasing
B76: Cost center: | C76: Any related to Leasing
B77: Tax code: | C77: Any fully recoverable VAT tax code
B78: Currency: | C78: Any currency other than local currency (LC1). If you do not have any foreign currency vendors, please state this in HPALM and use a local currency vendor
B79: Quantity: | C79: 15
B80: Price (ex. VAT): | C80: 1000
B82: Invoice Creation (AP)
B83: Invoice 1 Date: | C83: 43661
B84: Invoice 1 Qty: | C84: 1
B85: Invoice 1 Price (ex. VAT): | C85: 1000
B86: Invoice 1 PO: | C86: See PO numbers tab
B87: Invoice 2 Date: | C87: 43708
B88: Invoice 2 Qty: | C88: 1
B89: Invoice 2 Price (ex. VAT): | C89: 1015
B90: Invoice 2 PO: | C90: See PO tab
B92: Nakisa Contract Data
B93: Annual interest rate | C93: 0.125
B94: Lease payment per period | C94: 1000
B95: Payment frequency | C95: Arrears
B96: Payment timing | C96: Monthly
B97: First payment Date | C97: 43677
B98: Lease term (months) | C98: 15
B99: Lease start date | C99: 43647
B100: Lease end date | C100: 44104

Sheet PO numbers
B1: 2 | C1: 3 | D1: 4 | E1: 5 | F1: 6 | G1: 2 | H1: 3 | I1: 4 | J1: 5 | K1: 6 | L1: 2 | M1: 3 | N1: 4 | O1: 5 | P1: 6 | Q1: 2 | R1: 3 | S1: 4 | T1: 5 | U1: 6 | V1: 2 | W1: 3 | X1: 4 | Y1: 5 | Z1: 6 | AA1: 2 | AB1: 3 | AC1: 4 | AD1: 5 | AE1: 6 | AF1: 2 | AG1: 3 | AH1: 4 | AI1: 5 | AJ1: 6
B2: 1 - Capitalised Contract | G2: 2 - Low Value Contract | L2: 3 - Short Term Contract | Q2: 4 - Prepaid Contract | V2: 5 - Contract Extension | AA2: 6 - Contract Termination | AF2: 7 - Capitalised contract - foreign currency
B3: PO Number | C3: Cost Center | D3: Profit Center | E3: Vendor No. | F3: Contract currency (DC) | G3: PO Number | H3: Cost Center | I3: Profit Center | J3: Vendor No. | K3: Contract currency (DC) | L3: PO Number | M3: Cost Center | N3: Profit Center | O3: Vendor No. | P3: Contract currency (DC) | Q3: PO Number | R3: Cost Center | S3: Profit Center | T3: Vendor No. | U3: Contract currency (DC) | V3: PO Number | W3: Cost Center | X3: Profit Center | Y3: Vendor No. | Z3: Contract currency (DC) | AA3: PO Number | AB3: Cost Center | AC3: Profit Center | AD3: Vendor No. | AE3: Contract currency (DC) | AF3: PO Number | AG3: Cost Center | AH3: Profit Center | AI3: Vendor No. | AJ3: Contract currency (DC)
A4: 1011 | B4: 4700407259 | C4: 0000039351 | D4: G043 | E4: 119862 | F4: USD | G4: 4502609384 | H4: 0000039351 | I4: G043 | J4: 119862 | K4: USD | L4: 4700407298 | M4: 0000039351 | N4: G043 | O4: 119862 | P4: USD | Q4: 4700407299 | R4: 0000039351 | S4: G043 | T4: 119862 | U4: USD | V4: 4700407300 | W4: 0000039351 | X4: G043 | Y4: 119862 | Z4: USD | AA4: 4700407301 | AB4: 0000039351 | AC4: G043 | AD4: 119862 | AE4: USD | AF4: 4700407302 | AG4: 0000039351 | AH4: G043 | AI4: 119862 | AJ4: USD
A5: 1100 | B5: 4700405599 | C5: 0000014100 | D5: CH00 | E5: 123019 | F5: CHF | G5: 4502608390 | H5: 0000014100 | I5: CH00 | J5: 123019 | K5: CHF | L5: 4700406719 | M5: 0000014302 | N5: CHP1 | O5: 56851 | P5: CHF | Q5: 4700405661 | R5: 0000014100 | S5: CH00 | T5: 123019 | U5: CHF | V5: 4700405662 | W5: 0000014100 | X5: CH00 | Y5: 123019 | Z5: CHF | AA5: 4700405664 | AB5: 0000014100 | AC5: CH00 | AD5: 123019 | AE5: CHF | AF5: 4700405707 | AG5: 0000014100 | AH5: CH00 | AI5: 123019 | AJ5: CHF
A6: 1104 | B6: 4502609416 | C6: 0000023147 | D6: CY00 | E6: 94416 | F6: EUR | G6: 4502609422 | H6: 0000023147 | I6: CY00 | J6: 94416 | K6: EUR | L6: 4502609417 | M6: 0000023147 | N6: CY00 | O6: 94416 | P6: EUR | Q6: 4502609418 | R6: 0000023147 | S6: CY00 | T6: 94416 | U6: EUR | V6: 4502609419 | W6: 0000023147 | X6: CY00 | Y6: 94416 | Z6: EUR | AA6: 4502609420 | AB6: 0000023147 | AC6: CY00 | AD6: 94416 | AE6: EUR | AF6: 4502609421 | AG6: 0000023147 | AH6: CY00 | AI6: 94416 | AJ6: EUR
A7: 1106 | B7: 4700406277 | C7: 0000022310 | D7: DE00 | E7: 41106 | F7: EUR | G7: 4502608651 | H7: 0000022464 | I7: DE00 | J7: 18213 | K7: EUR | L7: 4700406282 | M7: 0000022464 | N7: DE00 | O7: 169884 | P7: EUR | Q7: 4700406283 | R7: 0000022072 | S7: DEP1 | T7: 202972 | U7: EUR | V7: 4700406286 | W7: 0000022072 | X7: DEP1 | Y7: 17198 | Z7: EUR | AA7: 4700406328 | AB7: 0000022072 | AC7: DEP1 | AD7: 152344 | AE7: EUR | AF7: 4700406329 | AG7: 0000022072 | AH7: DEP1 | AI7: 36823 | AJ7: CHF
A8: 1107 | B8: 4700405719 | C8: 0000012506 | D8: FR00 | E8: 248244 | F8: EUR | G8: 4502608438 | H8: 0000012307 | I8: FR00 | J8: 248244 | K8: EUR | L8: 4700405763 | M8: 0000012307 | N8: FR00 | O8: 248244 | P8: EUR | Q8: 4700405921 | R8: 0000012506 | S8: FR00 | T8: 248244 | U8: EUR | V8: 4700405940 | W8: 0000012307 | X8: FR00 | Y8: 248244 | Z8: EUR | AA8: 4700405983 | AB8: 0000012307 | AC8: FR00 | AD8: 248244 | AE8: EUR | AF8: 4700407101 | AG8: 0000012307 | AH8: FR00 | AI8: 248244 | AJ8: EUR
A9: 1114 | B9: 4700405979 | C9: 0000010203 | D9: NL00 | E9: 210725 | F9: EUR | G9: 4502608501 | H9: 0000010201 | I9: NL00 | J9: 23588 | K9: EUR | L9: 4700405962 | M9: 0000010201 | N9: NL00 | O9: 23588 | P9: EUR | Q9: 4700405963 | R9: 0000010201 | S9: NL00 | T9: 23588 | U9: EUR | V9: 4502608509 | W9: 0000010201 | X9: NL00 | Y9: 23588 | Z9: EUR | AA9: 4700405971 | AB9: 0000010201 | AC9: NL00 | AD9: 23588 | AE9: EUR | AF9: 4700405964 | AG9: 0000010201 | AH9: NL00 | AI9: 23588 | AJ9: USD
A10: 1116 | B10: 4502609276 | C10: 0000034001 | D10: GR00 | E10: 131553 | F10: EUR | G10: 4502609271 | H10: 0000034001 | I10: GR00 | J10: 131553 | K10: EUR | L10: 4502609272 | M10: 0000034001 | N10: GR00 | O10: 233392 | P10: EUR | Q10: 4502609270 | R10: 0000034001 | S10: GR00 | T10: 131553 | U10: EUR | V10: 4502609275 | W10: 0000034001 | X10: GR00 | Y10: 233392 | Z10: EUR | AA10: 4502609274 | AB10: 0000034001 | AC10: GR00 | AD10: 131553 | AE10: EUR | AF10: 4502609273 | AG10: 0000034001 | AH10: GR00 | AI10: 235849 | AJ10: USD
A11: 1118 | B11: 4700406288 | C11: 0000038740 | D11: CA00 | E11: 257180 | F11: CAD | G11: 4502608653 | H11: 0000038740 | I11: CA00 | J11: 257180 | K11: CAD | L11: 4700406293 | M11: 0000038740 | N11: CA00 | O11: 166279 | P11: CAD | Q11: 4700406294 | R11: 0000038740 | S11: CA00 | T11: 257180 | U11: CAD | V11: 4700406295 | W11: 0000038740 | X11: CA00 | Y11: 166279 | Z11: CAD | AA11: 4700406296 | AB11: 0000038740 | AC11: CA00 | AD11: 257180 | AE11: CAD | AF11: 4700406301 | AG11: 0000038740 | AH11: CA00 | AI11: 257180 | AJ11: CAD
A12: 1129 | B12: 4700406198 | C12: 0000036714 | D12: MY00 | E12: 97783 | F12: MYR | G12: 4502608626 | H12: 0000036802 | I12: M015 | J12: 97783 | K12: MYR | L12: 4700406231 | M12: 0000036715 | N12: MY00 | O12: 281416 | P12: MYR | Q12: 4700406245 | R12: 0000036802 | S12: M015 | T12: 280733 | U12: MYR | V12: 4700406260 | W12: 0000036714 | X12: MY00 | Y12: 176689 | Z12: MYR | AA12: 4700406269 | AB12: 0000036802 | AC12: M015 | AD12: 257030 | AE12: MYR | AF12: 4700406273 | AG12: 0000036712 | AH12: MY00 | AI12: 156446 | AJ12: MYR
A13: 1143 | B13: 4700407127 | C13: 0000035961 | D13: M015 | E13: 279849 | F13: USD | G13: 4502609306 | H13: 0000035962 | I13: M015 | J13: 82155 | K13: USD | L13: 4700407141 | M13: 0000035962 | N13: M015 | O13: 82155 | P13: USD | Q13: 4700407149 | R13: 0000035962 | S13: M015 | T13: 82155 | U13: USD | V13: 4700407151 | W13: 0000035962 | X13: M015 | Y13: 82155 | Z13: USD | AA13: 4700407162 | AB13: 0000035962 | AC13: M015 | AD13: 82155 | AE13: USD | AF13: 4700407172 | AG13: 0000035962 | AH13: M015 | AI13: 82155 | AJ13: HKD
A14: 1159 | B14: 4700405969 | C14: 0000012710 | D14: IT00 | E14: 267241 | F14: EUR | G14: 4700406984 | H14: 0000012760 | I14: IT00 | J14: 24648 | K14: EUR | L14: 4700406069 | M14: 0000012710 | N14: IT00 | O14: 144948 | P14: EUR | Q14: 4700406577 | R14: 0000012760 | S14: IT00 | T14: 280993 | U14: EUR | V14: 4700406080 | W14: 0000012770 | X14: IT00 | Y14: 24522 | Z14: EUR | AA14: 4700406125 | AB14: 0000012760 | AC14: IT00 | AD14: 162271 | AE14: EUR | AF14: 4700406994 | AG14: 0000012760 | AH14: IT00 | AI14: 24648 | AJ14: EUR
A15: 1169 | B15: 4700405754 | C15: 0000011822 | D15: CZ00 | E15: 233854 | F15: CZK | G15: 4502608443 | H15: 0000011822 | I15: CZ00 | J15: 233854 | K15: CZK | L15: 4700405756 | M15: 0000011803 | N15: CZ00 | O15: 233854 | P15: CZK | Q15: 4700405750 | R15: 0000011803 | S15: CZ00 | T15: 21846 | U15: CZK | V15: 4700405718 | W15: 0000011803 | X15: CZ00 | Y15: 21871 | Z15: CZK | AA15: 4700405751 | AB15: 0000011803 | AC15: CZ00 | AD15: 21846 | AE15: CZK | AF15: 4700405753 | AG15: 0000011803 | AH15: CZ00 | AI15: 221565 | AJ15: EUR
A16: 1171 | B16: 4700406543 | C16: 0000013102 | D16: TRP1 | E16: 10558 | F16: TRY | G16: 4700406552 | H16: 0000013102 | I16: TRP1 | J16: 10041 | K16: TRY | L16: 4700406553 | M16: 0000013102 | N16: TRP1 | O16: 108309 | P16: TRY | Q16: 4700406555 | R16: 0000013102 | S16: TRP1 | T16: 10558 | U16: TRY | V16: 4700406556 | W16: 0000013102 | X16: TRP1 | Y16: 108309 | Z16: TRY | AA16: 4700406557 | AB16: 0000013102 | AC16: TRP1 | AD16: 10044 | AE16: TRY | AF16: 4700406559 | AG16: 0000013102 | AH16: TRP1 | AI16: 10764 | AJ16: USD
A17: 1172 | B17: 4700406534 | C17: 0000013011 | D17: TR00 | E17: 10558 | F17: TRY | G17: 4700406532 | H17: 0000013011 | I17: TR00 | J17: 10041 | K17: TRY | L17: 4700406536 | M17: 0000013011 | N17: TR00 | O17: 108309 | P17: TRY | Q17: 4700406538 | R17: 0000013011 | S17: TR00 | T17: 10558 | U17: TRY | V17: 4700406537 | W17: 0000013011 | X17: TR00 | Y17: 288597 | Z17: TRY | AA17: 4700406533 | AB17: 0000013011 | AC17: TR00 | AD17: 10044 | AE17: TRY | AF17: 4700406535 | AG17: 0000013011 | AH17: TR00 | AI17: 10764 | AJ17: USD
A18: 1175 | B18: 4700405873 | C18: 0000028711 | D18: ROP1 | E18: 60156 | F18: RON | G18: 4502608495 | H18: 0000028711 | I18: ROP1 | J18: 60156 | K18: RON | L18: 4700405903 | M18: 0000028711 | N18: ROP1 | O18: 60156 | P18: RON | Q18: 4700405907 | R18: 0000028711 | S18: ROP1 | T18: 60156 | U18: RON | V18: 4700405909 | W18: 0000028711 | X18: ROP1 | Y18: 60156 | Z18: RON | AA18: 4700405917 | AB18: 0000028711 | AC18: ROP1 | AD18: 60156 | AE18: RON | AF18: 4700405919 | AG18: 0000028711 | AH18: ROP1 | AI18: 60156 | AJ18: EUR
... A24: 1197 | B24: 4700406542 | C24: 0000046030 | D24: F020 | E24: 10558 | F24: TRY | G24: 4700406544 | H24: 0000046030 | I24: F020 | J24: 43507 | K24: TRY | L24: 4700406545 | M24: 0000046030 | N24: F020 | O24: 108309 | P24: TRY | Q24: 4700406546 | R24: 0000046030 | S24: F020 | T24: 10036 | U24: TRY | V24: 4700406548 | W24: 0000046030 | X24: F020 | Y24: 105558 | Z24: TRY | AA24: 4700406549 | AB24: 0000046030 | AC24: F020 | AD24: 11360 | AE24: TRY | AF24: 4700406550 | AG24: 0000046030 | AH24: F020 | AI24: 202913 | AJ24: EUR
A25: 1199 | B25: 4700407212 | C25: 0000028015 | D25: TZ00 | E25: 242197 | F25: TZS | G25: 4502609443 | H25: 0000028009 | I25: TZ00 | J25: 262143 | K25: TZS | L25: 4700407351 | M25: 0000028107 | N25: TZ00 | O25: 241474 | P25: TZS | Q25: 4700407392 | R25: 0000028058 | S25: TZ00 | T25: 262153 | U25: TZS | V25: 4700407357 | W25: 0000028107 | X25: TZ00 | Y25: 241474 | Z25: TZS | AA25: 4700407395 | AB25: 0000028009 | AC25: TZ00 | AD25: 243587 | AE25: TZS | AF25: 4700407397 | AG25: 0000028009 | AH25: TZ00 | AI25: 225231 | AJ25: USD
A26: 1215 | B26: 4700407132 | C26: 0000040304 | D26: TN00 | E26: 266163 | F26: TND | G26: 4502609323 | H26: 0000040304 | I26: TN00 | J26: 266163 | K26: TND | L26: 4700407228 | M26: 0000040304 | N26: TN00 | O26: 266163 | P26: TND | Q26: 4700407229 | R26: 0000040300 | S26: TN00 | T26: 266163 | U26: TND | V26: 4700407230 | W26: 0000040304 | X26: TN00 | Y26: 266163 | Z26: TND | AA26: 4700407231 | AB26: 0000040304 | AC26: TN00 | AD26: 266163 | AE26: TND | AF26: 4700407239 | AG26: 0000040300 | AH26: TN00 | AI26: 266163 | AJ26: TND
A27: 1216 | B27: 4700405697 | C27: 0000013701 | D27: ES00 | E27: 136243 | F27: EUR | G27: 4502608435 | H27: 0000013701 | I27: ES00 | J27: 273179 | K27: EUR | L27: 4700405857 | M27: 0000013810 | N27: IC00 | O27: 26048 | P27: EUR | Q27: 4700405866 | R27: 0000013701 | S27: ES00 | T27: 248388 | U27: EUR | V27: 4700405956 | W27: 0000013701 | X27: ES00 | Y27: 26048 | Z27: EUR | AA27: 4700405994 | AB27: 0000013810 | AC27: IC00 | AD27: 158284 | AE27: EUR | AF27: 4700406211 | AG27: 0000013701 | AH27: ES00 | AI27: 114319 | AJ27: EUR
A28: 1229 | B28: 4502608699 | C28: 0000027013 | D28: ZA00 | E28: 256855 | F28: ZAR | G28: 4502608718 | H28: 0000027013 | I28: ZA00 | J28: 280364 | K28: ZAR | L28: 4700406402 | M28: 0000027013 | N28: ZA00 | O28: 261396 | P28: ZAR | Q28: 4700406407 | R28: 0000027013 | S28: ZA00 | T28: 272820 | U28: ZAR | V28: 4700406412 | W28: 0000027013 | X28: ZA00 | Y28: 261396 | Z28: ZAR | AA28: 4700406415 | AB28: 0000027013 | AC28: ZA00 | AD28: 261396 | AE28: ZAR | AF28: 4700406422 | AG28: 0000027013 | AH28: ZA00 | AI28: 251084 | AJ28: USD
A29: 1245 | B29: 4700406987 | C29: 0000011471 | D29: G003 | E29: 37061 | F29: USD | G29: 4502609164 | H29: 0000011471 | I29: G003 | J29: 23588 | K29: USD | L29: 4700406980 | M29: 0000011471 | N29: G003 | O29: 23588 | P29: USD | Q29: 4700406981 | R29: 0000011471 | S29: G003 | T29: 23588 | U29: USD | V29: 4700406985 | W29: 0000011471 | X29: G003 | Y29: 23588 | Z29: USD | AA29: 4700406986 | AB29: 0000011471 | AC29: G003 | AD29: 23588 | AE29: USD | AF29: 4700406982 | AG29: 0000011471 | AH29: G003 | AI29: 23588 | AJ29: EUR
A30: 1252 | B30: 4700405858 | C30: 0000035214 | D30: TW00 | E30: 81794 | F30: TWD | G30: 4502608537 | H30: 0000035215 | I30: TW00 | J30: 195316 | K30: TWD | L30: 4700406000 | M30: 0000035210 | N30: TW00 | O30: 81837 | P30: TWD | Q30: 4700406062 | R30: 0000035210 | S30: TW00 | T30: 81794 | U30: TWD | V30: 4700406076 | W30: 0000035216 | X30: TW00 | Y30: 252552 | Z30: TWD | AA30: 4700406107 | AB30: 0000035215 | AC30: TW00 | AD30: 151915 | AE30: TWD | AF30: 4700406124 | AG30: 0000035216 | AH30: TW00 | AI30: 36335 | AJ30: USD
A31: 1253 | B31: 4700405642 | C31: 0000034501 | D31: KR00 | E31: 161411 | F31: KRW | G31: 4502608696 | H31: 0000034501 | I31: KR00 | J31: 254514 | K31: KRW | L31: 4700405744 | M31: 0000034501 | N31: KR00 | O31: 284227 | P31: KRW | Q31: 4700405743 | R31: 0000034501 | S31: KR00 | T31: 254514 | U31: KRW | V31: 4700405759 | W31: 0000034501 | X31: KR00 | Y31: 284225 | Z31: KRW | AA31: 4700405868 | AB31: 0000034501 | AC31: KR00 | AD31: 284843 | AE31: KRW | AF31: 4700405941 | AG31: 0000034501 | AH31: KR00 | AI31: 85372 | AJ31: CHF
A32: 1256 | B32: 4700405995 | C32: 0000039486 | D32: US00 | E32: 277823 | F32: USD | G32: 4502608548 | H32: 0000039486 | I32: US00 | J32: 277823 | K32: USD | L32: 4700406056 | M32: 0000039486 | N32: US00 | O32: 277823 | P32: USD | Q32: 4700406064 | R32: 0000039486 | S32: US00 | T32: 277823 | U32: USD | V32: 4700406073 | W32: 0000039486 | X32: US00 | Y32: 277823 | Z32: USD | AA32: 4700406090 | AB32: 0000039486 | AC32: US00 | AD32: 277823 | AE32: USD | AF32: 4700406117 | AG32: 0000039486 | AH32: US00 | AI32: 277823 | AJ32: USD
A33: 1270 | B33: 4700406184 | C33: 0000038125 | D33: TH00 | E33: 267944 | F33: THB | G33: 4502608631 | H33: 0000038106 | I33: TH00 | J33: 259647 | K33: THB | L33: 4700406248 | M33: 0000038110 | N33: TH00 | O33: 259647 | P33: THB | Q33: 4700406265 | R33: 0000038106 | S33: TH00 | T33: 267944 | U33: THB | V33: 4700406376 | W33: 0000038110 | X33: TH00 | Y33: 259647 | Z33: THB | AA33: 4700406401 | AB33: 0000038125 | AC33: TH00 | AD33: 246824 | AE33: THB | AF33: 4700406968 | AG33: 0000038106 | AH33: TH00 | AI33: 246824 | AJ33: THB
A34: 1275 | B34: 4700406300 | C34: 0000039900 | D34: D003 | E34: 35777 | F34: USD | G34: 4502608655 | H34: 0000039900 | I34: D003 | J34: 35777 | K34: USD | L34: 4700406302 | M34: 0000039900 | N34: D003 | O34: 244857 | P34: USD | Q34: 4700406305 | R34: 0000039900 | S34: D003 | T34: 280671 | U34: USD | V34: 4700406308 | W34: 0000039900 | X34: D003 | Y34: 280671 | Z34: USD | AA34: 4700406310 | AB34: 0000039900 | AC34: D003 | AD34: 280671 | AE34: USD | AF34: 4700406311 | AG34: 0000039900 | AH34: D003 | AI34: 280671 | AJ34: USD
A35: 1277 | B35: 4700406353 | C35: 0000037515 | D35: SG00 | E35: 235693 | F35: SGD | G35: 4502608671 | H35: 0000037515 | I35: SG00 | J35: 271443 | K35: SGD | L35: 4700406363 | M35: 0000037515 | N35: SG00 | O35: 248848 | P35: SGD | Q35: 4700406366 | R35: 0000037515 | S35: SG00 | T35: 270380 | U35: SGD | V35: 4700406369 | W35: 0000037515 | X35: SG00 | Y35: 261883 | Z35: SGD | AA35: 4700406405 | AB35: 0000037515 | AC35: SG00 | AD35: 128149 | AE35: SGD | AF35: 4700406404 | AG35: 0000037515 | AH35: SG00 | AI35: 233668 | AJ35: SGD
A36: 1279 | B36: 4700406518 | C36: 0000038406 | D36: PH00 | E36: 226160 | F36: PHP | G36: 4502608786 | H36: 0000038406 | I36: PH00 | J36: 256115 | K36: PHP | L36: 4700406515 | M36: 0000038406 | N36: PH00 | O36: 226160 | P36: PHP | Q36: 4700406516 | R36: 0000038406 | S36: PH00 | T36: 226160 | U36: PHP | V36: 4700406517 | W36: 0000038406 | X36: PH00 | Y36: 226160 | Z36: PHP | AA36: 4700406519 | AB36: 0000038406 | AC36: PH00 | AD36: 226160 | AE36: PHP | AF36: 4700406514 | AG36: 0000038406 | AH36: PH00 | AI36: 19323 | AJ36: EUR
A37: 1284 | B37: 4700407025 | C37: 0000048812 | D37: JO00 | E37: 267031 | F37: JOD | G37: 4502609240 | H37: 0000048812 | I37: JO00 | J37: 267031 | K37: JOD | L37: 4700407032 | M37: 0000048812 | N37: JO00 | O37: 267031 | P37: JOD | Q37: 4700407035 | R37: 0000048812 | S37: JO00 | T37: 267031 | U37: JOD | V37: 4700407040 | W37: 0000048812 | X37: JO00 | Y37: 267031 | Z37: JOD | AA37: 4700407041 | AB37: 0000048812 | AC37: JO00 | AD37: 267031 | AE37: JOD | AF37: 4700407045 | AG37: 0000048812 | AH37: JO00 | AI37: 258174 | AJ37: USD
A38: 1285 | B38: 4700406098 | C38: 0000038505 | D38: VN00 | E38: 235510 | F38: USD | G38: 4502608591 | H38: 0000038505 | I38: VN00 | J38: 235510 | K38: USD | L38: 4700406183 | M38: 0000038505 | N38: VN00 | O38: 235510 | P38: USD | Q38: 4700406219 | R38: 0000038505 | S38: VN00 | T38: 235510 | U38: USD | V38: 4700406232 | W38: 0000038505 | X38: VN00 | Y38: 235510 | Z38: USD | AA38: 4700406243 | AB38: 0000038505 | AC38: VN00 | AD38: 235510 | AE38: USD | AF38: 4700406246 | AG38: 0000038505 | AH38: VN00 | AI38: 235510 | AJ38: VND
A39: 1299 | B39: 4700405960 | C39: 0000023821 | D39: G003 | E39: 263180 | F39: GBP | G39: 4502608519 | H39: 0000023821 | I39: G003 | J39: 263180 | K39: GBP | L39: 4700406010 | M39: 0000023821 | N39: G003 | O39: 263180 | P39: GBP | Q39: 4700406023 | R39: 0000023821 | S39: G003 | T39: 263180 | U39: GBP | V39: 4700406034 | W39: 0000023821 | X39: G003 | Y39: 263180 | Z39: GBP | AA39: 4700406039 | AB39: 0000023821 | AC39: G003 | AD39: 263180 | AE39: GBP | AF39: 4700406041 | AG39: 0000023821 | AH39: G003 | AI39: 263180 | AJ39: GBP
A40: 1300 | B40: 4502608871 | C40: 0000037366 | D40: F002 | E40: 263861 | F40: MYR | G40: 4502608873 | H40: 0000037366 | I40: F002 | J40: 263861 | K40: MYR | L40: 4502608874 | M40: 0000037366 | N40: F002 | O40: 263861 | P40: MYR | Q40: 4700406700 | R40: 0000037366 | S40: F002 | T40: 278190 | U40: MYR | V40: 4700406702 | W40: 0000037366 | X40: F002 | Y40: 263861 | Z40: MYR | AA40: 4700406703 | AB40: 0000037366 | AC40: F002 | AD40: 263861 | AE40: MYR | AF40: 4700406704 | AG40: 0000037366 | AH40: F002 | AI40: 263861 | AJ40: MYR
A41: 1303 | B41: 4700406235 | C41: 0000010001 | D41: BE00 | E41: 228389 | F41: EUR | G41: 4502608629 | H41: 0000010001 | I41: BE00 | J41: 197638 | K41: EUR | L41: 4700406224 | M41: 0000010001 | N41: BE00 | O41: 197638 | P41: EUR | Q41: 4700406225 | R41: 0000010001 | S41: BE00 | T41: 197638 | U41: EUR | V41: 4700406234 | W41: 0000010001 | X41: BE00 | Y41: 197638 | Z41: EUR | AA41: 4700406233 | AB41: 0000010001 | AC41: BE00 | AD41: 197638 | AE41: EUR | AF41: 4700406227 | AG41: 0000010001 | AH41: BE00 | AI41: 197638 | AJ41: EUR
A42: 1311 | B42: 4700406796 | C42: 0000024314 | D42: RUP3 | E42: 15251 | F42: RUB | G42: 4700406798 | H42: 0000024314 | I42: RUP3 | J42: 14761 | K42: RUB | L42: 4700406799 | M42: 0000024314 | N42: RUP3 | O42: 135780 | P42: RUB | Q42: 4700406800 | R42: 0000024314 | S42: RUP3 | T42: 14761 | U42: RUB | V42: 4700406801 | W42: 0000024314 | X42: RUP3 | Y42: 14761 | Z42: RUB | AA42: 4700406802 | AB42: 0000024314 | AC42: RUP3 | AD42: 15251 | AE42: RUB | AF42: 4700406803 | AG42: 0000024314 | AH42: RUP3 | AI42: 15251 | AJ42: RUB
A43: 1312 | B43: 4700405784 | C43: 0000033727 | D43: M002 | E43: 198111 | F43: RSD | G43: 4502608447 | H43: 0000033727 | I43: M002 | J43: 198111 | K43: RSD | L43: 4700405786 | M43: 0000033727 | N43: M002 | O43: 198111 | P43: RSD | Q43: 4700405787 | R43: 0000033727 | S43: M002 | T43: 198111 | U43: RSD | V43: 4700405788 | W43: 0000033727 | X43: M002 | Y43: 198111 | Z43: RSD | AA43: 4700405789 | AB43: 0000033727 | AC43: M002 | AD43: 198111 | AE43: RSD | AF43: 4700405783 | AG43: 0000033727 | AH43: M002 | AI43: 132025 | AJ43: EUR
A44: 1317 | B44: 4700406147 | C44: 0000050269 | D44: NGP1 | E44: 276536 | F44: NGN | G44: 4700406148 | H44: 0000050269 | I44: NGP1 | J44: 276536 | K44: NGN | L44: 4700406154 | M44: 0000050269 | N44: NGP1 | O44: 276536 | P44: NGN | Q44: 4700406157 | R44: 0000050269 | S44: NGP1 | T44: 276536 | U44: NGN | V44: 4700406160 | W44: 0000050269 | X44: NGP1 | Y44: 276536 | Z44: NGN | AA44: 4700406166 | AB44: 0000050269 | AC44: NGP1 | AD44: 276536 | AE44: NGN | AF44: 4700406979 | AG44: 0000050247 | AH44: NG00 | AI44: 276536 | AJ44: NGN
A45: 1318 | B45: 4700406055 | C45: 0000050012 | D45: BY00 | E45: 278091 | F45: BYN | G45: 4700406833 | H45: 0000050012 | I45: BY00 | J45: 278091 | K45: EUR | L45: 4700406922 | M45: 0000050012 | N45: BY00 | O45: 278261 | P45: BYN | Q45: 4700406923 | R45: 0000050012 | S45: BY00 | T45: 278287 | U45: BYN | V45: 4700406924 | W45: 0000050012 | X45: BY00 | Y45: 278204 | Z45: BYN | AA45: 4700406925 | AB45: 0000050012 | AC45: BY00 | AD45: 278024 | AE45: BYN | AF45: 4700406833 | AG45: 0000050012 | AH45: BY00 | AI45: 278091 | AJ45: EUR
A46: 1322 | B46: 4700406897 | C46: 0000046312 | D46: M013 | E46: 254069 | F46: USD | G46: 4502609255 | H46: 0000046312 | I46: M013 | J46: 254069 | K46: USD | L46: 4700407034 | M46: 0000046312 | N46: M013 | O46: 254069 | P46: USD | Q46: 4700407037 | R46: 0000046312 | S46: M013 | T46: 254069 | U46: USD | V46: 4700407250 | W46: 0000046312 | X46: M013 | Y46: 254069 | Z46: USD | AA46: 4700407254 | AB46: 0000046312 | AC46: M013 | AD46: 254069 | AE46: USD | AF46: 4700407042 | AG46: 0000046312 | AH46: M013 | AI46: 279306 | AJ46: MXN
... A48: 1325 | B48: 4700407140 | C48: 0000048778 | D48: JOP1 | E48: 265606 | F48: JOD | G48: 4502609322 | H48: 0000048778 | I48: JOP1 | J48: 265606 | K48: JOD | L48: 4700407150 | M48: 0000048778 | N48: JOP1 | O48: 265606 | P48: JOD | Q48: 4700407161 | R48: 0000048778 | S48: JOP1 | T48: 265606 | U48: JOD | V48: 4700407163 | W48: 0000048778 | X48: JOP1 | Y48: 265606 | Z48: JOD | AA48: 4700407165 | AB48: 0000048778 | AC48: JOP1 | AD48: 265606 | AE48: JOD | AF48: 4700407168 | AG48: 0000048778 | AH48: JOP1 | AI48: 114319 | AJ48: USD
A49: 1327 | B49: 4700406186 | C49: 0000046421 | D49: MWP1 | E49: 214942 | F49: MWK | G49: 4700406188 | H49: 0000046409 | I49: MWP1 | J49: 214942 | K49: MWK | L49: 4700406187 | M49: 0000046421 | N49: MWP1 | O49: 232047 | P49: MWK | Q49: 4700406185 | R49: 0000046421 | S49: MWP1 | T49: 214924 | U49: MWK | V49: 4700406092 | W49: 0000046421 | X49: MWP1 | Y49: 215120 | Z49: MWK | AA49: 4700406091 | AB49: 0000046421 | AC49: MWP1 | AD49: 214942 | AE49: MWK | AF49: 4700406126 | AG49: 0000046421 | AH49: MWP1 | AI49: 215081 | AJ49: MWK
A50: 1328 | B50: 4700406006 | C50: 0000046500 | D50: ZMP1 | E50: 226864 | F50: ZMW | G50: 4502608659 | H50: 0000046533 | I50: ZMP1 | J50: 266564 | K50: ZMW | L50: 4700406309 | M50: 0000046533 | N50: ZMP1 | O50: 266564 | P50: ZMW | Q50: 4700406306 | R50: 0000046533 | S50: ZMP1 | T50: 266564 | U50: ZMW | V50: 4700406304 | W50: 0000046533 | X50: ZMP1 | Y50: 266564 | Z50: ZMW | AA50: 4700406307 | AB50: 0000046533 | AC50: ZMP1 | AD50: 266564 | AE50: ZMW | AF50: 4700406287 | AG50: 0000046533 | AH50: ZMP1 | AI50: 266564 | AJ50: USD
A51: 1334 | B51: 4700406338 | C51: 0000046700 | D51: BRP2 | E51: 216795 | F51: BRL | G51: 4700406339 | H51: 0000046700 | I51: BRP2 | J51: 216795 | K51: BRL | L51: 4700406340 | M51: 0000046700 | N51: BRP2 | O51: 216795 | P51: BRL | Q51: 4700406341 | R51: 0000046700 | S51: BRP2 | T51: 216795 | U51: BRL | V51: 4700406342 | W51: 0000046700 | X51: BRP2 | Y51: 216795 | Z51: BRL | AA51: 4700406346 | AB51: 0000046700 | AC51: BRP2 | AD51: 216795 | AE51: BRL | AF51: 4700406347 | AG51: 0000046700 | AH51: BRP2 | AI51: 216795 | AJ51: BRL
A52: 1335 | B52: 4700405809 | C52: 0000050155 | D52: HR00 | E52: 276890 | F52: HRK | G52: 4502608448 | H52: 0000050155 | I52: HR00 | J52: 276890 | K52: HRK | L52: 4700405806 | M52: 0000050155 | N52: HR00 | O52: 276890 | P52: HRK | Q52: 4700405807 | R52: 0000050155 | S52: HR00 | T52: 276890 | U52: HRK | V52: 4700405808 | W52: 0000050155 | X52: HR00 | Y52: 276890 | Z52: HRK | AA52: 4700405810 | AB52: 0000050155 | AC52: HR00 | AD52: 276890 | AE52: HRK | AF52: 4700405811 | AG52: 0000050155 | AH52: HR00 | AI52: 276890 | AJ52: HRK
A53: 1341 | B53: 4700406012 | C53: 0000049078 | D53: MA00 | E53: 266114 | F53: MAD | G53: 4502608568 | H53: 0000049078 | I53: MA00 | J53: 266114 | K53: MAD | L53: 4700406171 | M53: 0000049077 | N53: MA00 | O53: 266114 | P53: MAD | Q53: 4700406181 | R53: 0000049077 | S53: MA00 | T53: 266114 | U53: MAD | V53: 4700406201 | W53: 0000049077 | X53: MA00 | Y53: 266114 | Z53: MAD | AA53: 4700406205 | AB53: 0000049077 | AC53: MA00 | AD53: 266114 | AE53: MAD | AF53: 4700406213 | AG53: 0000049077 | AH53: MA00 | AI53: 266114 | AJ53: MAD
A54: 1342 | B54: 4700405601 | C54: 0000046900 | D54: GE00 | E54: 212851 | F54: GEL | G54: 4502608542 | H54: 0000046901 | I54: GE00 | J54: 213542 | K54: GEL | L54: 4700405634 | M54: 0000046900 | N54: GE00 | O54: 212851 | P54: GEL | Q54: 4700405644 | R54: 0000046900 | S54: GE00 | T54: 212851 | U54: GEL | V54: 4700405669 | W54: 0000046900 | X54: GE00 | Y54: 212851 | Z54: GEL | AA54: 4700405675 | AB54: 0000046900 | AC54: GE00 | AD54: 212851 | AE54: GEL | AF54: 4700406015 | AG54: 0000046952 | AH54: AZ00 | AI54: 212605 | AJ54: AZN
A55: 1348 | B55: 4700406240 | C55: 0000046160 | D55: TZP2 | E55: 205196 | F55: TZS | G55: 4700406263 | H55: 0000046160 | I55: TZP2 | J55: 272869 | K55: TZS | L55: 4700406271 | M55: 0000046160 | N55: TZP2 | O55: 272869 | P55: TZS | Q55: 4700406279 | R55: 0000046160 | S55: TZP2 | T55: 205196 | U55: TZS | V55: 4700406291 | W55: 0000046160 | X55: TZP2 | Y55: 205196 | Z55: TZS | AA55: 4700406285 | AB55: 0000046160 | AC55: TZP2 | AD55: 272869 | AE55: TZS | AF55: 4700406289 | AG55: 0000046160 | AH55: TZP2 | AI55: 205196 | AJ55: USD
A56: 1359 | B56: 4700405958 | C56: 0000047569 | D56: TWP2 | E56: 252552 | F56: TWD | G56: 4502608508 | H56: 0000047569 | I56: TWP2 | J56: 81837 | K56: TWD | L56: 4700405966 | M56: 0000047569 | N56: TWP2 | O56: 246346 | P56: TWD | Q56: 4700405975 | R56: 0000047569 | S56: TWP2 | T56: 246346 | U56: TWD | V56: 4700405988 | W56: 0000047569 | X56: TWP2 | Y56: 53741 | Z56: TWD | AA56: 4700405996 | AB56: 0000047569 | AC56: TWP2 | AD56: 266087 | AE56: TWD | AF56: 4700405999 | AG56: 0000047569 | AH56: TWP2 | AI56: 235506 | AJ56: TWD
A57: 1363 | B57: 4700405821 | C57: 0000050049 | D57: AM00 | E57: 275340 | F57: AMD | G57: 4700405824 | H57: 0000050049 | I57: AM00 | J57: 275340 | K57: AMD | L57: 4700405826 | M57: 0000050049 | N57: AM00 | O57: 275340 | P57: AMD | Q57: 4700405825 | R57: 0000050049 | S57: AM00 | T57: 275340 | U57: AMD | V57: 4700405827 | W57: 0000050049 | X57: AM00 | Y57: 275340 | Z57: AMD | AA57: 4700405828 | AB57: 0000050049 | AC57: AM00 | AD57: 275340 | AE57: AMD | AF57: 4700405822 | AG57: 0000050049 | AH57: AM00 | AI57: 12056 | AJ57: USD
A58: 1364 | B58: 4700405912 | C58: 0000047531 | D58: M018 | E58: 251905 | F58: EUR | G58: 4502608512 | H58: 0000047513 | I58: LV00 | J58: 194398 | K58: EUR | L58: 4700406009 | M58: 0000047495 | N58: LT00 | O58: 105657 | P58: EUR | Q58: 4700406025 | R58: 0000047507 | S58: EE00 | T58: 221671 | U58: EUR | V58: 4700406045 | W58: 0000047331 | X58: LV00 | Y58: 106036 | Z58: EUR | AA58: 4700406048 | AB58: 0000047501 | AC58: M018 | AD58: 221587 | AE58: EUR | AF58: 4700406051 | AG58: 0000047512 | AH58: LT00 | AI58: 221587 | AJ58: EUR
A59: 1368 | B59: 4700406838 | C59: 0000048736 | D59: E003 | E59: 264623 | F59: LBP | G59: 4700406436 | H59: 0000048736 | I59: E003 | J59: 259546 | K59: LBP | L59: 4700406437 | M59: 0000048736 | N59: E003 | O59: 259586 | P59: USD | Q59: 4700406840 | R59: 0000048736 | S59: E003 | T59: 264623 | U59: LBP | V59: 4700406841 | W59: 0000048736 | X59: E003 | Y59: 259546 | Z59: LBP | AA59: 4700406844 | AB59: 0000048736 | AC59: E003 | AD59: 185970 | AE59: LBP | AF59: 4700406834 | AG59: 0000048736 | AH59: E003 | AI59: 185970 | AJ59: USD
A60: 1370 | B60: 4700405820 | C60: 0000013789 | D60: G001 | E60: 135677 | F60: EUR | G60: 4502608454 | H60: 0000050845 | I60: US00 | J60: 281537 | K60: USD | L60: 4700406292 | M60: 0000050845 | N60: US00 | O60: 217543 | P60: USD | Q60: 4700406465 | R60: 0000050845 | S60: US00 | T60: 281792 | U60: USD | V60: 4700406299 | W60: 0000050845 | X60: US00 | Y60: 217543 | Z60: USD | AA60: 4700406303 | AB60: 0000050845 | AC60: US00 | AD60: 281746 | AE60: USD | AF60: 4700406313 | AG60: 0000050845 | AH60: US00 | AI60: 262282 | AJ60: USD
A61: 1373 | B61: 4700407549 | C61: 0000049807 | D61: BR00 | E61: 236822 | F61: BRL | G61: 4700407550 | H61: 0000049807 | I61: BR00 | J61: 246307 | K61: BRL | L61: 4700407552 | M61: 0000049807 | N61: BR00 | O61: 228816 | P61: BRL | Q61: 4700407553 | R61: 0000049807 | S61: BR00 | T61: 236822 | U61: BRL | V61: 4700407554 | W61: 0000049807 | X61: BR00 | Y61: 216975 | Z61: BRL | AA61: 4700407555 | AB61: 0000049807 | AC61: BR00 | AD61: 227213 | AE61: BRL | AF61: 4700407556 | AG61: 0000049807 | AH61: BR00 | AI61: 235646 | AJ61: USD
A62: 1394 | B62: 4502609351 | C62: 0000050401 | D62: G002 | E62: 269067 | F62: CNY | G62: 4502609358 | H62: 0000050401 | I62: G002 | J62: 269067 | K62: CNY | L62: 4502609359 | M62: 0000050401 | N62: G002 | O62: 269067 | P62: CNY | Q62: 4502609360 | R62: 0000050401 | S62: G002 | T62: 269067 | U62: CNY | V62: 4502609362 | W62: 0000050401 | X62: G002 | Y62: 269067 | Z62: CNY | AA62: 4502609364 | AB62: 0000050401 | AC62: G002 | AD62: 269067 | AE62: CNY | AF62: 4502609365 | AG62: 0000050401 | AH62: G002 | AI62: 269067 | AJ62: USD
A63: 1799 | B63: 4700406910 | C63: 0000016147 | D63: G006 | E63: 37052 | F63: USD | G63: 4502609047 | H63: 0000016147 | I63: G006 | J63: 36856 | K63: USD | L63: 4700406912 | M63: 0000016147 | N63: G006 | O63: 36856 | P63: USD | Q63: 4700406913 | R63: 0000016147 | S63: G006 | T63: 37052 | U63: USD | V63: 4700406914 | W63: 0000016147 | X63: G006 | Y63: 36856 | Z63: USD | AA63: 4700406915 | AB63: 0000016147 | AC63: G006 | AD63: 37052 | AE63: USD | AF63: 4700406917 | AG63: 0000016147 | AH63: G006 | AI63: 37052 | AJ63: CHF
A64: 1800 | B64: 4700407183 | C64: 0000023431 | D64: LB00 | E64: 37061 | F64: USD | G64: 4502609343 | H64: 0000023431 | I64: LB00 | J64: 220234 | K64: USD | L64: 4700407184 | M64: 0000023431 | N64: LB00 | O64: 220234 | P64: AED | Q64: 4700407185 | R64: 0000023431 | S64: LB00 | T64: 220234 | U64: USD | V64: 4700407186 | W64: 0000023431 | X64: LB00 | Y64: 220234 | Z64: USD | AA64: 4700407187 | AB64: 0000023431 | AC64: LB00 | AD64: 220234 | AE64: USD | AF64: 4700407188 | AG64: 0000023431 | AH64: LB00 | AI64: 220234 | AJ64: EUR
A65: 1925 | B65: 4700406521 | C65: 0000048469 | D65: PHP5 | E65: 252146 | F65: PHP | G65: 4502608787 | H65: 0000048469 | I65: PHP5 | J65: 252146 | K65: PHP | L65: 4700406522 | M65: 0000048469 | N65: PHP5 | O65: 252146 | P65: PHP | Q65: 4700406524 | R65: 0000048469 | S65: PHP5 | T65: 252146 | U65: PHP | V65: 4700406525 | W65: 0000048469 | X65: PHP5 | Y65: 252146 | Z65: PHP | AA65: 4700406523 | AB65: 0000048469 | AC65: PHP5 | AD65: 252146 | AE65: PHP | AF65: 4700406520 | AG65: 0000048469 | AH65: PHP5 | AI65: 19323 | AJ65: EUR
A66: 2101 | B66: 4700405957 | C66: 0000042997 | D66: G002 | E66: 280669 | F66: GBP | G66: 4502608511 | H66: 0000042997 | I66: G002 | J66: 280669 | K66: GBP | L66: 4700406007 | M66: 0000043009 | N66: GB00 | O66: 280669 | P66: GBP | Q66: 4700406036 | R66: 0000042997 | S66: G002 | T66: 280669 | U66: GBP | V66: 4700406032 | W66: 0000042997 | X66: G002 | Y66: 280669 | Z66: GBP | AA66: 4700406031 | AB66: 0000042997 | AC66: G002 | AD66: 280669 | AE66: GBP | AF66: 4700406040 | AG66: 0000042997 | AH66: G002 | AI66: 280669 | AJ66: GBP
A67: 2102 | B67: 4700406696 | C67: 0000043958 | D67: IE00 | E67: 71543 | F67: EUR | G67: 4700406675 | H67: 0000043958 | I67: IE00 | J67: 71543 | K67: EUR | L67: 4700406676 | M67: 0000043958 | N67: IE00 | O67: 71543 | P67: EUR | Q67: 4700406677 | R67: 0000043958 | S67: IE00 | T67: 71543 | U67: EUR | V67: 4700406678 | W67: 0000043958 | X67: IE00 | Y67: 71543 | Z67: EUR | AA67: 4700406679 | AB67: 0000043958 | AC67: IE00 | AD67: 71543 | AE67: EUR | AF67: 4700406952 | AG67: 0000043925 | AH67: IE00 | AI67: 71543 | AJ67: EUR
A68: 2126 | B68: 4502608585 | C68: 0000044123 | D68: ESP2 | E68: 26048 | F68: EUR | G68: 4502608616 | H68: 0000044123 | I68: ESP2 | J68: 26048 | K68: EUR | L68: 4700406808 | M68: 0000044123 | N68: ESP2 | O68: 119973 | P68: EUR | Q68: 4700406218 | R68: 0000044123 | S68: ESP2 | T68: 26048 | U68: EUR | V68: 4502608701 | W68: 0000044123 | X68: ESP2 | Y68: 119973 | Z68: EUR | AA68: 4502608724 | AB68: 0000044123 | AC68: ESP2 | AD68: 119973 | AE68: EUR | AF68: 4700406812 | AG68: 0000044123 | AH68: ESP2 | AI68: 119973 | AJ68: USD
A69: 2154 | B69: 4700406955 | C69: 0000041176 | D69: KZ00 | E69: 247535 | F69: KZT | G69: 4502609123 | H69: 0000041176 | I69: KZ00 | J69: 196215 | K69: KZT | L69: 4700407014 | M69: 0000041176 | N69: KZ00 | O69: 163347 | P69: KZT | Q69: 4700407012 | R69: 0000041176 | S69: KZ00 | T69: 252498 | U69: KZT | V69: 4700407018 | W69: 0000041176 | X69: KZ00 | Y69: 185030 | Z69: KZT | AA69: 4700407026 | AB69: 0000041163 | AC69: KZ00 | AD69: 271588 | AE69: KZT | AF69: 4700407027 | AG69: 0000041359 | AH69: KZP2 | AI69: 196132 | AJ69: KZT
A70: 2156 | B70: 4700405705 | C70: 0000040881 | D70: PT00 | E70: 266580 | F70: EUR | G70: 4502608439 | H70: 0000040881 | I70: PT00 | J70: 273413 | K70: EUR | L70: 4700406214 | M70: 0000040881 | N70: PT00 | O70: 200656 | P70: EUR | Q70: 4700405761 | R70: 0000040881 | S70: PT00 | T70: 266580 | U70: EUR | V70: 4700405775 | W70: 0000040881 | X70: PT00 | Y70: 200656 | Z70: EUR | AA70: 4700405782 | AB70: 0000040881 | AC70: PT00 | AD70: 200656 | AE70: EUR | AF70: 4700405860 | AG70: 0000040881 | AH70: PT00 | AI70: 200656 | AJ70: EUR
A71: 2180 | B71: 4700406344 | C71: 0000044315 | D71: PL00 | E71: 183896 | F71: PLN | G71: 4502608679 | H71: 0000044309 | I71: PL00 | J71: 282597 | K71: PLN | L71: 4700406149 | M71: 0000044460 | N71: PLP2 | O71: 224360 | P71: PLN | Q71: 4700406403 | R71: 0000044398 | S71: PL00 | T71: 259198 | U71: PLN | V71: 4700406420 | W71: 0000044309 | X71: PL00 | Y71: 208008 | Z71: PLN | AA71: 4700406443 | AB71: 0000044389 | AC71: PL00 | AD71: 157230 | AE71: PLN | AF71: 4700406455 | AG71: 0000044389 | AH71: PL00 | AI71: 157230 | AJ71: EUR
A72: 2300 | B72: 4700405595 | C72: 0000044580 | D72: SE00 | E72: 31885 | F72: SEK | G72: 4502608382 | H72: 0000044580 | I72: SE00 | J72: 182638 | K72: SEK | L72: 4700405674 | M72: 0000044580 | N72: SE00 | O72: 182638 | P72: SEK | Q72: 4700405683 | R72: 0000044580 | S72: SE00 | T72: 182638 | U72: SEK | V72: 4700405733 | W72: 0000044580 | X72: SE00 | Y72: 210398 | Z72: SEK | AA72: 4700405742 | AB72: 0000044580 | AC72: SE00 | AD72: 210398 | AE72: SEK | AF72: 4700405749 | AG72: 0000044580 | AH72: SE00 | AI72: 210398 | AJ72: SEK
A73: 2301 | B73: 4502608398 | C73: 0000044862 | D73: G002 | E73: 166253 | F73: EUR | G73: 4502608409 | H73: 0000044862 | I73: G002 | J73: 126365 | K73: EUR | L73: 4502608414 | M73: 0000044862 | N73: G002 | O73: 79910 | P73: EUR | Q73: 4700407447 | R73: 0000044895 | S73: AT00 | T73: 79910 | U73: EUR | V73: 4502608424 | W73: 0000044862 | X73: G002 | Y73: 79910 | Z73: EUR | AA73: 4502608430 | AB73: 0000044862 | AC73: G002 | AD73: 77947 | AE73: EUR | AF73: 4700407448 | AG73: 0000044895 | AH73: AT00 | AI73: 192772 | AJ73: GBP
A74: 2302 | B74: 4700405943 | C74: 0000048078 | D74: DK00 | E74: 253279 | F74: DKK | G74: 4502608506 | H74: 0000048078 | I74: DK00 | J74: 253279 | K74: DKK | L74: 4700405974 | M74: 0000048078 | N74: DK00 | O74: 253279 | P74: DKK | Q74: 4700405989 | R74: 0000048078 | S74: DK00 | T74: 253279 | U74: DKK | V74: 4700406001 | W74: 0000048078 | X74: DK00 | Y74: 253279 | Z74: DKK | AA74: 4700406005 | AB74: 0000048078 | AC74: DK00 | AD74: 253279 | AE74: DKK | AF74: 4700406014 | AG74: 0000048078 | AH74: DK00 | AI74: 253279 | AJ74: DKK
A75: 2316 | B75: 4700405795 | C75: 0000048993 | D75: SK00 | E75: 269441 | F75: EUR | G75: 4502608446 | H75: 0000048993 | I75: SK00 | J75: 269441 | K75: EUR | L75: 4700405791 | M75: 0000048993 | N75: SK00 | O75: 266008 | P75: EUR | Q75: 4700405794 | R75: 0000048993 | S75: SK00 | T75: 266039 | U75: EUR | V75: 4700405792 | W75: 0000048993 | X75: SK00 | Y75: 266008 | Z75: EUR | AA75: 4700405793 | AB75: 0000048993 | AC75: SK00 | AD75: 266039 | AE75: EUR | AF75: 4700405790 | AG75: 0000048993 | AH75: SK00 | AI75: 140708 | AJ75: CZK
A76: 2322 | B76: 4700405959 | C76: 0000041708 | D76: HU00 | E76: 94281 | F76: HUF | G76: 4502608540 | H76: 0000041710 | I76: HU00 | J76: 94281 | K76: HUF | L76: 4700406044 | M76: 0000041704 | N76: HU00 | O76: 93476 | P76: HUF | Q76: 4700406046 | R76: 0000041721 | S76: HU00 | T76: 93476 | U76: HUF | V76: 4700405766 | W76: 0000041704 | X76: HU00 | Y76: 93476 | Z76: HUF | AA76: 4700405981 | AB76: 0000041721 | AC76: HU00 | AD76: 94281 | AE76: HUF | AF76: 4700405986 | AG76: 0000041708 | AH76: HU00 | AI76: 234353 | AJ76: EUR
A77: 2345 | B77: 4700407478 | C77: 0000045622 | D77: AT00 | E77: 166253 | F77: EUR | G77: 4502609500 | H77: 0000045622 | I77: AT00 | J77: 166253 | K77: EUR | L77: 4700407479 | M77: 0000045622 | N77: AT00 | O77: 166253 | P77: EUR | Q77: 4700407480 | R77: 0000045622 | S77: AT00 | T77: 166253 | U77: EUR | V77: 4700407477 | W77: 0000045622 | X77: AT00 | Y77: 79910 | Z77: EUR | AA77: 4700407498 | AB77: 0000045622 | AC77: AT00 | AD77: 79910 | AE77: EUR | AF77: 4700407481 | AG77: 0000045622 | AH77: AT00 | AI77: 205889 | AJ77: USD

Sheet Asset numbers
B1: 1 - Capitalised Contract | C1: 2 - Low Value Contract | D1: 3 - Short Term Contract | E1: 4 - Prepaid Contract | F1: 5 - Contract Extension | G1: 6 - Contract Termination | H1: 7 - Capitalised contract - foreign currency
A2: 1011 | B2: 1020000000 | C2: N/A | D2: N/A | E2: 1050000000 | F2: 1070000000 | G2: 1040000000 | H2: 1060000000
A3: 1100 | B3: 1020000001 | C3: N/A | D3: N/A | E3: 1050000000 | F3: 1070000034 | G3: 1040000015 | H3: 1060000005
A4: 1104 | B4: 1020000001 | C4: N/A | D4: N/A | E4: 1050000001 | F4: 1070000006 | G4: 1040000001 | H4: 1060000001
A5: 1106 | B5: 1020000038 | C5: N/A | D5: N/A | E5: 1050000000 | F5: 1070000062 | G5: 1040000000 | H5: 1060000004
A6: 1107 | B6: 1020000004 | C6: N/A | D6: N/A | E6: 1050000000 | F6: 1070000193 | G6: 1040000000 | H6: 1060000000
A7: 1114 | B7: 1020000001 | C7: N/A | D7: N/A | E7: 1050000000 | F7: 1070000048 | G7: 1040000016 | H7: 1060000000
A8: 1116 | B8: 1020000007 | C8: N/A | D8: N/A | E8: 1050000000 | F8: 1070000075 | G8: 1040000000 | H8: 1060000000
A9: 1118 | B9: 1020000012 | C9: N/A | D9: N/A | E9: 1050000000 | F9: 1070000110 | G9: 1040000000 | H9: 1060000000
A10: 1129 | B10: 1020000020 | C10: N/A | D10: N/A | E10: 1050000000 | F10: 1070000000 | G10: 1040000005 | H10: 1060000027
A11: 1143 | B11: 1020000041 | C11: N/A | D11: N/A | E11: 1050000000 | F11: 1070000000 | G11: 1040000000 | H11: 1060000004
A12: 1159 | B12: 1020000007 | C12: N/A | D12: N/A | E12: 1050000000 | F12: 1070000041 | G12: 1040000000 | H12: 1060000000
A13: 1169 | B13: 1020000003 | C13: N/A | D13: N/A | E13: 1050000000 | F13: 1070000089 | G13: 1040000000 | H13: 1060000000
... A75: 2345 | B75: 1020000052 | C75: N/A | D75: N/A | E75: 1050000000 | F75: 1070000019 | G75: 1040000000 | H75: 1060000000

Sheet SAP Transaction Guidance
A1: Guidance - SAP transaction FAGLL03
A3: Adding multiple GL accounts
A5: Enter SAP transaction code: | B5: FAGLL03
A6: Populate all the GL accounts by clicking:
A8: Populate all the GL account in the below fields:
A34: Select the green tick once all GL accounts are populated
A36: Then execute the transaction using the button on the far right bottom:
A40: Enter unique AG and PO number
A42: In order to filter on specific contracts using their AG number or PO number follow the below steps:
A44: Enter SAP transaction code: | B44: FAGLL03
A45: Select the custom Selections from the tops of the screen:
A52: Go to the G/L Account Line Items folder on the left hand side and expand it.
A53: Then double click on the Assignment field and you will notice it pop up on the right.
A54: Populate the AG numbers and PO number in this selection
A97: Then Save the changes
A101: Changing layout (e.g. custom report fields Assignment, Reference, Profit center etc.)
A103: To change a layout when using transaction FAGLL03 follow the below steps
A105: Once you have exectued the report select the option highlighted below:
A113: The below box will pop up and you can select any of the fields from the Hidden fields column and move them to the left by clicking button
A156: Once you have chosen all the fields you require press the copy button:
A158: Your fields will now be visible in your report.
A162: Checking asset movement types
A164: Enter SAP transaction code: | B164: AW01N
A165: Populate the company code and asset number. Then press enter
A166: Change the fiscal year to: | B166: 2019
A168: At the bottom under the transactions double click on the field under the 'Ttype' heading:
A213: This takes you to the document; then click on the line with the asset number:
A239: Select the 'more' button
A281: You will then be able to see the transaction type:

Sheet UAT Test Scripts
A1: SCENARIO | B1: STEP NAME | C1: DESCRIPTION | D1: EXPECTED RESULT
A2: SCENARIO 1
A4: 01. Scenarios & Results excel file attached (refers to this file)
A6: 02. Create Purchase Requisition
A7: 1 - Capitalised Contract | B7: 00 - Open file attached in the first test script 01 | C7: Open file attached in the first test script 01. Refer to "Scenarios" tab for details to create the PR for this contract.
A8: 1 - Capitalised Contract | B8: 01 - Enter requisition details in MyShop | C8: - Input requirements into Free-text field in MyShop - Select a random local currency Vendor used currently for Leasing (ZSRM PO must be created, no invoice plan) - Select a random cost center used currently for Leasing - Select the correct Material Group relating to Fixed leasing costs as per scenario details - Select Quantity (= no. of payments) & Price (= payment amount) - Add to shopping cart | D8: - Free-text, fixed leasing material group, cost center & payment details are input correctly
A9: 1 - Capitalised Contract | B9: 02 - Finalize PR | C9: - Ensure the right Material Group and GL account assignment (243032) is selected - PR is sent to Procurement for approval - Record PR number in HPALM Result Field | D9: - Correct fixed leasing material group can be selected - GL account assignment is defaulted to 243032 - PR number recorded in Result Field
A10: 1 - Capitalised Contract | B10: 03 - PR Approval | C10: - Procurement approves PR - Approve PR and ensure it follows the defined approval hierarchy | D10: - PR is approved - PR routing follows the right approval cycle
A12: 03. Create Purchase Order
A13: 1 - Capitalised Contract | B13: 00 - Open file attached in the first test script 01 | C13: Open file attached in the first test script 01. Refer to "Scenarios" tab for details to create the PO for this contract.
A14: 1 - Capitalised Contract | B14: 01 - PO Creation | C14: - PR is reviewed and converted to a PO (ZSRM) with all the necessary items (material group, vendor, cost center, quantity, price, account assignment 243032, GR flag unticked) - PO created and saved in SAP - Record PO number in HPALM Result Field | D14: - PR converted to PO with correct material group, vendor, cost center, quantity, price, account assignment 243032 and GR flag unticked - PO created and saved in SAP - PO number recorded in HPALM Result field
A15: 1 - Capitalised Contract | B15: 02 - GR flag removed (2 way match) | C15: - Verify the system has automatically removed the GR flag for Fixed Leasing material group | D15: - GR flag automatically removed
A16: 1 - Capitalised Contract | B16: 03 - PO Tax code (VAT) | C16: - Ensure that a "fully recoverable VAT" tax code has been selected | D16: - "Fully recoverable VAT" tax code has been selected for this scenario
A18: 04.a Create contract in Nakisa - Upload Masterdata (Lease Accounting Team - detailed test scripts not shown below)
A20: 04.b Create contract in Nakisa (Lease Accounting Team - detailed test scripts not shown below)
A22: 05. Process Invoice via MIRO
A23: 1 - Capitalised Contract | B23: 00 - Open Excel file attached in the first test script 01 | C23: Open Excel file attached in the first test script 01. Refer to "Scenarios" tab for details to create the Invoice for this contract. Refer to the "PO numbers" tab for the corresponding PO number for this Scenario / Entity
A24: 1 - Capitalised Contract | B24: 01 - Invoice posting (P7) | C24: - Post Invoice via MIRO (Input details are included in the attached file, "Scenarios" tab). Please use the specific PO number, Date, Qty & Price for this scenario as per "Invoice 1 details" - PO numbers for each scenario can be found on the "PO number" tab | D24: - Book the invoice without any errors. Confirm DR posting is made to GL 243032 - Vendor invoice with reference to PO is posted according to the input data - Recoverable Input VAT not posted to GL 243032
A25: 1 - Capitalised Contract | B25: 02 - 2 way match (No GR) - (P7) | C25: - Check that there are no errors/warnings stating that a GR needs to be booked - Ensure there are no bookings to the GRIR accounts | D25: - No GR errors/warnings - No bookings the in GRIR account
A26: 1 - Capitalised Contract | B26: 03 - Invoice posting (P8) | C26: - Post Invoice via MIRO (Input details are included in the attached file, "Scenarios" tab). Please use the specific PO number, Date, Qty & Price for this scenario as per "Invoice 2 details" - PO numbers for each scenario can be found on the "PO number" tab | D26: - Book the invoice without any errors. Confirm DR posting is made to GL 243032 - Vendor invoice with reference to PO is posted according to the input data - Recoverable Input VAT not posted to GL 243032
A27: 1 - Capitalised Contract | B27: 04 - 2 way match (No GR) - (P8) | C27: - Check that there are no errors/warnings stating that a GR needs to be booked - Ensure there are no bookings to the GRIR accounts | D27: - No GR errors/warnings - No bookings the in GRIR account
A29: 06.a FI validation (IFRS 16 Accounting Approach)
A30: 1 - Capitalised Contract | B30: 01 - Scenario Postings | C30: Open file attached in the first test script 01 for details of this E2E scenario and expected postings. All entities should validate IFRS 16 postings in the IFRS ledger (0L). For the STAT and TAX ledger validation, please refer to the "Entity setup" tab for details of your entity's accounting approach. If IFRS 16 is followed for ST / TX, please also validate postings in those ledgers. In this file you will find: - PO numbers, cost centers, profit centers and Vendor numbers related to this contract - Guidance on how to extract the relevant postings from SAP - S/4 Masterdata related to Leasing
A31: 1 - Capitalised Contract | B31: 01a - Extract SAP postings | C31: - Open SAP transaction FAGLL03 - In the GL account section, enter in all the GL's to be validated for this scenario as per the Excel results file (e.g. 203020 243031, 706030...) - To filter on a particular contract using the AG_XXXX_00000X number or PO number (for GL 243031 only), use the custom selections filter and pull accross the 'assignment field' from the GL Account Line items folder - Select "All items" - this will include any items already cleared - Exectute the transaction - To change the layout, go to the "change layout function" and pull through the Cost center, Profit centre, Assignment field and any other relevant fields needed for validation. | D31: - All postings are pulled through for the relevant contracts with required validation fields
A32: 1 - Capitalised Contract | B32: 02 - Capitalisation and Liability posting (1 & 2) | C32: - Check that the Capitalisation posting 1 and Liability posting 2 in the Excel results file are performed in SAP in applicable ledgers. Ensure that the SAP document date, GL account and amounts in DC, LC1, LC2, LC3 are correct. - Confirm postings are made with doc type "AN" for Asset Posting 1 and "YN" for Liability Posting 2 - Check that Consolidation Movement Type (120) used for Asset posting - Check that the capitalisation clearing account (203031) nets off to zero in LC 1, LC2 & LC3 for this specific contract - Ensure that postings to GL accounts have the Nakisa activation group number in format (AG_XXXX_000001) populated in the SAP "Assignment" field (XXXX represents the entity number) - Check that postings have the Nakisa contract number in format (CO_XXXX_000001) in the SAP reference field | D32: - Doc type AN used for Asset posting and YN for LT Liability posting - Postings done in correct ledgers based on accounting approach with correct Movement Type - Correct date, GL account amount and currency (DC, LC1, LC2, LC3) are used - Postings have correct format AG reference in Assignment field and contract number in the SAP reference field - Account 203031 nets off to zero in LC1, LC2 & LC3 for this specific contract
A33: 1 - Capitalised Contract | B33: 03 - LT to ST Liability Transfer (4 & 10) | C33: - Check that the LT to ST transfer posting (4 & 10) in the Excel results file are performed in SAP in applicable ledgers. Ensure that the SAP document date, GL account and amounts in DC, LC1, LC2, LC3 are correct. - Confirm postings are made with doc type "YN" - Ensure that postings to GL accounts have the Nakisa activation group number in format (AG_XXXX_000001) populated in the SAP "Assignment" field (XXXX represents the entity number) - Check that postings have the Nakisa contract number in format (CO_XXXX_000001) in the SAP reference field | D33: - Doc type YN used for postings - Postings done in correct ledgers based on accounting approach - Correct date, GL account, amount and currency (DC, LC1, LC2, LC3) are used - Postings have correct format AG reference in Assignment field and contract number in the SAP reference field
A34: 1 - Capitalised Contract | B34: 04 - Interest Accrual Postings (5 & 11) | C34: - Check that the Interest accrual posting (5 & 11) in the Excel results file are performed in SAP in applicable ledgers. Ensure that the SAP document date, GL account and amounts in DC, LC1, LC2, LC3 are correct. - Confirm postings are made with doc type "YN" - Ensure that postings to GL accounts have the Nakisa activation group number in format (AG_XXXX_000001) populated in the SAP "Assignment" field (XXXX represents the entity number) - Check that postings have the Nakisa contract number in format (CO_XXXX_000001) in the SAP reference field | D34: - Doc type YN used for postings - Postings done in correct ledgers based on accounting approach - Correct date, GL account, amount and currency (DC, LC1, LC2, LC3) are used - Postings have correct format AG reference in Assignment field and contract number in the SAP reference field
A35: 1 - Capitalised Contract | B35: 05 - Payment Postings (3 & 9) | C35: - Check that the Payment posting (3 & 9) in the Excel results file are performed in SAP in applicable ledgers. Ensure that the SAP document date, GL account and amounts in DC, LC1, LC2, LC3 are correct. - Confirm postings are made with doc type "YN" - Ensure that postings to GL account 243031 have the Purchase Order number populated in the SAP "Assignment" field - Ensure that postings to GL account 243040 / 243030 have the Nakisa activation group number in format (AG_XXXX_000001) populated in the SAP "Assignment" field (XXXX represents the entity number) | D35: - Doc type YN used for postings - Postings done in correct ledgers based on accounting approach - Correct date, GL account, amount and currency (DC, LC1, LC2, LC3) are used - Postings to account 243031 have PO number in Assignment field - Postings to account 243040 / 243030 have correct format AG reference in Assignment field
A36: 1 - Capitalised Contract | B36: 06 - AP: invoice booking (6 & 12) / invoice reposting (7 & 13) | C36: - Ensure that invoice posting 6 & 12 and invoice reposting 7 & 13 in the Excel results file are performed in SAP in applicable ledgers. Ensure that the SAP document date, GL account and amounts in DC, LC1, LC2, LC3 are correct. - Confirm that posting 6 and 12 are made with doc type "RE" - Confirm that posting 7 and 13 are made with doc type "F1" - Ensure that postings to GL account 243031 / 243032 have the Purchase Order number populated in the SAP "Assignment" field - Check that technical lease clearing account 243032 nets off to zero in LC1, LC2 and LC3 - Based on the tax code in the PO, check that recoverable VAT is correctly excluded from the invoice amount posted to account 243031 / 243032 | D36: - Correct Doc types used - Correct date, GL account, amount and currency (DC, LC1, LC2, LC3) are used - Postings to accounts 243031 / 243032 have PO number in Assignment field - Technical lease clearing account 243032 nets off to zero in LC1, LC2 and LC3 - Recoverable VAT excluded from account 243031/243032 when invoice is posted
A37: 1 - Capitalised Contract | B37: 07 - Depreciation (8 & 14) | C37: - Check that Depreciation posting 8 and 14 in the Excel results file are performed in SAP in applicable ledgers. Ensure that the SAP document date, GL account and amounts in DC, LC1, LC2, LC3 are correct. - Confirm postings are made with doc type "AF" - Check that Consolidation Movement Type (220) is used for Accumulated depreciation posting | D37: - Doc type AF used for postings - Postings done in correct ledgers based on accounting approach with correct Movement Type - Correct date, GL account, amount and currency (DC, LC1, LC2, LC3) are used
A38: 1 - Capitalised Contract | B38: 08 - Clearing | C38: - GL 243040, 243031 and 203031 are cleared by the Lease Accounting Team - Ensure that for contracts paid in arrears GL 243040 is cleared during the same month. For those paid in advance the interest accrued should be cleared in the following month. - For GL 243031 ensure that the invoice booked for the period has been cleared with the payment booked by nakisa for the same period - Ensure that GL 203031 is cleared each month - the asset and liability booking should match | D38: - All 3 GL's have been cleared with the correct items matching off - Any variances in LC1, LC2 and LC3 have been booked to the correct RFX lease liability accounts (727105 / 728005)
A40: 06.b FI validation (Accrual Accounting Approach)
A41: 1 - Capitalised Contract | B41: 01 - Scenario Postings | C41: Open file attached in the first test script 01 for details of this E2E scenario and expected postings. Accrual accounting approach only applies to the ST / TX ledger, IFRS ledger 0L will always contain IFRS 16 postings. For the STAT and TAX ledger validation, please refer to the "Entity setup" tab for details of your entity's accounting approach and validate postings in the ledgers where Accrual accounting is followed. In this file you will find: - PO numbers, cost centers, profit centers and Vendor numbers related to this contract - Guidance on how to extract the relevant postings from SAP - S/4 Masterdata related to Leasing
A42: 1 - Capitalised Contract | B42: 01a - Extract SAP postings | C42: - Open SAP transaction FAGLL03 - In the GL account section, enter in all the GL's to be validated for this scenario as per the Excel results file (e.g. 203020 243031, 706030...) - To filter on a particular contract using the AG_XXXX_00000X number or PO number (for GL 243031 only), use the custom selections filter and pull accross the 'assignment field' from the GL Account Line items folder - Select "All items" - this will include any items already cleared - Exectute the transaction - To change the layout, go to the "change layout function" and pull through the Cost center, Profit centre, Assignment field and any other relevant fields needed for validation. | D42: - All postings are pulled through for the relevant contracts with required validation fields
A43: 1 - Capitalised Contract | B43: 02 - Lease expense accrual postings (1 & 4) | C43: - Ensure that P&L accrual postings 1 and 4 in the Excel results file are performed in SAP in applicable ledgers. Ensure that the SAP document date, GL account and amounts in DC, LC1, LC2, LC3 are correct. - Confirm postings are made with doc type "YL" - Ensure that postings to GL account 243031 have the Purchase Order number populated in the SAP "Assignment" field - Ensure that postings to ST/TX GL account 5340XX have the Nakisa activation group number in format (AG_XXXX_000001) populated in the SAP "Assignment" field (XXXX represents the entity number) | D43: - Doc type YL used - Correct date, GL account, amount and currency (DC, LC1, LC2, LC3) are used - Postings have correct format AG reference in Assignment field - Check that correct ST/TX Lease expense accrual account (by asset class) is used
A44: 1 - Capitalised Contract | B44: 03 - AP: invoice booking (2 & 5) / invoice reposting (3 & 6) | C44: - Ensure that invoice posting 2 & 5 and invoice reposting 3 & 6 in the Excel results file are performed in SAP in applicable ledgers. Ensure that the SAP document date, GL account and amounts in DC, LC1, LC2, LC3 are correct. - Confirm that posting 2 and 5 are made with doc type "RE" - Confirm that posting 3 and 6 are made with doc type "F1" - Ensure that postings to GL account 243031 / 243032 have the Purchase Order number populated in the SAP "Assignment" field - Check that technical lease clearing account 243032 nets off to zero in LC1, LC2 & LC3 - Based on the tax code in the PO, check that recoverable VAT is correctly excluded from the invoice amount posted to account 243031/243032 | D44: - Correct Doc types used - Correct date, GL account, amount and currency (DC, LC1, LC2, LC3) are used - Postings to accounts 243031 / 243032 have PO number in Assignment field - Technical lease clearing account 243032 nets off to zero in LC1, LC2 and LC3 - Recoverable VAT excluded from account 243031/243032 when invoice is posted
A45: 1 - Capitalised Contract | B45: 04 - Clearing | C45: - GL 243031 is cleared by the Lease Accounting Team - Ensure that the invoice booked for the period has been cleared with the payment booked by Nakisa for the same period | D45: - GL 243031 is cleared with the correct items matching off - Any variances in LC1, LC2 and LC3 have been automatically to the correct RFX lease liability accounts (727105 / 728005)
A47: 06.c FI validation (IR Accounting Approach)
A48: 1 - Capitalised Contract | B48: 01 - Scenario Postings | C48: Open file attached in the first test script 01 for details of this E2E scenario and expected postings. Invoice Receipt accounting approach only applies to the ST / TX ledger, IFRS ledger 0L will always contain IFRS 16 postings. For the STAT and TAX ledger validation, please refer to the "Entity setup" tab for details of your entity's accounting approach and validate postings in the ledgers where Invoice Receipt accounting is followed. In this file you will find: - PO numbers, cost centers, profit centers and Vendor numbers related to this contract - Guidance on how to extract the relevant postings from SAP - S/4 Masterdata related to Leasing
A49: 1 - Capitalised Contract | B49: 01a - Extract SAP postings | C49: - Open SAP transaction FAGLL03 - In the GL account section, enter in all the GL's to be validated for this scenario as per the Excel results file (e.g. 203020 243031, 706030...) - To filter on a particular contract using the AG_XXXX_00000X number or PO number (for GL 243031 only), use the custom selections filter and pull accross the 'assignment field' from the GL Account Line items folder - Select "All items" - this will include any items already cleared - Exectute the transaction - To change the layout, go to the "change layout function" and pull through the Cost center, Profit centre, Assignment field and any other relevant fields needed for validation. | D49: - All postings are pulled through for the relevant contracts with required validation fields
A50: 1 - Capitalised Contract | B50: 02 - AP: invoice booking (1 & 3) | C50: - Ensure that invoice posting 1 & 3 in the Excel results file are performed in SAP in applicable ledgers for IR approach. Ensure that the SAP document date, GL account and amounts in DC, LC1, LC2, LC3 are correct. - Confirm that posting 1 and 3 are made with doc type "RE" - Check that technical lease clearing account 243032 nets off to zero in LC1, LC2 & LC3 - Ensure that postings to account 243032 have PO number in the SAP Assignment field | D50: - Correct Doc types used - Correct date, GL account, amount and currency (DC, LC1, LC2, LC3) are used - Postings to account 243032 have PO number in Assignment field - Technical lease clearing account 243032 nets off to zero in LC1, LC2 and LC3
A51: 1 - Capitalised Contract | B51: 03 - Lease expense postings (2 & 4) | C51: - Ensure that P&L Invoice Receipt postings 2 and 4 in the Excel results file are performed in SAP in applicable ledgers. Ensure that the SAP document date, GL account and amounts in DC, LC1, LC2, LC3 are correct. - Confirm postings are made with doc type "F1" | D51: - Doc type F1 used - Correct date, GL account, amount and currency (DC, LC1, LC2, LC3) are used - Check that correct ST/TX Lease expense account (by asset class) is used
A53: 07. FICO check - validate document splitting and Profit Center assignments
A54: 1 - Capitalised Contract | B54: 00 - Open file attached in the first test script 01 | C54: Open file attached in the first test script 01 for details of this E2E scenario and posting results. In this file you will find the: - PO numbers, cost centers, profit centers and Vendor numbers related to this contract - Guidance on how to extract the relevant postings from SAP - S/4 Masterdata related to Leasing
A55: 1 - Capitalised Contract | B55: 01 - FI document check | C55: FI document check: validate document splitting and Profit Center assignments following detailed instruction: https://jticorp.sharepoint.com/sites/BPM/ERPPublic/ChangeManagement/Testers%20Help/Forms/AllItems.aspx?id=%2Fsites%2FBPM%2FERPPublic%2FChangeManagement%2FTesters%20Help%2F5%5FMarket%20FCF | D55: FI requirements are met
A57: 08. CO check - validate correctness of assigned CO object (e.g. cost center)
A58: 1 - Capitalised Contract | B58: 00 - Open file attached in the first test script 01 | C58: Open file attached in the first test script 01 for details of this E2E scenario and posting results. In this file you will find the: - PO numbers, Cost centers, Profit centers and Vendor numbers related to this contract - Guidance on how to extract the relevant postings from SAP - S/4 Masterdata related to Leasing
A59: 1 - Capitalised Contract | B59: 01 - CO document check | C59: CO document check: validate correctness of assigned CO object | D59: CO requirements are met
A61: 09. FA check - validate RoU asset in FA module
A62: 1 - Capitalised Contract | B62: 01 - Scenario Postings - Expected results and Contract information | C62: Open file attached in the first test script 01 for details of this E2E scenario and expected postings. All entities should validate the RoU asset in the IFRS area. For the STAT and TAX area validation, this only needs to be done for entities following IFRS 16 accounting approach for STAT and TAX - please refer to the "Entity setup" tab for details of your entity's accounting approach. If your entity follows the Accrual or IR approach for STAT and TAX, please only validate the IFRS Area. In this file you will also find: - PO numbers, cost centers, profit centers and Vendor numbers related to this contract - Guidance on how to extract the relevant postings from SAP - S/4 Masterdata related to Leasing | D62: Referred to "Scenario results" file - entity accounting setup checked to confirm whether ST or TX areas also need to be reviewed
A63: 1 - Capitalised Contract | B63: 02 - Asset Shell | C63: - Run SAP transaction AS03 to view the asset shell - Check that the asset class used matches the schedule - Check Cost centre used is correct (refer to "Time-dependent" tab) - Check that the depreciation useful life for the applicable area (IFRS, STAT or TAX) is correct. Useful economic life should be the lower of the JTI standard UEL and the contract duration. | D63: - Correct asset class and cost centres used - Correct useful life populated in IFRS, STAT and TAX areas
A64: 1 - Capitalised Contract | B64: 03 - Depreciation Area | C64: - Open transaction AW01N - Ensure applicable areas (IFRS, STAT or TAX) are shown. | D64: Depreciation is shown correctly for applicable areas where IFRS16 is followed
A65: 1 - Capitalised Contract | B65: 04 - Depreciation Key | C65: - Ensure Depreciation key appears with ZLIN for areas where IFRS 16 is adopted and Z000 for the STAT and TAX areas where Accrual/IR approach is adopted (as per setup in Entity Accounting Approach). | D65: Correct Depreciation key populated in IFRS, STAT and TAX
A66: 1 - Capitalised Contract | B66: 05 - Transaction Type | C66: - Open transaction AW01N - Ensure transaction type is correct for asset capitalisation (e.g. Z31 for inception posting). Refer to bottom of "planned values" tab | D66: Correct transaction type shown in asset capitalisation posting
A67: 1 - Capitalised Contract | B67: 06 - Asset value | C67: - Open transaction AW01N - Confirm that ROU asset value in the "planned values" tab matches the schdedules in the results file | D67: RoU asset value in FA module matches amount per the schedule in results file
A68: 1 - Capitalised Contract | B68: 07 - Planned Depreciation | C68: - Open transaction AW01N - Ensure Depreciation is calculated at lower of Useful life / Contract duration - Check the planned depreciation values are correct as per schedule in the results file | D68: Correct depreciation calculation is done in SAP
A71: SCENARIO 2
A73: 01. Scenarios & Results excel file attached (refers to this file)
A75: 02. Create Purchase Requisition
A76: 2 - Low Value Contract | B76: 00 - Open file attached in the first test script 01 | C76: Open file attached in the first test script 01. Refer to "Scenarios" tab for details to create the PR for this contract.
A77: 2 - Low Value Contract | B77: 01 - Enter requisition details in MyShop | C77: - Input requirements into Free-text field in MyShop - Select a random local currency Vendor used currently for Leasing - Select a random cost center used currently for Leasing - Select the correct Material Group relating to Fixed leasing costs as per scenario details - Select First payment date (1 July 2019), last payment date (1 June 2021), 24 periods, Price = 250 - Add to shopping cart | D77: - Free-text, fixed leasing material group, cost center & payment details are input correctly
A78: 2 - Low Value Contract | B78: 02 - Finalize PR | C78: - Ensure the right Material Group and GL account assignment (243032) is selected - PR is sent to Procurement for approval - Record PR number in HPALM Result Field | D78: - Correct fixed leasing material group can be selected - GL account assignment is defaulted to 243032 - PR number recorded in Result Field
A79: 2 - Low Value Contract | B79: 03 - PR Approval | C79: - Procurement approves PR - Approve PR and ensure it follows the defined approval hierarchy | D79: - PR is approved - PR routing follows the right approval cycle
A81: 03. Create Purchase Order
A82: 2 - Low Value Contract | B82: 00 - Open file attached in the first test script 01 | C82: Open file attached in the first test script 01. Refer to "Scenarios" tab for details to create the PO for this contract.
A83: 2 - Low Value Contract | B83: 01 - PO Creation | C83: - PR is reviewed and Framework Order / Invoice Plan PO is manually created with all the necessary items from PR (first pmt date, last pmt date, material group, vendor, cost center, quantity, price, account assignment 243032, GR flag unticked) - Framework order / Invoice Plan PO is correctly created and saved in SAP - Record PO number in HPALM Result Field | D83: - PO manually created using details from PR (e.g. correct material group, vendor, cost center, quantity, price, account assignment 243032 and GR flag unticked) - PO created and saved in SAP - PO number recorded in HPALM Result field
A84: 2 - Low Value Contract | B84: 02 - GR flag removed (2 way match) | C84: - Verify the system has automatically removed the GR flag for Fixed Leasing material group | D84: - GR flag automatically removed
A85: 2 - Low Value Contract | B85: 03 - PO Tax code (VAT) | C85: - Ensure that a "fully recoverable VAT" tax code has been selected | D85: - "Fully recoverable VAT" tax code has been selected for this scenario
A87: 04.b Create contract in Nakisa (Lease Accounting Team - detailed test scripts not shown below)
A89: 06.a FI validation (IFRS 16 Accounting Approach)
A90: 2 - Low Value Contract | B90: 01 - Scenario Postings | C90: Open file attached in the first test script 01 for details of this E2E scenario and expected postings. All entities should validate IFRS 16 postings in the IFRS ledger (0L). For the STAT and TAX ledger validation, please refer to the "Entity setup" tab for details of your entity's accounting approach. If IFRS 16 is followed for ST / TX, please also validate postings in those ledgers. In this file you will find: - PO numbers, cost centers, profit centers and Vendor numbers related to this contract - Guidance on how to extract the relevant postings from SAP - S/4 Masterdata related to Leasing
A91: 2 - Low Value Contract | B91: 01a - Extract SAP postings | C91: - Open SAP transaction FAGLL03 - In the GL account section, enter in all the GL's to be validated for this scenario as per the Excel results file (e.g. 203020 243031, 706030...) - To filter on a particular contract using the AG_XXXX_00000X number or PO number (for GL 243031 only), use the custom selections filter and pull accross the 'assignment field' from the GL Account Line items folder - Select "All items" - this will include any items already cleared - Exectute the transaction - To change the layout, go to the "change layout function" and pull through the Cost center, Profit centre, Assignment field and any other relevant fields needed for validation. | D91: - All postings are pulled through for the relevant contracts with required validation fields
A92: 2 - Low Value Contract | B92: 02 - Payment Postings (1 & 5) | C92: - Check that the Payment posting (1 & 5) in the Excel results file are performed in SAP in applicable ledgers. Ensure that the SAP document date, GL account and amounts in DC, LC1, LC2, LC3 are correct. - Confirm postings are made with doc type "YN" - Ensure that postings to GL account 243031 have the Purchase Order number populated in the SAP "Assignment" field - Ensure that postings to GL account 167021 have the Nakisa activation group number in format (AG_XXXX_000001) populated in the SAP "Assignment" field (XXXX represents the entity number) | D92: - Doc type YN used for postings - Postings done in correct ledgers based on accounting approach - Correct date, GL account, amount and currency (DC, LC1, LC2, LC3) are used - Postings to account 243031 have PO number in Assignment field - Postings to account 167021 have correct format AG reference in Assignment field
A93: 2 - Low Value Contract | B93: 03 - AP: invoice booking / reposting (2, 3, 6, 7) | C93: - Ensure that invoice posting 2 & 6 and invoice reposting 3 & 7 in the Excel results file are performed in SAP in applicable ledgers. Ensure that the SAP document date, GL account and amounts in DC, LC1, LC2, LC3 are correct. - Confirm that posting 2 and 6 are made with doc type "RE" - Confirm that posting 3 and 7 are made with doc type "F1" - Ensure that postings to GL account 243031 / 243032 have the Purchase Order number populated in the SAP "Assignment" field - Check that technical lease clearing account 243032 nets off to zero in LC1, LC2 and LC3 - Based on the tax code in the PO, check that recoverable VAT is correctly excluded from the invoice amount posted to account 243031/243032 | D93: - Correct Doc types used - Correct date, GL account, amount and currency (DC, LC1, LC2, LC3) are used - Postings to accounts 243031 / 243032 have PO number in Assignment field - Technical lease clearing account 243032 nets off to zero in LC1, LC2 and LC3 - Recoverable VAT excluded from account 243031/243032 when invoice is posted
A94: 2 - Low Value Contract | B94: 04 - P&L exempt lease postings (4 & 8) | C94: - Check that P&L accrual postings (4 & 8) in the Excel results file are performed in SAP in applicable ledgers. Ensure that the SAP document date, GL account and amounts in DC, LC1, LC2, LC3 are correct. - Confirm postings are made with doc type "YN" - Ensure that postings have the Nakisa activation group number in format (AG_XXXX_000001) populated in the SAP "Assignment" field (XXXX represents the entity number) - Check that postings have the Nakisa contract number in format (CO_XXXX_000001) in the SAP reference field | D94: - Doc type YN used for postings - Postings done in correct ledgers based on accounting approach - Correct date, GL account, amount and currency (DC, LC1, LC2, LC3) are used - Postings have correct format AG reference in Assignment field and contract number in the SAP reference field
A95: 2 - Low Value Contract | B95: 05 - Clearing | C95: - GL 167021 and 243031 are cleared by the Lease accounting team - For GL 243031 ensure that the invoice booked for the period has been cleared with the payment booked by Nakisa for the same period - Ensure that contracts which are paid monthly are cleared from GL 167021 during the period (e.g payment and accrual should net off) - Contract not paid monthly should have uncleared items remaining in GL 167021 | D95: - Both GL's have been cleared with the correct items matching off - Any variances in LC1, LC2 and LC3 have been automatically booked to the correct RFX lease liability accounts (727105 / 728005)
A97: 06.b FI validation (Accrual Accounting Approach)
A98: 2 - Low Value Contract | B98: 01 - Scenario Postings | C98: Open file attached in the first test script 01 for details of this E2E scenario and expected postings. Accrual accounting approach only applies to the ST / TX ledger, IFRS ledger 0L will always contain IFRS 16 postings. For the STAT and TAX ledger validation, please refer to the "Entity setup" tab for details of your entity's accounting approach and validate postings in the ledgers where Accrual accounting is followed. In this file you will find: - PO numbers, cost centers, profit centers and Vendor numbers related to this contract - Guidance on how to extract the relevant postings from SAP - S/4 Masterdata related to Leasing
A99: 2 - Low Value Contract | B99: 01a - Extract SAP postings | C99: - Open SAP transaction FAGLL03 - In the GL account section, enter in all the GL's to be validated for this scenario as per the Excel results file (e.g. 203020 243031, 706030...) - To filter on a particular contract using the AG_XXXX_00000X number or PO number (for GL 243031 only), use the custom selections filter and pull accross the 'assignment field' from the GL Account Line items folder - Select "All items" - this will include any items already cleared - Exectute the transaction - To change the layout, go to the "change layout function" and pull through the Cost center, Profit centre, Assignment field and any other relevant fields needed for validation. | D99: - All postings are pulled through for the relevant contracts with required validation fields
A100: 2 - Low Value Contract | B100: 02 - Payment Postings (1 & 5) | C100: - Check that the Payment posting (1 & 5) in the Excel results file are performed in SAP in applicable ledgers. Ensure that the SAP document date, GL account and amounts in DC, LC1, LC2, LC3 are correct. - Confirm postings are made with doc type "YL" - Ensure that postings to GL account 243031 have the Purchase Order number populated in the SAP "Assignment" field - Ensure that postings to GL account 167021 have the Nakisa activation group number in format (AG_XXXX_000001) populated in the SAP "Assignment" field (XXXX represents the entity number) | D100: - Doc type YL used for postings - Postings done in correct ledgers based on accounting approach - Correct date, GL account, amount and currency (DC, LC1, LC2, LC3) are used - Postings to account 243031 have PO number in Assignment field - Postings to account 167021 have correct format AG reference in Assignment field
A101: 2 - Low Value Contract | B101: 03 - AP: invoice booking / reposting (2, 3, 6, 7) | C101: - Ensure that invoice posting 2 & 6 and invoice reposting 3 & 7 in the Excel results file are performed in SAP in applicable ledgers. Ensure that the SAP document date, GL account and amounts in DC, LC1, LC2, LC3 are correct. - Confirm that posting 2 and 6 are made with doc type "RE" - Confirm that posting 3 and 7 are made with doc type "F1" - Ensure that postings to GL account 243031 / 243032 have the Purchase Order number populated in the SAP "Assignment" field - Check that technical lease clearing account 243032 nets off to zero in LC1, LC2 and LC3 - Based on the tax code in the PO, check that recoverable VAT is correctly excluded from the invoice amount posted to account 243031/243032 | D101: - Correct Doc types used - Correct date, GL account, amount and currency (DC, LC1, LC2, LC3) are used - Postings to accounts 243031 / 243032 have PO number in Assignment field - Technical lease clearing account 243032 nets off to zero in LC1, LC2 and LC3 - Recoverable VAT excluded from account 243031/243032 when invoice is posted
A102: 2 - Low Value Contract | B102: 04 - Lease expense accrual postings (4 & 8) | C102: - Check that P&L accrual postings (4 & 8) in the Excel results file are performed in SAP in applicable ledgers. Ensure that the SAP document date, GL account and amounts in DC, LC1, LC2, LC3 are correct. - Confirm postings are made with doc type "YL" - Ensure that postings have the Nakisa activation group number in format (AG_XXXX_000001) populated in the SAP "Assignment" field (XXXX represents the entity number) | D102: - Doc type YL used for postings - Postings done in correct ledgers based on accounting approach - Correct date, GL account, amount and currency (DC, LC1, LC2, LC3) are used - Postings have correct format AG reference in Assignment field - Check that correct ST/TX Lease expense accrual account (by asset class) is used
A103: 2 - Low Value Contract | B103: 05 - Clearing | C103: - GL 167021 and 243031 are cleared by the Lease accounting team - For GL 243031 ensure that the invoice booked for the period has been cleared with the payment booked by Nakisa for the same period - Ensure that contracts which are paid monthly are cleared from GL 167021 during the period (e.g payment and accrual should net off) - Contract not paid monthly should have uncleared items remaining in GL 167021 | D103: - Both GL's have been cleared with the correct items matching off - Any variances in LC1, LC2 and LC3 have been automatically booked to the correct RFX lease liability accounts (727105 / 728005)
A105: 06.c FI validation (IR Accounting Approach)
A106: 2 - Low Value Contract | B106: 01 - Scenario Postings | C106: Open file attached in the first test script 01 for details of this E2E scenario and expected postings. Invoice Receipt accounting approach only applies to the ST / TX ledger, IFRS ledger 0L will always contain IFRS 16 postings. For the STAT and TAX ledger validation, please refer to the "Entity setup" tab for details of your entity's accounting approach and validate postings in the ledgers where Invoice Receipt accounting is followed. In this file you will find: - PO numbers, cost centers, profit centers and Vendor numbers related to this contract - Guidance on how to extract the relevant postings from SAP - S/4 Masterdata related to Leasing
A107: 2 - Low Value Contract | B107: 01a - Extract SAP postings | C107: - Open SAP transaction FAGLL03 - In the GL account section, enter in all the GL's to be validated for this scenario as per the Excel results file (e.g. 203020 243031, 706030...) - To filter on a particular contract using the AG_XXXX_00000X number or PO number (for GL 243031 only), use the custom selections filter and pull accross the 'assignment field' from the GL Account Line items folder - Select "All items" - this will include any items already cleared - Exectute the transaction - To change the layout, go to the "change layout function" and pull through the Cost center, Profit centre, Assignment field and any other relevant fields needed for validation. | D107: - All postings are pulled through for the relevant contracts with required validation fields
A108: 2 - Low Value Contract | B108: 02 - AP: invoice booking (1 & 3) | C108: - Ensure that invoice posting 1 & 3 in the Excel results file are performed in SAP in applicable ledgers for IR approach. Ensure that the SAP document date, GL account and amounts in DC, LC1, LC2, LC3 are correct. - Confirm that posting 1 and 3 are made with doc type "RE" - Check that technical lease clearing account 243032 nets off to zero in LC1, LC2 & LC3 - Ensure that postings to account 243032 have PO number in the SAP Assignment field | D108: - Correct Doc types used - Correct date, GL account, amount and currency (DC, LC1, LC2, LC3) are used - Postings to account 243032 have PO number in Assignment field - Technical lease clearing account 243032 nets off to zero in LC1, LC2 and LC3
A109: 2 - Low Value Contract | B109: 03 - Lease expense postings (2 & 4) | C109: - Ensure that P&L Invoice Receipt postings 2 and 4 in the Excel results file are performed in SAP in applicable ledgers. Ensure that the SAP document date, GL account and amounts in DC, LC1, LC2, LC3 are correct. - Confirm postings are made with doc type "F1" | D109: - Doc type F1 used - Correct date, GL account, amount and currency (DC, LC1, LC2, LC3) are used - Check that correct ST/TX Lease expense account (by asset class) is used
A111: 07. FICO check - validate document splitting and Profit Center assignments
A112: 2 - Low Value Contract | B112: 00 - Open file attached in the first test script 01 | C112: Open file attached in the first test script 01 for details of this E2E scenario and posting results. In this file you will find the: - PO numbers, cost centers, profit centers and Vendor numbers related to this contract - Guidance on how to extract the relevant postings from SAP - S/4 Masterdata related to Leasing
A113: 2 - Low Value Contract | B113: 01 - FI document check | C113: FI document check: validate document splitting and Profit Center assignments following detailed instruction: https://jticorp.sharepoint.com/sites/BPM/ERPPublic/ChangeManagement/Testers%20Help/Forms/AllItems.aspx?id=%2Fsites%2FBPM%2FERPPublic%2FChangeManagement%2FTesters%20Help%2F5%5FMarket%20FCF | D113: FI requirements are met
A115: 08. CO check - validate correctness of assigned CO object (e.g. cost center)
A116: 2 - Low Value Contract | B116: 00 - Open file attached in the first test script 01 | C116: Open file attached in the first test script 01 for details of this E2E scenario and posting results. In this file you will find the: - PO numbers, cost centers, profit centers and Vendor numbers related to this contract - Guidance on how to extract the relevant postings from SAP - S/4 Masterdata related to Leasing
A117: 2 - Low Value Contract | B117: 01 - CO document check | C117: CO document check: validate correctness of assigned CO object | D117: CO requirements are met
A119: SCENARIO 3
A121: 01. Scenarios & Results excel file attached (refers to this file)
A123: 02. Create Purchase Requisition
A124: 3 - Short Term Contract | B124: 00 - Open file attached in the first test script 01 | C124: Open file attached in the first test script 01. Refer to "Scenarios" tab for details to create the PR for this contract.
A125: 3 - Short Term Contract | B125: 01 - Enter requisition details in MyShop | C125: - Input requirements into Free-text field in MyShop - Select a random local currency Vendor used currently for Leasing (ZSRM PO must be created, no invoice plan) - Select a random cost center used currently for Leasing - Select the correct Material Group relating to Fixed leasing costs as per scenario details - Select Quantity (= no. of payments) & Price (= payment amount) - Add to shopping cart | D125: - Free-text, fixed leasing material group, cost center & payment details are input correctly
A126: 3 - Short Term Contract | B126: 02 - Finalize PR | C126: - Ensure the right Material Group and GL account assignment (243032) is selected - PR is sent to Procurement for approval - Record PR number in HPALM Result Field | D126: - Correct fixed leasing material group can be selected - GL account assignment is defaulted to 243032 - PR number recorded in Result Field
...

Sheet 1 - Capitalised Contract
C1: 1 - Capitalised Contract | BB1: Advance
BB2: Arrears
C3: Asset class name | E3: Buildings
C4: Asset class no. | E4: 103020
C5: Material group name | E5: =VLOOKUP(E6,'Material Groups'!$B:$C,2,0) -> LeaseBuild FixedCost | F5: =VLOOKUP(F6,'Material Groups'!$B:$C,2,0) -> #N/A
C6: Material group no. | E6: 95101111
C7: Shopping cart number
C8: PR number
C9: PO no.
C10: Vendor ID
C11: Invoice no.
C12: Annual interest rate | F12: 0.05
C13: Monthly interest rate | F13: =(1+F12)^(1/12)-1 -> 0.0040741238
C14: Lease payment per period (excl. VAT) | F14: 7500
C15: Payment frequency | F15: Monthly
C16: Payment timing | F16: Advance
C17: First payment Date | F17: 43647
C18: Lease term (months) | F18: 120
C19: Lease start date | F19: 43647
C20: Lease end date | F20: 47299
C21: Calculated NPV | F21: -710056.42
C22: Useful life (UL) of the asset (years) | F22: 50 | R22: IFRS 16 Approach
C23: Lower UL / contract duration (Months) | F23: =IF(F18<(F22*12),F18,F22*12) -> 120 | G23: for depreciation | R23: All amounts below are in contract currency (DC)
R24: Please check LC2, LC3 FX posting conversion where applicable | AA24: Asset class name | AC24: Buildings
W25: SAP Posting date | AA25: Asset class no. | AC25: 103020
R26: Description | W26: P7 | Y26: P8 | AA26: Material group name | AC26: LeaseBuild FixedCost
R27: Initial posting: recognition of assets | V27: 1 | W27: =$D$38 -> 43647 | Y27: - | AA27: Material group no. | AC27: 95101111
I28: LEASE LIABILITY | N28: RIGHT OF USE ASSET | R28: Initial posting: recognition of liability | V28: 2 | W28: =$D$38 -> 43647 | AA28: Lease payment per period (excl. VAT) | AD28: 7500
H29: Inception | L29: DR 203031(BS) | N29: Dr 203020 (BS) | R29: Payment by Nakisa | V29: 3 | W29: =$D$38 -> 43647 | X29: 9 | Y29: =$D$39 -> 43678 | AA29: Payment frequency | AD29: Monthly
L30: CR 262530 (BS) | N30: CR 203031 (BS) | R30: LT liability to ST liability reclass | V30: 4 | W30: =$E$38 -> 43677 | X30: 10 | Y30: =$E$39 -> 43708 | AA30: Payment timing | AD30: Advance
H31: Monthly Acc. | I31: DR 706030 (PL) | K31: DR 262530 (BS) | L31: DR 262530 (BS) | O31: DR 534080 (PL) | P31: DR 534080 (PL) | R31: Interest accrual | V31: 5 | W31: =$E$38 -> 43677 | X31: 11 | Y31: =$E$39 -> 43708 | AA31: Lease term (months) | AD31: 120
I32: CR 243040 (BS) | K32: CR 243030 (BS) | L32: CR 243030 (BS) | O32: CR 211520 (BS) | P32: CR 211520 (BS) | R32: AP: invoice booking | V32: 6 | W32: =$D$38 -> 43647 | X32: 12 | Y32: =$D$39 -> 43678 | AA32: Lease start date | AD32: 43647
H33: Payment | I33: DR 243040 (BS) | K33: DR 243030 (BS) | R33: Automated reposting of AP | V33: 7 | W33: =$D$38 -> 43647 | X33: 13 | Y33: =$D$39 -> 43678 | AA33: Lease end date | AD33: 47299
I34: CR 243031 (BS) | K34: CR 243031 (BS) | R34: Depreciation run | V34: 8 | W34: =$E$38 -> 43677 | X34: 14 | Y34: =$E$39 -> 43708 | AA34: Calculated NPV | AD34: -710056.42
B36: Days | C36: Period | D36: Start Date | E36: End Date | F36: Opening Lease Liability (Principal) | G36: Total Repayment | H36: Principal repayment | I36: Interest (PL) 706030 | J36: Closing Lease Liability (Principal) | K36: ST Liability (BS) 243030 | L36: LT Liability (BS) 262530 | N36: Right of Use Asset (BS) | O36: Accumulated Depreciation (BS) | P36: Depreciation (PL) 534080
R37: Leasing ROU - Building 203020 (BS) | W37: Capitalization clearing (203031) | AB37: Lease LT Liability (262530)
B38: =E38-D38+1 -> 31 | C38: 1 | D38: =F19 -> 43647 | E38: =EOMONTH(D38,0) -> 43677 | F38: =F21 -> -710056.42 | G38: =$F$14 -> 7500 | H38: =F14 -> 7500 | I38: =(F38+G38)*F12/12 -> -2927.3184 | J38: =SUM(F38,H38) -> -702556.42 | K38: =J38-J50 -> -56147.296 | L38: =J38-K38 -> -646409.12 | N38: =IF(C38>$F$23,0,-$F$38) -> 710056.42 | O38: =-P38 -> -5917.1368 | P38: =N38/$F$23 -> 5917.1368 | R38: 1 | S38: =N38 -> 710056.42 | W38: 2 | X38: =AD38 -> 710056.42 | Y38: =S38 -> 710056.42 | Z38: 1 | AB38: 4 | AC38: =SUM(H38:H50) -> 63647.296 | AD38: =-F38 -> 710056.42 | AE38: 2
B39: =E39-D39+1 -> 31 | C39: 2 | D39: =EDATE(D38,1) -> 43678 | E39: =EOMONTH(D39,0) -> 43708 | F39: =J38 -> -702556.42 | G39: =$F$14 -> 7500 | H39: =G39+I38 -> 4572.6816 | I39: =(F39+G39+I38)*$F$12/12 -> -2908.2656 | J39: =SUM(F39,H39) -> -697983.74 | K39: =J39-J51 -> -56381.243 | L39: =J39-K39 -> -641602.49 | N39: =IF(C39>$F$23,0,-$F$38) -> 710056.42 | O39: =IF(N39=0,0,O38-P39) -> -11834.274 | P39: =N39/$F$23 -> 5917.1368 | AB39: 10 | AC39: =AD44 -> 4806.6287
B40: =E40-D40+1 -> 30 | C40: 3 | D40: =EDATE(D39,1) -> 43709 | E40: =EOMONTH(D40,0) -> 43738 | F40: =J39 -> -697983.74 | G40: =$F$14 -> 7500 | H40: =G40+I39 -> 4591.7344 | I40: =(F40+G40+I39)*$F$12/12 -> -2889.1333 | J40: =SUM(F40,H40) -> -693392 | K40: =J40-J52 -> -56616.165 | L40: =J40-K40 -> -636775.84 | N40: =IF(C40>$F$23,0,-$F$38) -> 710056.42 | O40: =IF(N40=0,0,O39-P40) -> -17751.41 | P40: =N40/$F$23 -> 5917.1368
B41: =E41-D41+1 -> 31 | C41: 4 | D41: =EDATE(D40,1) -> 43739 | E41: =EOMONTH(D41,0) -> 43769 | F41: =J40 -> -693392 | G41: =$F$14 -> 7500 | H41: =G41+I40 -> 4610.8667 | I41: =(F41+G41+I40)*$F$12/12 -> -2869.9214 | J41: =SUM(F41,H41) -> -688781.14 | K41: =J41-J53 -> -56852.066 | L41: =J41-K41 -> -631929.07 | N41: =IF(C41>$F$23,0,-$F$38) -> 710056.42 | O41: =IF(N41=0,0,O40-P41) -> -23668.547 | P41: =N41/$F$23 -> 5917.1368
B42: =E42-D42+1 -> 30 | C42: 5 | D42: =EDATE(D41,1) -> 43770 | E42: =EOMONTH(D42,0) -> 43799 | F42: =J41 -> -688781.14 | G42: =$F$14 -> 7500 | H42: =G42+I41 -> 4630.0786 | I42: =(F42+G42+I41)*$F$12/12 -> -2850.6294 | J42: =SUM(F42,H42) -> -684151.06 | K42: =J42-J54 -> -57088.95 | L42: =J42-K42 -> -627062.11 | N42: =IF(C42>$F$23,0,-$F$38) -> 710056.42 | O42: =IF(N42=0,0,O41-P42) -> -29585.684 | P42: =N42/$F$23 -> 5917.1368 | R42: Lease Interest (P&L) (706030) | W42: Lease Accrued interest (BS) (243040) | AB42: Lease ST Liability (243030)
B43: =E43-D43+1 -> 31 | C43: 6 | D43: =EDATE(D42,1) -> 43800 | E43: =EOMONTH(D43,0) -> 43830 | F43: =J42 -> -684151.06 | G43: =$F$14 -> 7500 | H43: =G43+I42 -> 4649.3706 | I43: =(F43+G43+I42)*$F$12/12 -> -2831.257 | J43: =SUM(F43,H43) -> -679501.69 | K43: =J43-J55 -> -57326.82 | L43: =J43-K43 -> -622174.87 | N43: =IF(C43>$F$23,0,-$F$38) -> 710056.42 | O43: =IF(N43=0,0,O42-P43) -> -35502.821 | P43: =N43/$F$23 -> 5917.1368 | R43: 5 | S43: =-I38 -> 2927.3184 | W43: 9 | X43: =Y43 -> 2927.3184 | Y43: =S43 -> 2927.3184 | Z43: 5 | AB43: 3 | AC43: =H38 -> 7500 | AD43: =AC38 -> 63647.296 | AE43: 4
B44: =E44-D44+1 -> 31 | C44: 7 | D44: =EDATE(D43,1) -> 43831 | E44: =EOMONTH(D44,0) -> 43861 | F44: =J43 -> -679501.69 | G44: =$F$14 -> 7500 | H44: =G44+I43 -> 4668.743 | I44: =(F44+G44+I43)*$F$12/12 -> -2811.8039 | J44: =SUM(F44,H44) -> -674832.94 | K44: =J44-J56 -> -57565.682 | L44: =J44-K44 -> -617267.26 | N44: =IF(C44>$F$23,0,-$F$38) -> 710056.42 | O44: =IF(N44=0,0,O43-P44) -> -41419.958 | P44: =N44/$F$23 -> 5917.1368 | R44: 11 | S44: =-I39 -> 2908.2656 | Y44: =S44 -> 2908.2656 | Z44: 11 | AB44: 9 | AC44: =H39 -> 4572.6816 | AD44: =H51 -> 4806.6287 | AE44: 10
B45: =E45-D45+1 -> 29 | C45: 8 | D45: =EDATE(D44,1) -> 43862 | E45: =EOMONTH(D45,0) -> 43890 | F45: =J44 -> -674832.94 | G45: =$F$14 -> 7500 | H45: =G45+I44 -> 4688.1961 | I45: =(F45+G45+I44)*$F$12/12 -> -2792.2698 | J45: =SUM(F45,H45) -> -670144.75 | K45: =J45-J57 -> -57805.539 | L45: =J45-K45 -> -612339.21 | N45: =IF(C45>$F$23,0,-$F$38) -> 710056.42 | O45: =IF(N45=0,0,O44-P45) -> -47337.095 | P45: =N45/$F$23 -> 5917.1368
B46: =E46-D46+1 -> 31 | C46: 9 | D46: =EDATE(D45,1) -> 43891 | E46: =EOMONTH(D46,0) -> 43921 | F46: =J45 -> -670144.75 | G46: =$F$14 -> 7500 | H46: =G46+I45 -> 4707.7302 | I46: =(F46+G46+I45)*$F$12/12 -> -2772.6542 | J46: =SUM(F46,H46) -> -665437.02 | K46: =J46-J58 -> -58046.395 | L46: =J46-K46 -> -607390.62 | N46: =IF(C46>$F$23,0,-$F$38) -> 710056.42 | O46: =IF(N46=0,0,O45-P46) -> -53254.231 | P46: =N46/$F$23 -> 5917.1368
B47: =E47-D47+1 -> 30 | C47: 10 | D47: =EDATE(D46,1) -> 43922 | E47: =EOMONTH(D47,0) -> 43951 | F47: =J46 -> -665437.02 | G47: =$F$14 -> 7500 | H47: =G47+I46 -> 4727.3458 | I47: =(F47+G47+I46)*$F$12/12 -> -2752.957 | J47: =SUM(F47,H47) -> -660709.67 | K47: =J47-J59 -> -58288.255 | L47: =J47-K47 -> -602421.42 | N47: =IF(C47>$F$23,0,-$F$38) -> 710056.42 | O47: =IF(N47=0,0,O46-P47) -> -59171.368 | P47: =N47/$F$23 -> 5917.1368 | R47: Invoice Clearing Leasing (243031) | W47: Invoice Clearing Leasing - Technical (243032) | AB47: Accounts Payable*
B48: =E48-D48+1 -> 31 | C48: 11 | D48: =EDATE(D47,1) -> 43952 | E48: =EOMONTH(D48,0) -> 43982 | F48: =J47 -> -660709.67 | G48: =$F$14 -> 7500 | H48: =G48+I47 -> 4747.043 | I48: =(F48+G48+I47)*$F$12/12 -> -2733.1776 | J48: =SUM(F48,H48) -> -655962.63 | K48: =J48-J60 -> -58531.123 | L48: =J48-K48 -> -597431.51 | N48: =IF(C48>$F$23,0,-$F$38) -> 710056.42 | O48: =IF(N48=0,0,O47-P48) -> -65088.505 | P48: =N48/$F$23 -> 5917.1368 | R48: 7 | S48: =Y48 -> 7500 | T48: =AC43 -> 7500 | U48: 3 | W48: 6 | X48: =AD48-AC53 -> 7500 | Y48: =X48 -> 7500 | Z48: 7 | AD48: 9000 | AE48: 6
B49: =E49-D49+1 -> 30 | C49: 12 | D49: =EDATE(D48,1) -> 43983 | E49: =EOMONTH(D49,0) -> 44012 | F49: =J48 -> -655962.63 | G49: =$F$14 -> 7500 | H49: =G49+I48 -> 4766.8224 | I49: =(F49+G49+I48)*$F$12/12 -> -2713.3159 | J49: =SUM(F49,H49) -> -651195.81 | K49: =J49-J61 -> -58775.003 | L49: =J49-K49 -> -592420.8 | N49: =IF(C49>$F$23,0,-$F$38) -> 710056.42 | O49: =IF(N49=0,0,O48-P49) -> -71005.642 | P49: =N49/$F$23 -> 5917.1368 | R49: 13 | S49: =Y49 -> 7500 | T49: =SUM(AC44,X43) -> 7500 | U49: 9 | W49: 12 | X49: =AD49-AC54 -> 7500 | Y49: =X49 -> 7500 | Z49: 13 | AD49: 9000 | AE49: 12
B50: =E50-D50+1 -> 31 | C50: 13 | D50: =EDATE(D49,1) -> 44013 | E50: =EOMONTH(D50,0) -> 44043 | F50: =J49 -> -651195.81 | G50: =$F$14 -> 7500 | H50: =G50+I49 -> 4786.6841 | I50: =(F50+G50+I49)*$F$12/12 -> -2693.3713 | J50: =SUM(F50,H50) -> -646409.12 | K50: =J50-J62 -> -59019.899 | L50: =J50-K50 -> -587389.22 | N50: =IF(C50>$F$23,0,-$F$38) -> 710056.42 | O50: =IF(N50=0,0,O49-P50) -> -76922.779 | P50: =N50/$F$23 -> 5917.1368
B51: =E51-D51+1 -> 31 | C51: 14 | D51: =EDATE(D50,1) -> 44044 | E51: =EOMONTH(D51,0) -> 44074 | F51: =J50 -> -646409.12 | G51: =$F$14 -> 7500 | H51: =G51+I50 -> 4806.6287 | I51: =(F51+G51+I50)*$F$12/12 -> -2673.3437 | J51: =SUM(F51,H51) -> -641602.49 | K51: =J51-J63 -> -59265.815 | L51: =J51-K51 -> -582336.68 | N51: =IF(C51>$F$23,0,-$F$38) -> 710056.42 | O51: =IF(N51=0,0,O50-P51) -> -82839.916 | P51: =N51/$F$23 -> 5917.1368
B52: =E52-D52+1 -> 30 | C52: 15 | D52: =EDATE(D51,1) -> 44075 | E52: =EOMONTH(D52,0) -> 44104 | F52: =J51 -> -641602.49 | G52: =$F$14 -> 7500 | H52: =G52+I51 -> 4826.6563 | I52: =(F52+G52+I51)*$F$12/12 -> -2653.2327 | J52: =SUM(F52,H52) -> -636775.84 | K52: =J52-J64 -> -59512.756 | L52: =J52-K52 -> -577263.08 | N52: =IF(C52>$F$23,0,-$F$38) -> 710056.42 | O52: =IF(N52=0,0,O51-P52) -> -88757.052 | P52: =N52/$F$23 -> 5917.1368 | R52: Depreciation ROU Lease (P&L) (534080) | W52: Acc. Depreciation ROU Buildings 211520 (BS) | AB52: Input VAT (example - different by entity)
B53: =E53-D53+1 -> 31 | C53: 16 | D53: =EDATE(D52,1) -> 44105 | E53: =EOMONTH(D53,0) -> 44135 | F53: =J52 -> -636775.84 | G53: =$F$14 -> 7500 | H53: =G53+I52 -> 4846.7673 | I53: =(F53+G53+I52)*$F$12/12 -> -2633.0378 | J53: =SUM(F53,H53) -> -631929.07 | K53: =J53-J65 -> -59760.726 | L53: =J53-K53 -> -572168.35 | N53: =IF(C53>$F$23,0,-$F$38) -> 710056.42 | O53: =IF(N53=0,0,O52-P53) -> -94674.189 | P53: =N53/$F$23 -> 5917.1368 | R53: 8 | S53: =P38 -> 5917.1368 | Y53: =S53 -> 5917.1368 | Z53: 8 | AB53: 6 | AC53: =AD49*20/120 -> 1500
B54: =E54-D54+1 -> 30 | C54: 17 | D54: =EDATE(D53,1) -> 44136 | E54: =EOMONTH(D54,0) -> 44165 | F54: =J53 -> -631929.07 | G54: =$F$14 -> 7500 | H54: =G54+I53 -> 4866.9622 | I54: =(F54+G54+I53)*$F$12/12 -> -2612.7588 | J54: =SUM(F54,H54) -> -627062.11 | K54: =J54-J66 -> -60009.729 | L54: =J54-K54 -> -567052.38 | N54: =IF(C54>$F$23,0,-$F$38) -> 710056.42 | O54: =IF(N54=0,0,O53-P54) -> -100591.33 | P54: =N54/$F$23 -> 5917.1368 | R54: 14 | S54: =P39 -> 5917.1368 | Y54: =S54 -> 5917.1368 | Z54: 14 | AB54: 12 | AC54: =AD49*20/120 -> 1500
B55: =E55-D55+1 -> 31 | C55: 18 | D55: =EDATE(D54,1) -> 44166 | E55: =EOMONTH(D55,0) -> 44196 | F55: =J54 -> -627062.11 | G55: =$F$14 -> 7500 | H55: =G55+I54 -> 4887.2412 | I55: =(F55+G55+I54)*$F$12/12 -> -2592.3953 | J55: =SUM(F55,H55) -> -622174.87 | K55: =J55-J67 -> -60259.769 | L55: =J55-K55 -> -561915.1 | N55: =IF(C55>$F$23,0,-$F$38) -> 710056.42 | O55: =IF(N55=0,0,O54-P55) -> -106508.46 | P55: =N55/$F$23 -> 5917.1368
B56: =E56-D56+1 -> 31 | C56: 19 | D56: =EDATE(D55,1) -> 44197 | E56: =EOMONTH(D56,0) -> 44227 | F56: =J55 -> -622174.87 | G56: =$F$14 -> 7500 | H56: =G56+I55 -> 4907.6047 | I56: =(F56+G56+I55)*$F$12/12 -> -2571.9469 | J56: =SUM(F56,H56) -> -617267.26 | K56: =J56-J68 -> -60510.852 | L56: =J56-K56 -> -556756.41 | N56: =IF(C56>$F$23,0,-$F$38) -> 710056.42 | O56: =IF(N56=0,0,O55-P56) -> -112425.6 | P56: =N56/$F$23 -> 5917.1368
B57: =E57-D57+1 -> 28 | C57: 20 | D57: =EDATE(D56,1) -> 44228 | E57: =EOMONTH(D57,0) -> 44255 | F57: =J56 -> -617267.26 | G57: =$F$14 -> 7500 | H57: =G57+I56 -> 4928.0531 | I57: =(F57+G57+I56)*$F$12/12 -> -2551.4134 | J57: =SUM(F57,H57) -> -612339.21 | K57: =J57-J69 -> -60762.98 | L57: =J57-K57 -> -551576.23 | N57: =IF(C57>$F$23,0,-$F$38) -> 710056.42 | O57: =IF(N57=0,0,O56-P57) -> -118342.74 | P57: =N57/$F$23 -> 5917.1368
B58: =E58-D58+1 -> 31 | C58: 21 | D58: =EDATE(D57,1) -> 44256 | E58: =EOMONTH(D58,0) -> 44286 | F58: =J57 -> -612339.21 | G58: =$F$14 -> 7500 | H58: =G58+I57 -> 4948.5866 | I58: =(F58+G58+I57)*$F$12/12 -> -2530.7943 | J58: =SUM(F58,H58) -> -607390.62 | K58: =J58-J70 -> -61016.159 | L58: =J58-K58 -> -546374.46 | N58: =IF(C58>$F$23,0,-$F$38) -> 710056.42 | O58: =IF(N58=0,0,O57-P58) -> -124259.87 | P58: =N58/$F$23 -> 5917.1368 | R58: Accrual Approach
B59: =E59-D59+1 -> 30 | C59: 22 | D59: =EDATE(D58,1) -> 44287 | E59: =EOMONTH(D59,0) -> 44316 | F59: =J58 -> -607390.62 | G59: =$F$14 -> 7500 | H59: =G59+I58 -> 4969.2057 | I59: =(F59+G59+I58)*$F$12/12 -> -2510.0892 | J59: =SUM(F59,H59) -> -602421.42 | K59: =J59-J71 -> -61270.393 | L59: =J59-K59 -> -541151.02 | N59: =IF(C59>$F$23,0,-$F$38) -> 710056.42 | O59: =IF(N59=0,0,O58-P59) -> -130177.01 | P59: =N59/$F$23 -> 5917.1368 | R59: Lease expense postings for Accrual Approach are triggered by LAT based on contract payment terms (posting performed when expense is incurred - similar to GR)
B60: =E60-D60+1 -> 31 | C60: 23 | D60: =EDATE(D59,1) -> 44317 | E60: =EOMONTH(D60,0) -> 44347 | F60: =J59 -> -602421.42 | G60: =$F$14 -> 7500 | H60: =G60+I59 -> 4989.9108 | I60: =(F60+G60+I59)*$F$12/12 -> -2489.2979 | J60: =SUM(F60,H60) -> -597431.51 | K60: =J60-J72 -> -61525.686 | L60: =J60-K60 -> -535905.82 | N60: =IF(C60>$F$23,0,-$F$38) -> 710056.42 | O60: =IF(N60=0,0,O59-P60) -> -136094.15 | P60: =N60/$F$23 -> 5917.1368 | R60: All amounts below are in contract currency (DC)
B61: =E61-D61+1 -> 30 | C61: 24 | D61: =EDATE(D60,1) -> 44348 | E61: =EOMONTH(D61,0) -> 44377 | F61: =J60 -> -597431.51 | G61: =$F$14 -> 7500 | H61: =G61+I60 -> 5010.7021 | I61: =(F61+G61+I60)*$F$12/12 -> -2468.42 | J61: =SUM(F61,H61) -> -592420.8 | K61: =J61-J73 -> -61782.043 | L61: =J61-K61 -> -530638.76 | N61: =IF(C61>$F$23,0,-$F$38) -> 710056.42 | O61: =IF(N61=0,0,O60-P61) -> -142011.28 | P61: =N61/$F$23 -> 5917.1368 | R61: Please check LC2, LC3 FX posting conversion where applicable | AA61: Asset class name | AC61: Buildings
B62: =E62-D62+1 -> 31 | C62: 25 | D62: =EDATE(D61,1) -> 44378 | E62: =EOMONTH(D62,0) -> 44408 | F62: =J61 -> -592420.8 | G62: =$F$14 -> 7500 | H62: =G62+I61 -> 5031.58 | I62: =(F62+G62+I61)*$F$12/12 -> -2447.4551 | J62: =SUM(F62,H62) -> -587389.22 | K62: =J62-J74 -> -62039.469 | L62: =J62-K62 -> -525349.76 | N62: =IF(C62>$F$23,0,-$F$38) -> 710056.42 | O62: =IF(N62=0,0,O61-P62) -> -147928.42 | P62: =N62/$F$23 -> 5917.1368 | W62: SAP Posting date | AA62: Asset class no. | AC62: 103020
B63: =E63-D63+1 -> 31 | C63: 26 | D63: =EDATE(D62,1) -> 44409 | E63: =EOMONTH(D63,0) -> 44439 | F63: =J62 -> -587389.22 | G63: =$F$14 -> 7500 | H63: =G63+I62 -> 5052.5449 | I63: =(F63+G63+I62)*$F$12/12 -> -2426.4028 | J63: =SUM(F63,H63) -> -582336.68 | K63: =J63-J75 -> -62297.966 | L63: =J63-K63 -> -520038.71 | N63: =IF(C63>$F$23,0,-$F$38) -> 710056.42 | O63: =IF(N63=0,0,O62-P63) -> -153845.56 | P63: =N63/$F$23 -> 5917.1368 | R63: Description | W63: P7 | Y63: P8 | AA63: Material group name | AC63: LeaseBuild FixedCost
B64: =E64-D64+1 -> 30 | C64: 27 | D64: =EDATE(D63,1) -> 44440 | E64: =EOMONTH(D64,0) -> 44469 | F64: =J63 -> -582336.68 | G64: =$F$14 -> 7500 | H64: =G64+I63 -> 5073.5972 | I64: =(F64+G64+I63)*$F$12/12 -> -2405.2628 | J64: =SUM(F64,H64) -> -577263.08 | K64: =J64-J76 -> -62557.541 | L64: =J64-K64 -> -514705.54 | N64: =IF(C64>$F$23,0,-$F$38) -> 710056.42 | O64: =IF(N64=0,0,O63-P64) -> -159762.69 | P64: =N64/$F$23 -> 5917.1368 | R64: Monthly Lease expense posting | V64: 1 | W64: 43678 | X64: 4 | Y64: 43708 | AA64: Material group no. | AC64: 95101111
B65: =E65-D65+1 -> 31 | C65: 28 | D65: =EDATE(D64,1) -> 44470 | E65: =EOMONTH(D65,0) -> 44500 | F65: =J64 -> -577263.08 | G65: =$F$14 -> 7500 | H65: =G65+I64 -> 5094.7372 | I65: =(F65+G65+I64)*$F$12/12 -> -2384.0348 | J65: =SUM(F65,H65) -> -572168.35 | K65: =J65-J77 -> -62818.198 | L65: =J65-K65 -> -509350.15 | N65: =IF(C65>$F$23,0,-$F$38) -> 710056.42 | O65: =IF(N65=0,0,O64-P65) -> -165679.83 | P65: =N65/$F$23 -> 5917.1368 | R65: AP: invoice booking | V65: 2 | W65: =$D$38 -> 43647 | X65: 5 | Y65: =$D$39 -> 43678 | AA65: Lease payment per period (excl. VAT) | AD65: 7500
B66: =E66-D66+1 -> 30 | C66: 29 | D66: =EDATE(D65,1) -> 44501 | E66: =EOMONTH(D66,0) -> 44530 | F66: =J65 -> -572168.35 | G66: =$F$14 -> 7500 | H66: =G66+I65 -> 5115.9652 | I66: =(F66+G66+I65)*$F$12/12 -> -2362.7183 | J66: =SUM(F66,H66) -> -567052.38 | K66: =J66-J78 -> -63079.94 | L66: =J66-K66 -> -503972.44 | N66: =IF(C66>$F$23,0,-$F$38) -> 710056.42 | O66: =IF(N66=0,0,O65-P66) -> -171596.97 | P66: =N66/$F$23 -> 5917.1368 | R66: Automated reposting of AP | V66: 3 | W66: =$D$38 -> 43647 | X66: 6 | Y66: =$D$39 -> 43678 | AA66: Payment frequency | AD66: Monthly
B67: =E67-D67+1 -> 31 | C67: 30 | D67: =EDATE(D66,1) -> 44531 | E67: =EOMONTH(D67,0) -> 44561 | F67: =J66 -> -567052.38 | G67: =$F$14 -> 7500 | H67: =G67+I66 -> 5137.2817 | I67: =(F67+G67+I66)*$F$12/12 -> -2341.3129 | J67: =SUM(F67,H67) -> -561915.1 | K67: =J67-J79 -> -63342.773 | L67: =J67-K67 -> -498572.33 | N67: =IF(C67>$F$23,0,-$F$38) -> 710056.42 | O67: =IF(N67=0,0,O66-P67) -> -177514.1 | P67: =N67/$F$23 -> 5917.1368 | AA67: Payment timing | AD67: Advance
B68: =E68-D68+1 -> 31 | C68: 31 | D68: =EDATE(D67,1) -> 44562 | E68: =EOMONTH(D68,0) -> 44592 | F68: =J67 -> -561915.1 | G68: =$F$14 -> 7500 | H68: =G68+I67 -> 5158.6871 | I68: =(F68+G68+I67)*$F$12/12 -> -2319.8184 | J68: =SUM(F68,H68) -> -556756.41 | K68: =J68-J80 -> -63606.702 | L68: =J68-K68 -> -493149.71 | N68: =IF(C68>$F$23,0,-$F$38) -> 710056.42 | O68: =IF(N68=0,0,O67-P68) -> -183431.24 | P68: =N68/$F$23 -> 5917.1368 | AA68: Lease term (months) | AD68: 120
B69: =E69-D69+1 -> 28 | C69: 32 | D69: =EDATE(D68,1) -> 44593 | E69: =EOMONTH(D69,0) -> 44620 | F69: =J68 -> -556756.41 | G69: =$F$14 -> 7500 | H69: =G69+I68 -> 5180.1816 | I69: =(F69+G69+I68)*$F$12/12 -> -2298.2343 | J69: =SUM(F69,H69) -> -551576.23 | K69: =J69-J81 -> -63871.729 | L69: =J69-K69 -> -487704.5 | N69: =IF(C69>$F$23,0,-$F$38) -> 710056.42 | O69: =IF(N69=0,0,O68-P69) -> -189348.38 | P69: =N69/$F$23 -> 5917.1368 | AA69: Lease start date | AD69: 43647
B70: =E70-D70+1 -> 31 | C70: 33 | D70: =EDATE(D69,1) -> 44621 | E70: =EOMONTH(D70,0) -> 44651 | F70: =J69 -> -551576.23 | G70: =$F$14 -> 7500 | H70: =G70+I69 -> 5201.7657 | I70: =(F70+G70+I69)*$F$12/12 -> -2276.5603 | J70: =SUM(F70,H70) -> -546374.46 | K70: =J70-J82 -> -64137.862 | L70: =J70-K70 -> -482236.6 | N70: =IF(C70>$F$23,0,-$F$38) -> 710056.42 | O70: =IF(N70=0,0,O69-P70) -> -195265.52 | P70: =N70/$F$23 -> 5917.1368 | AA70: Lease end date | AD70: 47299
B71: =E71-D71+1 -> 30 | C71: 34 | D71: =EDATE(D70,1) -> 44652 | E71: =EOMONTH(D71,0) -> 44681 | F71: =J70 -> -546374.46 | G71: =$F$14 -> 7500 | H71: =G71+I70 -> 5223.4397 | I71: =(F71+G71+I70)*$F$12/12 -> -2254.7959 | J71: =SUM(F71,H71) -> -541151.02 | K71: =J71-J83 -> -64405.103 | L71: =J71-K71 -> -476745.92 | N71: =IF(C71>$F$23,0,-$F$38) -> 710056.42 | O71: =IF(N71=0,0,O70-P71) -> -201182.65 | P71: =N71/$F$23 -> 5917.1368 | AA71: Calculated NPV | AD71: -710056.42
B72: =E72-D72+1 -> 31 | C72: 35 | D72: =EDATE(D71,1) -> 44682 | E72: =EOMONTH(D72,0) -> 44712 | F72: =J71 -> -541151.02 | G72: =$F$14 -> 7500 | H72: =G72+I71 -> 5245.2041 | I72: =(F72+G72+I71)*$F$12/12 -> -2232.9409 | J72: =SUM(F72,H72) -> -535905.82 | K72: =J72-J84 -> -64673.457 | L72: =J72-K72 -> -471232.36 | N72: =IF(C72>$F$23,0,-$F$38) -> 710056.42 | O72: =IF(N72=0,0,O71-P72) -> -207099.79 | P72: =N72/$F$23 -> 5917.1368
B73: =E73-D73+1 -> 30 | C73: 36 | D73: =EDATE(D72,1) -> 44713 | E73: =EOMONTH(D73,0) -> 44742 | F73: =J72 -> -535905.82 | G73: =$F$14 -> 7500 | H73: =G73+I72 -> 5267.0591 | I73: =(F73+G73+I72)*$F$12/12 -> -2210.9948 | J73: =SUM(F73,H73) -> -530638.76 | K73: =J73-J85 -> -64942.93 | L73: =J73-K73 -> -465695.83 | N73: =IF(C73>$F$23,0,-$F$38) -> 710056.42 | O73: =IF(N73=0,0,O72-P73) -> -213016.93 | P73: =N73/$F$23 -> 5917.1368 | R73: Invoice Clearing Leasing (243031) | W73: Invoice Clearing Leasing - Technical (243032) | AB73: Accounts Payable*
B74: =E74-D74+1 -> 31 | C74: 37 | D74: =EDATE(D73,1) -> 44743 | E74: =EOMONTH(D74,0) -> 44773 | F74: =J73 -> -530638.76 | G74: =$F$14 -> 7500 | H74: =G74+I73 -> 5289.0052 | I74: =(F74+G74+I73)*$F$12/12 -> -2188.9573 | J74: =SUM(F74,H74) -> -525349.76 | K74: =J74-J86 -> -65213.526 | L74: =J74-K74 -> -460136.23 | N74: =IF(C74>$F$23,0,-$F$38) -> 710056.42 | O74: =IF(N74=0,0,O73-P74) -> -218934.06 | P74: =N74/$F$23 -> 5917.1368 | R74: 3 | S74: =G38 -> 7500 | T74: =G38 -> 7500 | U74: 1 | W74: 2 | X74: =AD74-AC80 -> 7500 | Y74: =S74 -> 7500 | Z74: 3 | AD74: 9000 | AE74: 2
B75: =E75-D75+1 -> 31 | C75: 38 | D75: =EDATE(D74,1) -> 44774 | E75: =EOMONTH(D75,0) -> 44804 | F75: =J74 -> -525349.76 | G75: =$F$14 -> 7500 | H75: =G75+I74 -> 5311.0427 | I75: =(F75+G75+I74)*$F$12/12 -> -2166.828 | J75: =SUM(F75,H75) -> -520038.71 | K75: =J75-J87 -> -65485.249 | L75: =J75-K75 -> -454553.46 | N75: =IF(C75>$F$23,0,-$F$38) -> 710056.42 | O75: =IF(N75=0,0,O74-P75) -> -224851.2 | P75: =N75/$F$23 -> 5917.1368 | R75: 6 | S75: =G39 -> 7500 | T75: =G39 -> 7500 | U75: 4 | W75: 5 | X75: =AD75-AC81 -> 7500 | Y75: =S75 -> 7500 | Z75: 6 | AD75: 9000 | AE75: 5
B76: =E76-D76+1 -> 30 | C76: 39 | D76: =EDATE(D75,1) -> 44805 | E76: =EOMONTH(D76,0) -> 44834 | F76: =J75 -> -520038.71 | G76: =$F$14 -> 7500 | H76: =G76+I75 -> 5333.172 | I76: =(F76+G76+I75)*$F$12/12 -> -2144.6064 | J76: =SUM(F76,H76) -> -514705.54 | K76: =J76-J88 -> -65758.104 | L76: =J76-K76 -> -448947.44 | N76: =IF(C76>$F$23,0,-$F$38) -> 710056.42 | O76: =IF(N76=0,0,O75-P76) -> -230768.34 | P76: =N76/$F$23 -> 5917.1368
B77: =E77-D77+1 -> 31 | C77: 40 | D77: =EDATE(D76,1) -> 44835 | E77: =EOMONTH(D77,0) -> 44865 | F77: =J76 -> -514705.54 | G77: =$F$14 -> 7500 | H77: =G77+I76 -> 5355.3936 | I77: =(F77+G77+I76)*$F$12/12 -> -2122.2923 | J77: =SUM(F77,H77) -> -509350.15 | K77: =J77-J89 -> -66032.096 | L77: =J77-K77 -> -443318.05 | N77: =IF(C77>$F$23,0,-$F$38) -> 710056.42 | O77: =IF(N77=0,0,O76-P77) -> -236685.47 | P77: =N77/$F$23 -> 5917.1368
B78: =E78-D78+1 -> 30 | C78: 41 | D78: =EDATE(D77,1) -> 44866 | E78: =EOMONTH(D78,0) -> 44895 | F78: =J77 -> -509350.15 | G78: =$F$14 -> 7500 | H78: =G78+I77 -> 5377.7077 | I78: =(F78+G78+I77)*$F$12/12 -> -2099.8852 | J78: =SUM(F78,H78) -> -503972.44 | K78: =J78-J90 -> -66307.23 | L78: =J78-K78 -> -437665.21 | N78: =IF(C78>$F$23,0,-$F$38) -> 710056.42 | O78: =IF(N78=0,0,O77-P78) -> -242602.61 | P78: =N78/$F$23 -> 5917.1368
B79: =E79-D79+1 -> 31 | C79: 42 | D79: =EDATE(D78,1) -> 44896 | E79: =EOMONTH(D79,0) -> 44926 | F79: =J78 -> -503972.44 | G79: =$F$14 -> 7500 | H79: =G79+I78 -> 5400.1148 | I79: =(F79+G79+I78)*$F$12/12 -> -2077.3847 | J79: =SUM(F79,H79) -> -498572.33 | K79: =J79-J91 -> -66583.51 | L79: =J79-K79 -> -431988.82 | N79: =IF(C79>$F$23,0,-$F$38) -> 710056.42 | O79: =IF(N79=0,0,O78-P79) -> -248519.75 | P79: =N79/$F$23 -> 5917.1368 | R79: Lease expense - Buildings Stat/Tax (534035) | AB79: Input VAT (example - different by entity)
B80: =E80-D80+1 -> 31 | C80: 43 | D80: =EDATE(D79,1) -> 44927 | E80: =EOMONTH(D80,0) -> 44957 | F80: =J79 -> -498572.33 | G80: =$F$14 -> 7500 | H80: =G80+I79 -> 5422.6153 | I80: =(F80+G80+I79)*$F$12/12 -> -2054.7905 | J80: =SUM(F80,H80) -> -493149.71 | K80: =J80-J92 -> -66860.941 | L80: =J80-K80 -> -426288.77 | N80: =IF(C80>$F$23,0,-$F$38) -> 710056.42 | O80: =IF(N80=0,0,O79-P80) -> -254436.88 | P80: =N80/$F$23 -> 5917.1368 | R80: 1 | S80: =T74 -> 7500 | AB80: 2 | AC80: 1500
B81: =E81-D81+1 -> 28 | C81: 44 | D81: =EDATE(D80,1) -> 44958 | E81: =EOMONTH(D81,0) -> 44985 | F81: =J80 -> -493149.71 | G81: =$F$14 -> 7500 | H81: =G81+I80 -> 5445.2095 | I81: =(F81+G81+I80)*$F$12/12 -> -2032.1021 | J81: =SUM(F81,H81) -> -487704.5 | K81: =J81-J93 -> -67139.528 | L81: =J81-K81 -> -420564.97 | N81: =IF(C81>$F$23,0,-$F$38) -> 710056.42 | O81: =IF(N81=0,0,O80-P81) -> -260354.02 | P81: =N81/$F$23 -> 5917.1368 | R81: 4 | S81: =T75 -> 7500 | AB81: 5 | AC81: 1500
B82: =E82-D82+1 -> 31 | C82: 45 | D82: =EDATE(D81,1) -> 44986 | E82: =EOMONTH(D82,0) -> 45016 | F82: =J81 -> -487704.5 | G82: =$F$14 -> 7500 | H82: =G82+I81 -> 5467.8979 | I82: =(F82+G82+I81)*$F$12/12 -> -2009.3192 | J82: =SUM(F82,H82) -> -482236.6 | K82: =J82-J94 -> -67419.276 | L82: =J82-K82 -> -414817.33 | N82: =IF(C82>$F$23,0,-$F$38) -> 710056.42 | O82: =IF(N82=0,0,O81-P82) -> -266271.16 | P82: =N82/$F$23 -> 5917.1368
B83: =E83-D83+1 -> 30 | C83: 46 | D83: =EDATE(D82,1) -> 45017 | E83: =EOMONTH(D83,0) -> 45046 | F83: =J82 -> -482236.6 | G83: =$F$14 -> 7500 | H83: =G83+I82 -> 5490.6808 | I83: =(F83+G83+I82)*$F$12/12 -> -1986.4413 | J83: =SUM(F83,H83) -> -476745.92 | K83: =J83-J95 -> -67700.19 | L83: =J83-K83 -> -409045.73 | N83: =IF(C83>$F$23,0,-$F$38) -> 710056.42 | O83: =IF(N83=0,0,O82-P83) -> -272188.29 | P83: =N83/$F$23 -> 5917.1368
B84: =E84-D84+1 -> 31 | C84: 47 | D84: =EDATE(D83,1) -> 45047 | E84: =EOMONTH(D84,0) -> 45077 | F84: =J83 -> -476745.92 | G84: =$F$14 -> 7500 | H84: =G84+I83 -> 5513.5587 | I84: =(F84+G84+I83)*$F$12/12 -> -1963.4682 | J84: =SUM(F84,H84) -> -471232.36 | K84: =J84-J96 -> -67982.274 | L84: =J84-K84 -> -403250.09 | N84: =IF(C84>$F$23,0,-$F$38) -> 710056.42 | O84: =IF(N84=0,0,O83-P84) -> -278105.43 | P84: =N84/$F$23 -> 5917.1368
B85: =E85-D85+1 -> 30 | C85: 48 | D85: =EDATE(D84,1) -> 45078 | E85: =EOMONTH(D85,0) -> 45107 | F85: =J84 -> -471232.36 | G85: =$F$14 -> 7500 | H85: =G85+I84 -> 5536.5318 | I85: =(F85+G85+I84)*$F$12/12 -> -1940.3993 | J85: =SUM(F85,H85) -> -465695.83 | K85: =J85-J97 -> -68265.534 | L85: =J85-K85 -> -397430.3 | N85: =IF(C85>$F$23,0,-$F$38) -> 710056.42 | O85: =IF(N85=0,0,O84-P85) -> -284022.57 | P85: =N85/$F$23 -> 5917.1368
B86: =E86-D86+1 -> 31 | C86: 49 | D86: =EDATE(D85,1) -> 45108 | E86: =EOMONTH(D86,0) -> 45138 | F86: =J85 -> -465695.83 | G86: =$F$14 -> 7500 | H86: =G86+I85 -> 5559.6007 | I86: =(F86+G86+I85)*$F$12/12 -> -1917.2343 | J86: =SUM(F86,H86) -> -460136.23 | K86: =J86-J98 -> -68549.973 | L86: =J86-K86 -> -391586.26 | N86: =IF(C86>$F$23,0,-$F$38) -> 710056.42 | O86: =IF(N86=0,0,O85-P86) -> -289939.7 | P86: =N86/$F$23 -> 5917.1368 | R86: Invoice Receipt Approach
B87: =E87-D87+1 -> 31 | C87: 50 | D87: =EDATE(D86,1) -> 45139 | E87: =EOMONTH(D87,0) -> 45169 | F87: =J86 -> -460136.23 | G87: =$F$14 -> 7500 | H87: =G87+I86 -> 5582.7657 | I87: =(F87+G87+I86)*$F$12/12 -> -1893.9728 | J87: =SUM(F87,H87) -> -454553.46 | K87: =J87-J99 -> -68835.598 | L87: =J87-K87 -> -385717.87 | N87: =IF(C87>$F$23,0,-$F$38) -> 710056.42 | O87: =IF(N87=0,0,O86-P87) -> -295856.84 | P87: =N87/$F$23 -> 5917.1368 | R87: Lease expense recognition for IR approach is triggered by the invoice posting
B88: =E88-D88+1 -> 30 | C88: 51 | D88: =EDATE(D87,1) -> 45170 | E88: =EOMONTH(D88,0) -> 45199 | F88: =J87 -> -454553.46 | G88: =$F$14 -> 7500 | H88: =G88+I87 -> 5606.0272 | I88: =(F88+G88+I87)*$F$12/12 -> -1870.6143 | J88: =SUM(F88,H88) -> -448947.44 | K88: =J88-J100 -> -69122.413 | L88: =J88-K88 -> -379825.02 | N88: =IF(C88>$F$23,0,-$F$38) -> 710056.42 | O88: =IF(N88=0,0,O87-P88) -> -301773.98 | P88: =N88/$F$23 -> 5917.1368 | R88: All amounts below are in contract currency (DC)
B89: =E89-D89+1 -> 31 | C89: 52 | D89: =EDATE(D88,1) -> 45200 | E89: =EOMONTH(D89,0) -> 45230 | F89: =J88 -> -448947.44 | G89: =$F$14 -> 7500 | H89: =G89+I88 -> 5629.3857 | I89: =(F89+G89+I88)*$F$12/12 -> -1847.1585 | J89: =SUM(F89,H89) -> -443318.05 | K89: =J89-J101 -> -69410.423 | L89: =J89-K89 -> -373907.63 | N89: =IF(C89>$F$23,0,-$F$38) -> 710056.42 | O89: =IF(N89=0,0,O88-P89) -> -307691.12 | P89: =N89/$F$23 -> 5917.1368 | R89: Please check LC2, LC3 FX posting conversion where applicable | AA89: Asset class name | AC89: Buildings
B90: =E90-D90+1 -> 30 | C90: 53 | D90: =EDATE(D89,1) -> 45231 | E90: =EOMONTH(D90,0) -> 45260 | F90: =J89 -> -443318.05 | G90: =$F$14 -> 7500 | H90: =G90+I89 -> 5652.8415 | I90: =(F90+G90+I89)*$F$12/12 -> -1823.605 | J90: =SUM(F90,H90) -> -437665.21 | K90: =J90-J102 -> -69699.633 | L90: =J90-K90 -> -367965.58 | N90: =IF(C90>$F$23,0,-$F$38) -> 710056.42 | O90: =IF(N90=0,0,O89-P90) -> -313608.25 | P90: =N90/$F$23 -> 5917.1368 | W90: SAP Posting date | AA90: Asset class no. | AC90: 103020
B91: =E91-D91+1 -> 31 | C91: 54 | D91: =EDATE(D90,1) -> 45261 | E91: =EOMONTH(D91,0) -> 45291 | F91: =J90 -> -437665.21 | G91: =$F$14 -> 7500 | H91: =G91+I90 -> 5676.395 | I91: =(F91+G91+I90)*$F$12/12 -> -1799.9534 | J91: =SUM(F91,H91) -> -431988.82 | K91: =J91-J103 -> -69990.049 | L91: =J91-K91 -> -361998.77 | N91: =IF(C91>$F$23,0,-$F$38) -> 710056.42 | O91: =IF(N91=0,0,O90-P91) -> -319525.39 | P91: =N91/$F$23 -> 5917.1368 | R91: Description | W91: P7 | Y91: P8 | AA91: Material group name | AC91: LeaseBuild FixedCost
B92: =E92-D92+1 -> 31 | C92: 55 | D92: =EDATE(D91,1) -> 45292 | E92: =EOMONTH(D92,0) -> 45322 | F92: =J91 -> -431988.82 | G92: =$F$14 -> 7500 | H92: =G92+I91 -> 5700.0466 | I92: =(F92+G92+I91)*$F$12/12 -> -1776.2032 | J92: =SUM(F92,H92) -> -426288.77 | K92: =J92-J104 -> -70281.674 | L92: =J92-K92 -> -356007.1 | N92: =IF(C92>$F$23,0,-$F$38) -> 710056.42 | O92: =IF(N92=0,0,O91-P92) -> -325442.53 | P92: =N92/$F$23 -> 5917.1368 | R92: AP: invoice booking | V92: 1 | W92: =$D$38 -> 43647 | X92: 3 | Y92: =$D$39 -> 43678 | AA92: Material group no. | AC92: 95101111
B93: =E93-D93+1 -> 29 | C93: 56 | D93: =EDATE(D92,1) -> 45323 | E93: =EOMONTH(D93,0) -> 45351 | F93: =J92 -> -426288.77 | G93: =$F$14 -> 7500 | H93: =G93+I92 -> 5723.7968 | I93: =(F93+G93+I92)*$F$12/12 -> -1752.354 | J93: =SUM(F93,H93) -> -420564.97 | K93: =J93-J105 -> -70574.514 | L93: =J93-K93 -> -349990.46 | N93: =IF(C93>$F$23,0,-$F$38) -> 710056.42 | O93: =IF(N93=0,0,O92-P93) -> -331359.66 | P93: =N93/$F$23 -> 5917.1368 | R93: Automated reposting of Invoice to P&L | V93: 2 | W93: =$D$38 -> 43647 | X93: 4 | Y93: =$D$39 -> 43678 | AA93: Lease payment per period (excl. VAT) | AD93: 7500
B94: =E94-D94+1 -> 31 | C94: 57 | D94: =EDATE(D93,1) -> 45352 | E94: =EOMONTH(D94,0) -> 45382 | F94: =J93 -> -420564.97 | G94: =$F$14 -> 7500 | H94: =G94+I93 -> 5747.646 | I94: =(F94+G94+I93)*$F$12/12 -> -1728.4055 | J94: =SUM(F94,H94) -> -414817.33 | K94: =J94-J106 -> -70868.575 | L94: =J94-K94 -> -343948.75 | N94: =IF(C94>$F$23,0,-$F$38) -> 710056.42 | O94: =IF(N94=0,0,O93-P94) -> -337276.8 | P94: =N94/$F$23 -> 5917.1368 | AA94: Payment frequency | AD94: Monthly
B95: =E95-D95+1 -> 30 | C95: 58 | D95: =EDATE(D94,1) -> 45383 | E95: =EOMONTH(D95,0) -> 45412 | F95: =J94 -> -414817.33 | G95: =$F$14 -> 7500 | H95: =G95+I94 -> 5771.5945 | I95: =(F95+G95+I94)*$F$12/12 -> -1704.3572 | J95: =SUM(F95,H95) -> -409045.73 | K95: =J95-J107 -> -71163.86 | L95: =J95-K95 -> -337881.87 | N95: =IF(C95>$F$23,0,-$F$38) -> 710056.42 | O95: =IF(N95=0,0,O94-P95) -> -343193.94 | P95: =N95/$F$23 -> 5917.1368 | AA95: Payment timing | AD95: Advance
B96: =E96-D96+1 -> 31 | C96: 59 | D96: =EDATE(D95,1) -> 45413 | E96: =EOMONTH(D96,0) -> 45443 | F96: =J95 -> -409045.73 | G96: =$F$14 -> 7500 | H96: =G96+I95 -> 5795.6428 | I96: =(F96+G96+I95)*$F$12/12 -> -1680.2087 | J96: =SUM(F96,H96) -> -403250.09 | K96: =J96-J108 -> -71460.376 | L96: =J96-K96 -> -331789.71 | N96: =IF(C96>$F$23,0,-$F$38) -> 710056.42 | O96: =IF(N96=0,0,O95-P96) -> -349111.07 | P96: =N96/$F$23 -> 5917.1368 | AA96: Lease term (months) | AD96: 120
B97: =E97-D97+1 -> 30 | C97: 60 | D97: =EDATE(D96,1) -> 45444 | E97: =EOMONTH(D97,0) -> 45473 | F97: =J96 -> -403250.09 | G97: =$F$14 -> 7500 | H97: =G97+I96 -> 5819.7913 | I97: =(F97+G97+I96)*$F$12/12 -> -1655.9596 | J97: =SUM(F97,H97) -> -397430.3 | K97: =J97-J109 -> -71758.128 | L97: =J97-K97 -> -325672.17 | N97: =IF(C97>$F$23,0,-$F$38) -> 710056.42 | O97: =IF(N97=0,0,O96-P97) -> -355028.21 | P97: =N97/$F$23 -> 5917.1368 | AA97: Lease start date | AD97: 43647
B98: =E98-D98+1 -> 31 | C98: 61 | D98: =EDATE(D97,1) -> 45474 | E98: =EOMONTH(D98,0) -> 45504 | F98: =J97 -> -397430.3 | G98: =$F$14 -> 7500 | H98: =G98+I97 -> 5844.0404 | I98: =(F98+G98+I97)*$F$12/12 -> -1631.6094 | J98: =SUM(F98,H98) -> -391586.26 | K98: =J98-J110 -> -72057.12 | L98: =J98-K98 -> -319529.14 | N98: =IF(C98>$F$23,0,-$F$38) -> 710056.42 | O98: =IF(N98=0,0,O97-P98) -> -360945.35 | P98: =N98/$F$23 -> 5917.1368 | AA98: Lease end date | AD98: 47299
B99: =E99-D99+1 -> 31 | C99: 62 | D99: =EDATE(D98,1) -> 45505 | E99: =EOMONTH(D99,0) -> 45535 | F99: =J98 -> -391586.26 | G99: =$F$14 -> 7500 | H99: =G99+I98 -> 5868.3906 | I99: =(F99+G99+I98)*$F$12/12 -> -1607.1578 | J99: =SUM(F99,H99) -> -385717.87 | K99: =J99-J111 -> -72357.358 | L99: =J99-K99 -> -313360.51 | N99: =IF(C99>$F$23,0,-$F$38) -> 710056.42 | O99: =IF(N99=0,0,O98-P99) -> -366862.48 | P99: =N99/$F$23 -> 5917.1368 | AA99: Calculated NPV | AD99: -710056.42
B100: =E100-D100+1 -> 30 | C100: 63 | D100: =EDATE(D99,1) -> 45536 | E100: =EOMONTH(D100,0) -> 45565 | F100: =J99 -> -385717.87 | G100: =$F$14 -> 7500 | H100: =G100+I99 -> 5892.8422 | I100: =(F100+G100+I99)*$F$12/12 -> -1582.6043 | J100: =SUM(F100,H100) -> -379825.02 | K100: =J100-J112 -> -72658.847 | L100: =J100-K100 -> -307166.18 | N100: =IF(C100>$F$23,0,-$F$38) -> 710056.42 | O100: =IF(N100=0,0,O99-P100) -> -372779.62 | P100: =N100/$F$23 -> 5917.1368
B101: =E101-D101+1 -> 31 | C101: 64 | D101: =EDATE(D100,1) -> 45566 | E101: =EOMONTH(D101,0) -> 45596 | F101: =J100 -> -379825.02 | G101: =$F$14 -> 7500 | H101: =G101+I100 -> 5917.3957 | I101: =(F101+G101+I100)*$F$12/12 -> -1557.9485 | J101: =SUM(F101,H101) -> -373907.63 | K101: =J101-J113 -> -72961.592 | L101: =J101-K101 -> -300946.04 | N101: =IF(C101>$F$23,0,-$F$38) -> 710056.42 | O101: =IF(N101=0,0,O100-P101) -> -378696.76 | P101: =N101/$F$23 -> 5917.1368 | R101: Lease expense - Buildings Stat/Tax (534035) | W101: Invoice Clearing Leasing - Technical (243032) | AB101: Accounts Payable*
...

Sheet 2 - Low Value Contract
C1: 2 - Low Value Contract | BB1: Advance
C3: IFRS 16 Approach
C4: All amounts below are in contract currency (DC)
C5: Please check LC2, LC3 FX posting conversion where applicable | J5: Lease payment per period (excl. VAT) | L5: 250
F6: SAP Posting date | J6: Payment frequency | L6: Monthly
C7: Description | F7: P7 | H7: P8 | J7: Payment timing | L7: Advance
C8: Payment by Nakisa | E8: 1 | F8: 43647 | G8: 5 | H8: 43678 | J8: First payment Date | L8: 43647
C9: Invoice booking | E9: 2 | F9: 43647 | G9: 6 | H9: 43678 | J9: Lease term (months) | L9: 24
C10: Automated reposting of Invoice | E10: 3 | F10: 43647 | G10: 7 | H10: 43678 | J10: Lease start date | L10: 43647
C11: Monthly Exempt Lease Posting | E11: 4 | F11: 43677 | G11: 8 | H11: 43708 | J11: Lease end date | L11: 44377
C14: Exempt Lease - Low Value (P&L) (534090) | H14: Prepaid rent (BS) - (167021)
C15: 4 | D15: =L5 -> 250 | H15: 1 | I15: =E20 -> 250 | J15: =D15 -> 250 | K15: 4
C16: 8 | D16: =L5 -> 250 | H16: 5 | I16: =E21 -> 250 | J16: =D16 -> 250 | K16: 8
C19: Invoice Clearing Leasing (243031) | H19: Invoice Clearing Leasing - Technical (243032)
C20: 3 | D20: =L5 -> 250 | E20: =L5 -> 250 | F20: 1 | H20: 2 | I20: =E25-I25 -> 250 | J20: =D20 -> 250 | K20: 3
C21: 7 | D21: =L5 -> 250 | E21: =L5 -> 250 | F21: 5 | H21: 6 | I21: =E26-I26 -> 250 | J21: =D21 -> 250 | K21: 7
C24: Accounts Payable* | H24: Input VAT (example - different by entity)
E25: =L5*1.2 -> 300 | F25: 2 | H25: 2 | I25: =E25*20/120 -> 50
E26: =L5*1.2 -> 300 | F26: 6 | H26: 6 | I26: =E26*20/120 -> 50
C29: Accrual Approach
C30: Lease expense postings for Accrual Approach are triggered by LAT based on contract payment terms (posting performed when expense is incurred - similar to GR)
C31: All amounts below are in contract currency (DC)
C32: Please check LC2, LC3 FX posting conversion where applicable | J32: Lease payment per period (excl. VAT) | L32: 250
F33: SAP Posting date | J33: Payment frequency | L33: Monthly
C34: Description | F34: P7 | H34: P8 | J34: Payment timing | L34: Advance
C35: Payment by Nakisa | E35: 1 | F35: 43678 | G35: 5 | H35: 43678 | J35: First payment Date | L35: 43647
C36: Invoice booking | E36: 2 | F36: 43647 | G36: 6 | H36: 43678 | J36: Lease term (months) | L36: 24
C37: Automated reposting of Invoice | E37: 3 | F37: 43647 | G37: 7 | H37: 43678 | J37: Lease start date | L37: 43647
C38: Monthly Lease expense posting | E38: 4 | F38: 43678 | G38: 8 | H38: 43708 | J38: Lease end date | L38: 44377
C41: Lease expense - FurnFx Stat/Tax (534065) | H41: Prepaid Lease Cost (167021)
C42: 4 | D42: =J42 -> 250 | H42: 1 | I42: =E47 -> 250 | J42: =L32 -> 250 | K42: 4
C43: 8 | D43: =J43 -> 250 | H43: 5 | I43: =E48 -> 250 | J43: =L32 -> 250 | K43: 8
C46: Invoice Clearing Leasing (243031) | H46: Invoice Clearing Leasing - Technical (243032)
C47: 3 | D47: =J47 -> 250 | E47: =L32 -> 250 | F47: 1 | H47: 2 | I47: =E52-I52 -> 250 | J47: =L32 -> 250 | K47: 3
C48: 7 | D48: =J48 -> 250 | E48: =L32 -> 250 | F48: 5 | H48: 6 | I48: =E53-I52 -> 250 | J48: =L32 -> 250 | K48: 7
C51: Accounts Payable* | H51: Input VAT (example - different by entity)
E52: 300 | F52: 2 | H52: 2 | I52: 50
E53: 300 | F53: 6 | H53: 6 | I53: 50
C59: Invoice Receipt Approach
C60: Lease expense recognition for IR approach is triggered by the invoice posting
C61: All amounts below are in contract currency (DC)
C62: Please check LC2, LC3 FX posting conversion where applicable | J62: Lease payment per period (excl. VAT) | L62: 250
F63: SAP Posting date | J63: Payment frequency | L63: Monthly
C64: Description | F64: P7 | H64: P8 | J64: Payment timing | L64: Advance
C65: Invoice booking | E65: 1 | F65: 43647 | G65: 3 | H65: 43678 | J65: First payment Date | L65: 43647
C66: Automated reposting of Invoice to P&L | E66: 2 | F66: 43647 | G66: 4 | H66: 43678 | J66: Lease term (months) | L66: 24
J67: Lease start date | L67: 43647
J68: Lease end date | L68: 44377
C71: Lease expense - FurnFx Stat/Tax (534065) | H71: Invoice Clearing Leasing - Technical (243032)
C72: 2 | D72: =J72 -> 250 | H72: 1 | I72: =E77-I77 -> 250 | J72: =I72 -> 250 | K72: 2
C73: 4 | D73: =J73 -> 250 | H73: 3 | I73: =E78-I78 -> 250 | J73: =I73 -> 250 | K73: 4
C76: Accounts Payable* | H76: Input VAT (example - different by entity)
E77: 300 | F77: 1 | H77: 1 | I77: 50
E78: 300 | F78: 3 | H78: 3 | I78: 50

Sheet 3 - Short Term Contract
C1: 3 - Short Term Contract (non-recoverable VAT) | BB1: Advance
C3: IFRS 16 Approach
C4: All amounts below are in contract currency (DC)
C5: Please check LC2, LC3 FX posting conversion where applicable | J5: Lease payment per period | L5: 5000
F6: SAP Posting date | J6: Payment frequency | L6: Monthly
C7: Description | F7: P7 | H7: P8 | J7: Payment timing | L7: Advance
C8: Payment by Nakisa | E8: 1 | F8: 43647 | G8: 5 | H8: 43678 | J8: First payment Date | L8: 43647
C9: AP: invoice booking | E9: 2 | F9: 43647 | G9: 6 | H9: 43678 | J9: Lease term (months) | L9: 9
C10: Automated reposting of AP | E10: 3 | F10: 43647 | G10: 7 | H10: 43678 | J10: Lease start date | L10: 43647
C11: Monthly Exempt Lease Posting | E11: 4 | F11: 43677 | G11: 8 | H11: 43708 | J11: Lease end date | L11: 43921
C14: Exempt Lease - Short Term (P&L) (534095) | H14: Prepaid Lease Cost (BS) - (167021)
C15: 4 | D15: =L5 -> 5000 | H15: 1 | I15: =E20 -> 5000 | J15: =D15 -> 5000 | K15: 4
C16: 8 | D16: =L5 -> 5000 | H16: 5 | I16: =E21 -> 5000 | J16: =D16 -> 5000 | K16: 8
C19: Invoice Clearing Leasing (243031) | H19: Invoice Clearing Leasing - Technical (243032)
C20: 3 | D20: =J26 -> 5000 | E20: =L5 -> 5000 | F20: 1 | H20: 2 | I20: =J26 -> 5000 | J20: =D20 -> 5000 | K20: 3
C21: 7 | D21: =J27 -> 5000 | E21: =L5 -> 5000 | F21: 5 | H21: 6 | I21: =J27 -> 5000 | J21: =D21 -> 5000 | K21: 7
C25: Input VAT (non-recoverable so amount posted to P&L) | H25: Accounts Payable*
C26: 2 | D26: 0 | J26: =L5 -> 5000 | K26: 2
C27: 6 | D27: 0 | J27: =L5 -> 5000 | K27: 6
H29: *For this specific example, illustrative amounts in AP exclude VAT. Ensure non-recoverable Input VAT is included in all postings in GL 243031, 243032, 167021, 534095
C33: Accrual Approach
C34: Lease expense postings for Accrual Approach are triggered by LAT based on contract payment terms (posting performed when expense is incurred - similar to GR)
C35: All amounts below are in contract currency (DC)
C36: Please check LC2, LC3 FX posting conversion where applicable | J36: Lease payment per period | L36: 5000
F37: SAP Posting date | J37: Payment frequency | L37: Monthly
C38: Description | F38: P7 | H38: P8 | J38: Payment timing | L38: Advance
C39: Payment by Nakisa | E39: 1 | F39: 43678 | G39: 5 | H39: 43678 | J39: First payment Date | L39: 43647
C40: AP: invoice booking | E40: 2 | F40: 43647 | G40: 6 | H40: 43678 | J40: Lease term (months) | L40: 9
C41: Automated reposting of AP | E41: 3 | F41: 43647 | G41: 7 | H41: 43678 | J41: Lease start date | L41: 43647
C42: Monthly Lease expense posting | E42: 4 | F42: 43678 | G42: 8 | H42: 43708 | J42: Lease end date | L42: 43921
C45: Lease expense - Vehicles Stat/Tax (534025) | H45: Prepaid Lease Cost (BS) - (167021)
C46: 4 | D46: 5000 | H46: 1 | I46: 5000 | J46: 5000 | K46: 4
C47: 8 | D47: 5000 | H47: 5 | I47: 5000 | J47: 5000 | K47: 8
C50: Invoice Clearing Leasing (243031) | H50: Invoice Clearing Leasing - Technical (243032)
C51: 3 | D51: 5000 | E51: 5000 | F51: 1 | H51: 2 | I51: 5000 | J51: 5000 | K51: 3
C52: 7 | D52: 5000 | E52: 5000 | F52: 5 | H52: 6 | I52: 5000 | J52: 5000 | K52: 7
C56: Input VAT (non-recoverable so amount posted to P&L) | H56: Accounts Payable*
C57: 2 | D57: 0 | J57: 5000 | K57: 2
C58: 6 | D58: 0 | J58: 5000 | K58: 6
H60: *For this specific example, illustrative amounts in AP exclude VAT. Ensure non-recoverable Input VAT is included in all postings in GL 243031, 243032, 167021, 534025
C64: Invoice Receipt Approach
C65: Lease expense recognition for IR approach is triggered by the invoice posting
C66: All amounts below are in contract currency (DC)
C67: Please check LC2, LC3 FX posting conversion where applicable | J67: Lease payment per period | L67: 5000
F68: SAP Posting date | J68: Payment frequency | L68: Monthly
C69: Description | F69: P7 | H69: P8 | J69: Payment timing | L69: Advance
C70: AP: invoice booking | E70: 1 | F70: 43647 | G70: 3 | H70: 43678 | J70: First payment Date | L70: 43647
C71: Automated reposting of Invoice to P&L | E71: 2 | F71: 43647 | G71: 4 | H71: 43678 | J71: Lease term (months) | L71: 9
J72: Lease start date | L72: 43647
J73: Lease end date | L73: 43921
C76: Lease expense - Vehicles Stat/Tax (534025) | H76: Invoice Clearing Leasing - Technical (243032)
C77: 2 | D77: 5000 | H77: 1 | I77: 5000 | J77: 5000 | K77: 2
C78: 4 | D78: 5000 | H78: 3 | I78: 5000 | J78: 5000 | K78: 4
C81: Input VAT (non-recoverable so amount posted to P&L) | H81: Accounts Payable*
C82: 1 | D82: 0 | J82: 5000 | K82: 1
C83: 3 | D83: 0 | J83: 5000 | K83: 3
H85: *For this specific example, illustrative amounts in AP exclude VAT. Ensure non-recoverable Input VAT is included in all postings in GL 243032, 534025

Sheet 4 - Prepaid Contract
C1: 4 - Prepaid Contract | BB1: Advance
BB2: Arrears
C3: Asset class name | E3: Land
C4: Asset class no. | E4: 103050
C5: Material group name | E5: =VLOOKUP(E6,'Material Groups'!$B:$C,2,0) -> LeaseLand FixedCost | F5: =VLOOKUP(F6,'Material Groups'!$B:$C,2,0) -> #N/A
C6: Mateial group no. | E6: 95101113
C7: Shopping cart number
C8: PR number
C9: PO no.
C10: Vendor ID
C11: Invoice no.
C12: Annual interest rate | F12: 0.03
C13: Monthly interest rate | F13: =(1+F12)^(1/12)-1 -> 0.0024662698
C14: Lease payment per period (excl. VAT) | F14: 60000
C15: Payment frequency | F15: Prepaid
C16: Payment timing | F16: Advance
C17: First payment Date | F17: 43647
C18: Lease term (months) | F18: 14
C19: Lease start date | F19: 43647
C20: Lease end date | F20: 44074
C21: Calculated NPV | F21: -60000
C22: Useful life (UL) of the asset (years) | F22: 999 | R22: IFRS 16 Approach
C23: Lower UL / contract duration (Months) | F23: =IF(F18<(F22*12),F18,F22*12) -> 14 | G23: for depreciation | R23: All amounts below are in contract currency (DC)
R24: Please check LC2, LC3 FX posting conversion where applicable | AA24: Asset class name | AC24: Land
W25: SAP Posting date | AA25: Asset class no. | AC25: 103050
R26: Description | W26: P7 | Y26: P8 | AA26: Material group name | AC26: LeaseLand FixedCost
R27: Initial posting: recognition of assets | V27: 1 | W27: 43647 | Y27: - | AA27: Mateial group no. | AC27: 95101113
I28: LEASE LIABILITY | N28: RIGHT OF USE ASSET | R28: Initial posting: recognition of liability | V28: 2 | W28: 43647 | Y28: - | AA28: Lease payment per period (excl. VAT) | AD28: 60000
H29: Inception | L29: DR 203031(BS) | N29: DR 203050 (BS) | R29: Payment by Nakisa | V29: 3 | W29: 43647 | Y29: - | AA29: Payment frequency | AD29: Prepaid
L30: CR 262530 (BS) | N30: CR 203031 (BS) | R30: LT liability to ST liability reclass | V30: 4 | W30: 43677 | Y30: - | AA30: Payment timing | AD30: Advance
H31: Monthly Acc. | I31: DR 706030 (PL) | K31: DR 262530 (BS) | L31: DR 262530 (BS) | O31: DR 534080 (PL) | P31: DR 534080 (PL) | R31: AP: invoice booking | V31: 5 | W31: 43647 | Y31: - | AA31: Lease term (months) | AD31: 14
I32: CR 243040 (BS) | K32: CR 243030 (BS) | L32: CR 243030 (BS) | O32: CR 211550 (BS) | P32: CR 211550 (BS) | R32: Automated reposting of AP | V32: 6 | W32: 43647 | Y32: - | AA32: Lease start date | AD32: 43647
H33: Payment | I33: DR 243040 (BS) | K33: DR 243030 (BS) | R33: Depreciation run | V33: 7 | W33: 43677 | X33: 8 | Y33: 43708 | AA33: Lease end date | AD33: 44074
I34: CR 243031 (BS) | K34: CR 243031 (BS) | AA34: Calculated NPV | AD34: -60000
B36: Days | C36: Period | D36: Start Date | E36: End Date | F36: Opening Lease Liability (Principal) | G36: Total Repayment | H36: Principal repayment | I36: Interest (PL) 706030 | J36: Closing Lease Liability (Principal) | K36: ST Liability (BS) 243030 | L36: LT Liability (BS) 262530 | N36: Right of Use Asset (BS) | O36: Accumulated Depreciation (BS) | P36: Depreciation (PL) 534080
R37: Leasing ROU - Land 203050 (BS) | W37: Capitalization clearing (203031) | AB37: Lease LT Liability (262530)
B38: =E38-D38+1 -> 31 | C38: 1 | D38: =F19 -> 43647 | E38: =EOMONTH(D38,0) -> 43677 | F38: =F21 -> -60000 | G38: =$F$14 -> 60000 | H38: =F14 -> 60000 | I38: =(F38+G38)*F12/12 -> -2.1827873e-13 | J38: =SUM(F38,H38) -> -8.7311491e-11 | K38: =J38-J50 -> 2.6556626e-12 | L38: =J38-K38 -> -8.9967154e-11 | N38: =IF(C38>$F$23,0,-$F$38) -> 60000 | O38: =-P38 -> -4285.7143 | P38: =N38/$F$23 -> 4285.7143 | R38: 1 | S38: =N38 -> 60000 | W38: 2 | X38: =AD38 -> 60000 | Y38: =S38 -> 60000 | Z38: 1 | AB38: 4 | AC38: =SUM(H38:H50) -> 60000 | AD38: =-F38 -> 60000 | AE38: 2
B39: =E39-D39+1 -> 31 | C39: 2 | D39: =EDATE(D38,1) -> 43678 | E39: =EOMONTH(D39,0) -> 43708 | F39: =J38 -> -8.7311491e-11 | H39: =G39+I38 -> -2.1827873e-13 | I39: =(F39+G39+I38)*$F$12/12 -> -2.1882443e-13 | J39: =SUM(F39,H39) -> -8.752977e-11 | K39: =J39-J51 -> 2.6623017e-12 | L39: =J39-K39 -> -9.0192072e-11 | N39: =IF(C39>$F$23,0,-$F$38) -> 60000 | O39: =IF(N39=0,0,O38-P39) -> -8571.4286 | P39: =N39/$F$23 -> 4285.7143
B40: =E40-D40+1 -> 30 | C40: 3 | D40: =EDATE(D39,1) -> 43709 | E40: =EOMONTH(D40,0) -> 43738 | F40: =J39 -> -8.752977e-11 | H40: =G40+I39 -> -2.1882443e-13 | I40: =(F40+G40+I39)*$F$12/12 -> -2.1937149e-13 | J40: =SUM(F40,H40) -> -8.7748595e-11 | K40: =J40-J52 -> -8.7748595e-11 | L40: =J40-K40 -> 0 | N40: =IF(C40>$F$23,0,-$F$38) -> 60000 | O40: =IF(N40=0,0,O39-P40) -> -12857.143 | P40: =N40/$F$23 -> 4285.7143
B41: =E41-D41+1 -> 31 | C41: 4 | D41: =EDATE(D40,1) -> 43739 | E41: =EOMONTH(D41,0) -> 43769 | F41: =J40 -> -8.7748595e-11 | H41: =G41+I40 -> -2.1937149e-13 | I41: =(F41+G41+I40)*$F$12/12 -> -2.1991992e-13 | J41: =SUM(F41,H41) -> -8.7967966e-11 | K41: =J41-J53 -> -8.7967966e-11 | L41: =J41-K41 -> 0 | N41: =IF(C41>$F$23,0,-$F$38) -> 60000 | O41: =IF(N41=0,0,O40-P41) -> -17142.857 | P41: =N41/$F$23 -> 4285.7143
B42: =E42-D42+1 -> 30 | C42: 5 | D42: =EDATE(D41,1) -> 43770 | E42: =EOMONTH(D42,0) -> 43799 | F42: =J41 -> -8.7967966e-11 | H42: =G42+I41 -> -2.1991992e-13 | I42: =(F42+G42+I41)*$F$12/12 -> -2.2046971e-13 | J42: =SUM(F42,H42) -> -8.8187886e-11 | K42: =J42-J54 -> -8.8187886e-11 | L42: =J42-K42 -> 0 | N42: =IF(C42>$F$23,0,-$F$38) -> 60000 | O42: =IF(N42=0,0,O41-P42) -> -21428.571 | P42: =N42/$F$23 -> 4285.7143 | R42: Lease Interest (P&L) (706030) | W42: Lease Accrued interest (BS) (243040) | AB42: Lease ST Liability (243030)
B43: =E43-D43+1 -> 31 | C43: 6 | D43: =EDATE(D42,1) -> 43800 | E43: =EOMONTH(D43,0) -> 43830 | F43: =J42 -> -8.8187886e-11 | H43: =G43+I42 -> -2.2046971e-13 | I43: =(F43+G43+I42)*$F$12/12 -> -2.2102089e-13 | J43: =SUM(F43,H43) -> -8.8408356e-11 | K43: =J43-J55 -> -8.8408356e-11 | L43: =J43-K43 -> 0 | N43: =IF(C43>$F$23,0,-$F$38) -> 60000 | O43: =IF(N43=0,0,O42-P43) -> -25714.286 | P43: =N43/$F$23 -> 4285.7143 | AB43: 3 | AC43: =H38 -> 60000 | AD43: =AC38 -> 60000 | AE43: 4
B44: =E44-D44+1 -> 31 | C44: 7 | D44: =EDATE(D43,1) -> 43831 | E44: =EOMONTH(D44,0) -> 43861 | F44: =J43 -> -8.8408356e-11 | H44: =G44+I43 -> -2.2102089e-13 | I44: =(F44+G44+I43)*$F$12/12 -> -2.2157344e-13 | J44: =SUM(F44,H44) -> -8.8629377e-11 | K44: =J44-J56 -> -8.8629377e-11 | L44: =J44-K44 -> 0 | N44: =IF(C44>$F$23,0,-$F$38) -> 60000 | O44: =IF(N44=0,0,O43-P44) -> -30000 | P44: =N44/$F$23 -> 4285.7143
B45: =E45-D45+1 -> 29 | C45: 8 | D45: =EDATE(D44,1) -> 43862 | E45: =EOMONTH(D45,0) -> 43890 | F45: =J44 -> -8.8629377e-11 | H45: =G45+I44 -> -2.2157344e-13 | I45: =(F45+G45+I44)*$F$12/12 -> -2.2212737e-13 | J45: =SUM(F45,H45) -> -8.885095e-11 | K45: =J45-J57 -> -8.885095e-11 | L45: =J45-K45 -> 0 | N45: =IF(C45>$F$23,0,-$F$38) -> 60000 | O45: =IF(N45=0,0,O44-P45) -> -34285.714 | P45: =N45/$F$23 -> 4285.7143
B46: =E46-D46+1 -> 31 | C46: 9 | D46: =EDATE(D45,1) -> 43891 | E46: =EOMONTH(D46,0) -> 43921 | F46: =J45 -> -8.885095e-11 | H46: =G46+I45 -> -2.2212737e-13 | I46: =(F46+G46+I45)*$F$12/12 -> -2.2268269e-13 | J46: =SUM(F46,H46) -> -8.9073077e-11 | K46: =J46-J58 -> -8.9073077e-11 | L46: =J46-K46 -> 0 | N46: =IF(C46>$F$23,0,-$F$38) -> 60000 | O46: =IF(N46=0,0,O45-P46) -> -38571.429 | P46: =N46/$F$23 -> 4285.7143
B47: =E47-D47+1 -> 30 | C47: 10 | D47: =EDATE(D46,1) -> 43922 | E47: =EOMONTH(D47,0) -> 43951 | F47: =J46 -> -8.9073077e-11 | H47: =G47+I46 -> -2.2268269e-13 | I47: =(F47+G47+I46)*$F$12/12 -> -2.232394e-13 | J47: =SUM(F47,H47) -> -8.929576e-11 | K47: =J47-J59 -> -8.929576e-11 | L47: =J47-K47 -> 0 | N47: =IF(C47>$F$23,0,-$F$38) -> 60000 | O47: =IF(N47=0,0,O46-P47) -> -42857.143 | P47: =N47/$F$23 -> 4285.7143 | R47: Invoice Clearing Leasing (243031) | W47: Invoice Clearing Leasing - Technical (243032) | AB47: Accounts Payable*
B48: =E48-D48+1 -> 31 | C48: 11 | D48: =EDATE(D47,1) -> 43952 | E48: =EOMONTH(D48,0) -> 43982 | F48: =J47 -> -8.929576e-11 | H48: =G48+I47 -> -2.232394e-13 | I48: =(F48+G48+I47)*$F$12/12 -> -2.237975e-13 | J48: =SUM(F48,H48) -> -8.9518999e-11 | K48: =J48-J60 -> -8.9518999e-11 | L48: =J48-K48 -> 0 | N48: =IF(C48>$F$23,0,-$F$38) -> 60000 | O48: =IF(N48=0,0,O47-P48) -> -47142.857 | P48: =N48/$F$23 -> 4285.7143 | R48: 6 | S48: =AD48-AC53 -> 60000 | T48: =AC43 -> 60000 | U48: 3 | W48: 5 | X48: =AD48-AC53 -> 60000 | Y48: =X48 -> 60000 | Z48: 6 | AD48: 72000 | AE48: 5
B49: =E49-D49+1 -> 30 | C49: 12 | D49: =EDATE(D48,1) -> 43983 | E49: =EOMONTH(D49,0) -> 44012 | F49: =J48 -> -8.9518999e-11 | H49: =G49+I48 -> -2.237975e-13 | I49: =(F49+G49+I48)*$F$12/12 -> -2.2435699e-13 | J49: =SUM(F49,H49) -> -8.9742797e-11 | K49: =J49-J61 -> -8.9742797e-11 | L49: =J49-K49 -> 0 | N49: =IF(C49>$F$23,0,-$F$38) -> 60000 | O49: =IF(N49=0,0,O48-P49) -> -51428.571 | P49: =N49/$F$23 -> 4285.7143
B50: =E50-D50+1 -> 31 | C50: 13 | D50: =EDATE(D49,1) -> 44013 | E50: =EOMONTH(D50,0) -> 44043 | F50: =J49 -> -8.9742797e-11 | H50: =G50+I49 -> -2.2435699e-13 | I50: =(F50+G50+I49)*$F$12/12 -> -2.2491788e-13 | J50: =SUM(F50,H50) -> -8.9967154e-11 | K50: =J50-J62 -> -8.9967154e-11 | L50: =J50-K50 -> 0 | N50: =IF(C50>$F$23,0,-$F$38) -> 60000 | O50: =IF(N50=0,0,O49-P50) -> -55714.286 | P50: =N50/$F$23 -> 4285.7143
B51: =E51-D51+1 -> 31 | C51: 14 | D51: =EDATE(D50,1) -> 44044 | E51: =EOMONTH(D51,0) -> 44074 | F51: =J50 -> -8.9967154e-11 | H51: =G51+I50 -> -2.2491788e-13 | I51: =(F51+G51+I50)*$F$12/12 -> -2.2548018e-13 | J51: =SUM(F51,H51) -> -9.0192072e-11 | K51: =J51-J63 -> -9.0192072e-11 | L51: =J51-K51 -> 0 | N51: =IF(C51>$F$23,0,-$F$38) -> 60000 | O51: =IF(N51=0,0,O50-P51) -> -60000 | P51: =N51/$F$23 -> 4285.7143
B52: =E52-D52+1 -> 30 | C52: 15 | D52: =EDATE(D51,1) -> 44075 | E52: =EOMONTH(D52,0) -> 44104 | N52: =IF(C52>$F$23,0,-$F$38) -> 0 | O52: =IF(N52=0,0,O51-P52) -> 0 | P52: =N52/$F$23 -> 0 | R52: Depreciation ROU Lease (P&L) (534080) | W52: Acc. Depreciation ROU Land 211550 (BS) | AB52: Input VAT (example - different by entity)
B53: =E53-D53+1 -> 31 | C53: 16 | D53: =EDATE(D52,1) -> 44105 | E53: =EOMONTH(D53,0) -> 44135 | N53: =IF(C53>$F$23,0,-$F$38) -> 0 | O53: =IF(N53=0,0,O52-P53) -> 0 | P53: =N53/$F$23 -> 0 | R53: 7 | S53: =P38 -> 4285.7143 | Y53: =S53 -> 4285.7143 | Z53: 7 | AB53: 5 | AC53: 12000
B54: =E54-D54+1 -> 30 | C54: 17 | D54: =EDATE(D53,1) -> 44136 | E54: =EOMONTH(D54,0) -> 44165 | N54: =IF(C54>$F$23,0,-$F$38) -> 0 | O54: =IF(N54=0,0,O53-P54) -> 0 | P54: =N54/$F$23 -> 0 | R54: 8 | S54: =P39 -> 4285.7143 | Y54: =S54 -> 4285.7143 | Z54: 8
B55: =E55-D55+1 -> 31 | C55: 18 | D55: =EDATE(D54,1) -> 44166 | E55: =EOMONTH(D55,0) -> 44196 | N55: =IF(C55>$F$23,0,-$F$38) -> 0 | O55: =IF(N55=0,0,O54-P55) -> 0 | P55: =N55/$F$23 -> 0
B56: =E56-D56+1 -> 31 | C56: 19 | D56: =EDATE(D55,1) -> 44197 | E56: =EOMONTH(D56,0) -> 44227 | N56: =IF(C56>$F$23,0,-$F$38) -> 0 | O56: =IF(N56=0,0,O55-P56) -> 0 | P56: =N56/$F$23 -> 0
B57: =E57-D57+1 -> 28 | C57: 20 | D57: =EDATE(D56,1) -> 44228 | E57: =EOMONTH(D57,0) -> 44255 | N57: =IF(C57>$F$23,0,-$F$38) -> 0 | O57: =IF(N57=0,0,O56-P57) -> 0 | P57: =N57/$F$23 -> 0 | R57: Accrual Approach
B58: =E58-D58+1 -> 31 | C58: 21 | D58: =EDATE(D57,1) -> 44256 | E58: =EOMONTH(D58,0) -> 44286 | N58: =IF(C58>$F$23,0,-$F$38) -> 0 | O58: =IF(N58=0,0,O57-P58) -> 0 | P58: =N58/$F$23 -> 0 | R58: Lease expense postings for Accrual Approach are triggered by LAT based on contract payment terms (posting performed when expense is incurred - similar to GR)
B59: =E59-D59+1 -> 30 | C59: 22 | D59: =EDATE(D58,1) -> 44287 | E59: =EOMONTH(D59,0) -> 44316 | N59: =IF(C59>$F$23,0,-$F$38) -> 0 | O59: =IF(N59=0,0,O58-P59) -> 0 | P59: =N59/$F$23 -> 0 | R59: All amounts below are in contract currency (DC)
B60: =E60-D60+1 -> 31 | C60: 23 | D60: =EDATE(D59,1) -> 44317 | E60: =EOMONTH(D60,0) -> 44347 | N60: =IF(C60>$F$23,0,-$F$38) -> 0 | O60: =IF(N60=0,0,O59-P60) -> 0 | P60: =N60/$F$23 -> 0 | R60: Please check LC2, LC3 FX posting conversion where applicable | AA60: Asset class name | AC60: Land
B61: =E61-D61+1 -> 30 | C61: 24 | D61: =EDATE(D60,1) -> 44348 | E61: =EOMONTH(D61,0) -> 44377 | N61: =IF(C61>$F$23,0,-$F$38) -> 0 | O61: =IF(N61=0,0,O60-P61) -> 0 | P61: =N61/$F$23 -> 0 | W61: SAP Posting date | AA61: Asset class no. | AC61: 103050
B62: =E62-D62+1 -> 31 | C62: 25 | D62: =EDATE(D61,1) -> 44378 | E62: =EOMONTH(D62,0) -> 44408 | N62: =IF(C62>$F$23,0,-$F$38) -> 0 | O62: =IF(N62=0,0,O61-P62) -> 0 | P62: =N62/$F$23 -> 0 | R62: Description | W62: P7 | Y62: P8 | AA62: Material group name | AC62: LeaseLand FixedCost
B63: =E63-D63+1 -> 31 | C63: 26 | D63: =EDATE(D62,1) -> 44409 | E63: =EOMONTH(D63,0) -> 44439 | N63: =IF(C63>$F$23,0,-$F$38) -> 0 | O63: =IF(N63=0,0,O62-P63) -> 0 | P63: =N63/$F$23 -> 0 | R63: Lease expense (Invoice amount) | V63: 1 | W63: 43678 | Y63: - | AA63: Mateial group no. | AC63: 95101113
B64: =E64-D64+1 -> 30 | C64: 27 | D64: =EDATE(D63,1) -> 44440 | E64: =EOMONTH(D64,0) -> 44469 | N64: =IF(C64>$F$23,0,-$F$38) -> 0 | O64: =IF(N64=0,0,O63-P64) -> 0 | P64: =N64/$F$23 -> 0 | R64: Accrual object creation - reverse lease expense | V64: 2 | W64: =$D$38 -> 43647 | Y64: - | AA64: Lease payment per period (excl. VAT) | AD64: 60000
B65: =E65-D65+1 -> 31 | C65: 28 | D65: =EDATE(D64,1) -> 44470 | E65: =EOMONTH(D65,0) -> 44500 | N65: =IF(C65>$F$23,0,-$F$38) -> 0 | O65: =IF(N65=0,0,O64-P65) -> 0 | P65: =N65/$F$23 -> 0 | R65: Monthly lease expense (accrual object amortisation) | V65: 3 | W65: =$E$38 -> 43677 | X65: 6 | Y65: 43708 | AA65: Payment frequency | AD65: Prepaid
B66: =E66-D66+1 -> 30 | C66: 29 | D66: =EDATE(D65,1) -> 44501 | E66: =EOMONTH(D66,0) -> 44530 | N66: =IF(C66>$F$23,0,-$F$38) -> 0 | O66: =IF(N66=0,0,O65-P66) -> 0 | P66: =N66/$F$23 -> 0 | R66: AP: invoice booking | V66: 4 | W66: 43647 | Y66: - | AA66: Payment timing | AD66: Advance
B67: =E67-D67+1 -> 31 | C67: 30 | D67: =EDATE(D66,1) -> 44531 | E67: =EOMONTH(D67,0) -> 44561 | N67: =IF(C67>$F$23,0,-$F$38) -> 0 | O67: =IF(N67=0,0,O66-P67) -> 0 | P67: =N67/$F$23 -> 0 | R67: Automated reposting of AP | V67: 5 | W67: 43647 | Y67: - | AA67: Lease term (months) | AD67: 14
B68: =E68-D68+1 -> 31 | C68: 31 | D68: =EDATE(D67,1) -> 44562 | E68: =EOMONTH(D68,0) -> 44592 | N68: =IF(C68>$F$23,0,-$F$38) -> 0 | O68: =IF(N68=0,0,O67-P68) -> 0 | P68: =N68/$F$23 -> 0 | AA68: Lease start date | AD68: 43647
B69: =E69-D69+1 -> 28 | C69: 32 | D69: =EDATE(D68,1) -> 44593 | E69: =EOMONTH(D69,0) -> 44620 | N69: =IF(C69>$F$23,0,-$F$38) -> 0 | O69: =IF(N69=0,0,O68-P69) -> 0 | P69: =N69/$F$23 -> 0 | AA69: Lease end date | AD69: 44074
B70: =E70-D70+1 -> 31 | C70: 33 | D70: =EDATE(D69,1) -> 44621 | E70: =EOMONTH(D70,0) -> 44651 | N70: =IF(C70>$F$23,0,-$F$38) -> 0 | O70: =IF(N70=0,0,O69-P70) -> 0 | P70: =N70/$F$23 -> 0 | AA70: Calculated NPV | AD70: -60000
B71: =E71-D71+1 -> 30 | C71: 34 | D71: =EDATE(D70,1) -> 44652 | E71: =EOMONTH(D71,0) -> 44681 | N71: =IF(C71>$F$23,0,-$F$38) -> 0 | O71: =IF(N71=0,0,O70-P71) -> 0 | P71: =N71/$F$23 -> 0
B72: =E72-D72+1 -> 31 | C72: 35 | D72: =EDATE(D71,1) -> 44682 | E72: =EOMONTH(D72,0) -> 44712 | N72: =IF(C72>$F$23,0,-$F$38) -> 0 | O72: =IF(N72=0,0,O71-P72) -> 0 | P72: =N72/$F$23 -> 0 | R72: Invoice Clearing Leasing (243031) | W72: Invoice Clearing Leasing - Technical (243032) | AB72: Accounts Payable*
B73: =E73-D73+1 -> 30 | C73: 36 | D73: =EDATE(D72,1) -> 44713 | E73: =EOMONTH(D73,0) -> 44742 | N73: =IF(C73>$F$23,0,-$F$38) -> 0 | O73: =IF(N73=0,0,O72-P73) -> 0 | P73: =N73/$F$23 -> 0 | R73: 5 | S73: =G38 -> 60000 | T73: =G38 -> 60000 | U73: 1 | W73: 4 | X73: =AD73-AC79 -> 60000 | Y73: =S73 -> 60000 | Z73: 5 | AD73: =G38*1.2 -> 72000 | AE73: 4
B74: =E74-D74+1 -> 31 | C74: 37 | D74: =EDATE(D73,1) -> 44743 | E74: =EOMONTH(D74,0) -> 44773 | N74: =IF(C74>$F$23,0,-$F$38) -> 0 | O74: =IF(N74=0,0,O73-P74) -> 0 | P74: =N74/$F$23 -> 0
B75: =E75-D75+1 -> 31 | C75: 38 | D75: =EDATE(D74,1) -> 44774 | E75: =EOMONTH(D75,0) -> 44804 | N75: =IF(C75>$F$23,0,-$F$38) -> 0 | O75: =IF(N75=0,0,O74-P75) -> 0 | P75: =N75/$F$23 -> 0
B76: =E76-D76+1 -> 30 | C76: 39 | D76: =EDATE(D75,1) -> 44805 | E76: =EOMONTH(D76,0) -> 44834 | N76: =IF(C76>$F$23,0,-$F$38) -> 0 | O76: =IF(N76=0,0,O75-P76) -> 0 | P76: =N76/$F$23 -> 0
B77: =E77-D77+1 -> 31 | C77: 40 | D77: =EDATE(D76,1) -> 44835 | E77: =EOMONTH(D77,0) -> 44865 | N77: =IF(C77>$F$23,0,-$F$38) -> 0 | O77: =IF(N77=0,0,O76-P77) -> 0 | P77: =N77/$F$23 -> 0
B78: =E78-D78+1 -> 30 | C78: 41 | D78: =EDATE(D77,1) -> 44866 | E78: =EOMONTH(D78,0) -> 44895 | N78: =IF(C78>$F$23,0,-$F$38) -> 0 | O78: =IF(N78=0,0,O77-P78) -> 0 | P78: =N78/$F$23 -> 0 | R78: Lease expense - Land Stat/Tax (534015) | W78: Prepaid Lease Cost (167021) | AB78: Input VAT (example - different by entity)
B79: =E79-D79+1 -> 31 | C79: 42 | D79: =EDATE(D78,1) -> 44896 | E79: =EOMONTH(D79,0) -> 44926 | N79: =IF(C79>$F$23,0,-$F$38) -> 0 | O79: =IF(N79=0,0,O78-P79) -> 0 | P79: =N79/$F$23 -> 0 | R79: 1 | S79: =T73 -> 60000 | T79: =S79 -> 60000 | U79: 2 | W79: 2 | X79: =T79 -> 60000 | Y79: =S80 -> 4285.7143 | Z79: 3 | AB79: 4 | AC79: =AD73*20/120 -> 12000
B80: =E80-D80+1 -> 31 | C80: 43 | D80: =EDATE(D79,1) -> 44927 | E80: =EOMONTH(D80,0) -> 44957 | N80: =IF(C80>$F$23,0,-$F$38) -> 0 | O80: =IF(N80=0,0,O79-P80) -> 0 | P80: =N80/$F$23 -> 0 | R80: 3 | S80: =P38 -> 4285.7143 | Y80: =Y79 -> 4285.7143 | Z80: 6
B81: =E81-D81+1 -> 28 | C81: 44 | D81: =EDATE(D80,1) -> 44958 | E81: =EOMONTH(D81,0) -> 44985 | N81: =IF(C81>$F$23,0,-$F$38) -> 0 | O81: =IF(N81=0,0,O80-P81) -> 0 | P81: =N81/$F$23 -> 0 | R81: 6 | S81: =S80 -> 4285.7143
B82: =E82-D82+1 -> 31 | C82: 45 | D82: =EDATE(D81,1) -> 44986 | E82: =EOMONTH(D82,0) -> 45016 | N82: =IF(C82>$F$23,0,-$F$38) -> 0 | O82: =IF(N82=0,0,O81-P82) -> 0 | P82: =N82/$F$23 -> 0
B83: =E83-D83+1 -> 30 | C83: 46 | D83: =EDATE(D82,1) -> 45017 | E83: =EOMONTH(D83,0) -> 45046 | N83: =IF(C83>$F$23,0,-$F$38) -> 0 | O83: =IF(N83=0,0,O82-P83) -> 0 | P83: =N83/$F$23 -> 0
B84: =E84-D84+1 -> 31 | C84: 47 | D84: =EDATE(D83,1) -> 45047 | E84: =EOMONTH(D84,0) -> 45077 | N84: =IF(C84>$F$23,0,-$F$38) -> 0 | O84: =IF(N84=0,0,O83-P84) -> 0 | P84: =N84/$F$23 -> 0
B85: =E85-D85+1 -> 30 | C85: 48 | D85: =EDATE(D84,1) -> 45078 | E85: =EOMONTH(D85,0) -> 45107 | N85: =IF(C85>$F$23,0,-$F$38) -> 0 | O85: =IF(N85=0,0,O84-P85) -> 0 | P85: =N85/$F$23 -> 0 | R85: Invoice Receipt Approach
B86: =E86-D86+1 -> 31 | C86: 49 | D86: =EDATE(D85,1) -> 45108 | E86: =EOMONTH(D86,0) -> 45138 | N86: =IF(C86>$F$23,0,-$F$38) -> 0 | O86: =IF(N86=0,0,O85-P86) -> 0 | P86: =N86/$F$23 -> 0 | R86: Lease expense recognition for IR approach is triggered by the invoice posting
B87: =E87-D87+1 -> 31 | C87: 50 | D87: =EDATE(D86,1) -> 45139 | E87: =EOMONTH(D87,0) -> 45169 | N87: =IF(C87>$F$23,0,-$F$38) -> 0 | O87: =IF(N87=0,0,O86-P87) -> 0 | P87: =N87/$F$23 -> 0 | R87: All amounts below are in contract currency (DC)
B88: =E88-D88+1 -> 30 | C88: 51 | D88: =EDATE(D87,1) -> 45170 | E88: =EOMONTH(D88,0) -> 45199 | N88: =IF(C88>$F$23,0,-$F$38) -> 0 | O88: =IF(N88=0,0,O87-P88) -> 0 | P88: =N88/$F$23 -> 0 | R88: Please check LC2, LC3 FX posting conversion where applicable | AA88: Asset class name | AC88: Land
B89: =E89-D89+1 -> 31 | C89: 52 | D89: =EDATE(D88,1) -> 45200 | E89: =EOMONTH(D89,0) -> 45230 | N89: =IF(C89>$F$23,0,-$F$38) -> 0 | O89: =IF(N89=0,0,O88-P89) -> 0 | P89: =N89/$F$23 -> 0 | W89: SAP Posting date | AA89: Asset class no. | AC89: 103050
B90: =E90-D90+1 -> 30 | C90: 53 | D90: =EDATE(D89,1) -> 45231 | E90: =EOMONTH(D90,0) -> 45260 | N90: =IF(C90>$F$23,0,-$F$38) -> 0 | O90: =IF(N90=0,0,O89-P90) -> 0 | P90: =N90/$F$23 -> 0 | R90: Description | W90: P7 | AA90: Material group name | AC90: LeaseLand FixedCost
B91: =E91-D91+1 -> 31 | C91: 54 | D91: =EDATE(D90,1) -> 45261 | E91: =EOMONTH(D91,0) -> 45291 | N91: =IF(C91>$F$23,0,-$F$38) -> 0 | O91: =IF(N91=0,0,O90-P91) -> 0 | P91: =N91/$F$23 -> 0 | R91: AP: invoice booking | V91: 1 | W91: =$D$38 -> 43647 | AA91: Mateial group no. | AC91: 95101113
B92: =E92-D92+1 -> 31 | C92: 55 | D92: =EDATE(D91,1) -> 45292 | E92: =EOMONTH(D92,0) -> 45322 | N92: =IF(C92>$F$23,0,-$F$38) -> 0 | O92: =IF(N92=0,0,O91-P92) -> 0 | P92: =N92/$F$23 -> 0 | R92: Automated reposting of Invoice to P&L | V92: 2 | W92: =$D$38 -> 43647 | AA92: Lease payment per period (excl. VAT) | AD92: 60000
B93: =E93-D93+1 -> 29 | C93: 56 | D93: =EDATE(D92,1) -> 45323 | E93: =EOMONTH(D93,0) -> 45351 | N93: =IF(C93>$F$23,0,-$F$38) -> 0 | O93: =IF(N93=0,0,O92-P93) -> 0 | P93: =N93/$F$23 -> 0 | AA93: Payment frequency | AD93: Prepaid
B94: =E94-D94+1 -> 31 | C94: 57 | D94: =EDATE(D93,1) -> 45352 | E94: =EOMONTH(D94,0) -> 45382 | N94: =IF(C94>$F$23,0,-$F$38) -> 0 | O94: =IF(N94=0,0,O93-P94) -> 0 | P94: =N94/$F$23 -> 0 | AA94: Payment timing | AD94: Advance
B95: =E95-D95+1 -> 30 | C95: 58 | D95: =EDATE(D94,1) -> 45383 | E95: =EOMONTH(D95,0) -> 45412 | N95: =IF(C95>$F$23,0,-$F$38) -> 0 | O95: =IF(N95=0,0,O94-P95) -> 0 | P95: =N95/$F$23 -> 0 | AA95: Lease term (months) | AD95: 14
B96: =E96-D96+1 -> 31 | C96: 59 | D96: =EDATE(D95,1) -> 45413 | E96: =EOMONTH(D96,0) -> 45443 | N96: =IF(C96>$F$23,0,-$F$38) -> 0 | O96: =IF(N96=0,0,O95-P96) -> 0 | P96: =N96/$F$23 -> 0 | AA96: Lease start date | AD96: 43647
B97: =E97-D97+1 -> 30 | C97: 60 | D97: =EDATE(D96,1) -> 45444 | E97: =EOMONTH(D97,0) -> 45473 | N97: =IF(C97>$F$23,0,-$F$38) -> 0 | O97: =IF(N97=0,0,O96-P97) -> 0 | P97: =N97/$F$23 -> 0 | AA97: Lease end date | AD97: 44074
B98: =E98-D98+1 -> 31 | C98: 61 | D98: =EDATE(D97,1) -> 45474 | E98: =EOMONTH(D98,0) -> 45504 | N98: =IF(C98>$F$23,0,-$F$38) -> 0 | O98: =IF(N98=0,0,O97-P98) -> 0 | P98: =N98/$F$23 -> 0 | AA98: Calculated NPV | AD98: -60000
B99: =E99-D99+1 -> 31 | C99: 62 | D99: =EDATE(D98,1) -> 45505 | E99: =EOMONTH(D99,0) -> 45535 | N99: =IF(C99>$F$23,0,-$F$38) -> 0 | O99: =IF(N99=0,0,O98-P99) -> 0 | P99: =N99/$F$23 -> 0
B100: =E100-D100+1 -> 30 | C100: 63 | D100: =EDATE(D99,1) -> 45536 | E100: =EOMONTH(D100,0) -> 45565 | N100: =IF(C100>$F$23,0,-$F$38) -> 0 | O100: =IF(N100=0,0,O99-P100) -> 0 | P100: =N100/$F$23 -> 0 | R100: Lease expense - Land Stat/Tax (534015) | W100: Invoice Clearing Leasing - Technical (243032) | AB100: Accounts Payable*
B101: =E101-D101+1 -> 31 | C101: 64 | D101: =EDATE(D100,1) -> 45566 | E101: =EOMONTH(D101,0) -> 45596 | N101: =IF(C101>$F$23,0,-$F$38) -> 0 | O101: =IF(N101=0,0,O100-P101) -> 0 | P101: =N101/$F$23 -> 0 | R101: 2 | S101: =Y101 -> 60000 | W101: 1 | X101: =AD101-AC106 -> 60000 | Y101: =X101 -> 60000 | Z101: 2 | AD101: 72000 | AE101: 1
...

Sheet 5 - Contract Extension
C1: 5 - Contract Extension | BB1: Advance
BB2: Arrears
C3: Asset class name | E3: Vehicle
C4: Asset class no. | E4: 103070
C5: Material group name | E5: =VLOOKUP(E6,'Material Groups'!$B:$C,2,0) -> LeaseVehicle FixCost | F5: =VLOOKUP(F6,'Material Groups'!$B:$C,2,0) -> #N/A
C6: Mateial group no. | E6: 95101110
C7: Annual interest rate | F7: 0.09
C8: Monthly interest rate | F8: =(1+F7)^(1/12)-1 -> 0.0072073233
C9: Lease payment per period (excl. VAT) | F9: 2000
C10: Payment frequency | F10: Monthly
C11: Payment timing | F11: Arrears
C12: First payment Date | F12: 43677
C13: Lease term (months) | F13: 84
C14: Lease start date | F14: 43647
C15: Lease end date | F15: 46203
C16: Calculated NPV | F16: -124307.93
C17: Useful life (UL) of the asset (years) | F17: 5 | R17: IFRS 16 Approach
C18: Lower UL / contract duration (Months) | F18: =IF(F13<(F17*12),F13,F17*12) -> 60 | G18: for depreciation | R18: All amounts below are in contract currency (DC)
R19: Please check LC2, LC3 FX posting conversion where applicable | AB19: Asset class name | AD19: Vehicle
C20: After reassessment: | W20: SAP Posting date | AB20: Asset class no. | AD20: 103070
C21: Calculated NPV - reassess on 1 August 2019 | F21: -135540.75 | R21: Description | W21: P7 | Y21: P8 | AB21: Material group name | AD21: LeaseVehicle FixCost
C22: Lower of UL or contract duration (Depreciation) | F22: =F18 -> 60 | R22: Initial posting: P7 recognition of assets / P8 extension | V22: 1 | W22: =$D$33 -> 43647 | X22: *09 | Y22: 43678 | AB22: Mateial group no. | AD22: 95101110
C23: Extension Date | F23: 46568 | I23: LEASE LIABILITY | N23: RIGHT OF USE ASSET | R23: Initial posting: P7 recognition of liability / P8 extension | V23: 2 | W23: =$D$33 -> 43647 | X23: *10 | Y23: 43678 | AB23: Lease payment per period (excl. VAT) | AE23: 2000
H24: Inception | L24: DR 203031(BS) | N24: DR 203070 (BS) | R24: Payment by Nakisa | V24: 3 | W24: =$E$33 -> 43677 | X24: 11 | Y24: =$E$35 -> 43708 | AB24: Payment frequency | AE24: Monthly
L25: CR 262530 (BS) | N25: CR 203031 (BS) | R25: LT liability to ST liability reclass | V25: 4 | W25: =$E$33 -> 43677 | X25: 12 | Y25: =$E$35 -> 43708 | AB25: Payment timing | AE25: Arrears
H26: Monthly Acc. | I26: DR 706030 (PL) | K26: DR 262530 (BS) | L26: DR 262530 (BS) | O26: DR 534080 (PL) | P26: DR 534080 (PL) | R26: Interest accrual | V26: 5 | W26: =$E$33 -> 43677 | X26: 13 | Y26: =$E$35 -> 43708 | AB26: Lease term (months) | AE26: 84
I27: CR 243040 (BS) | K27: CR 243030 (BS) | L27: CR 243030 (BS) | O27: CR 211570 (BS) | P27: CR 211570 (BS) | R27: AP: invoice booking | V27: 6 | W27: 43682 | X27: 14 | Y27: =$E$35 -> 43708 | AB27: Lease start date | AE27: 43647
H28: Payment | I28: DR 243040 (BS) | K28: DR 243030 (BS) | R28: Automated reposting of AP | V28: 7 | W28: 43682 | X28: 15 | Y28: =$E$35 -> 43708 | AB28: Lease end date | AE28: 46203
I29: CR 243031 (BS) | K29: CR 243031 (BS) | R29: Depreciation run | V29: 8 | W29: =$E$33 -> 43677 | X29: 16 | Y29: =$E$35 -> 43708 | AB29: Calculated NPV | AE29: =F16 -> -124307.93
B31: Days | C31: Period | D31: Start Date | E31: End Date | F31: Opening Lease Liability (Principal) | G31: Total Repayment | H31: Principal repayment | I31: Interest (PL) 706030 | J31: Closing Lease Liability (Principal) | K31: ST Liability (BS) 243030 | L31: LT Liability (BS) 262530 | N31: Right of Use Asset (BS) | O31: Accumulated Depreciation (BS) | P31: Depreciation (PL) 534080 | Y31: *CONTRACT EXTENSION effective 1 August 2019
R32: Leasing RoU - Vehicles 203070 (BS) | W32: Capitalization clearing (203031) | AB32: Lease LT Liability (262530)
B33: =E33-D33+1 -> 31 | C33: 1 | D33: =F14 -> 43647 | E33: =EOMONTH(D33,0) -> 43677 | F33: -124307.93 | G33: 2000 | H33: 1067.69 | I33: -932.31 | J33: =F33+H33 -> -123240.24 | K33: -13454.39 | L33: =J33-K33 -> -109785.85 | N33: 124307.93 | O33: =-P33 -> -2071.7988 | P33: =N33/F18 -> 2071.7988 | R33: 1 | S33: =N33 -> 124307.93 | W33: 2 | X33: =AD33 -> 124307.93 | Y33: =S33 -> 124307.93 | Z33: 1 | AB33: 4 | AC33: =-K33+H33 -> 14522.08 | AD33: =-F33 -> 124307.93 | AE33: 2
B34: =E35-D35+1 -> 31 | D34: 43678 | E34: 43678 | F34: =F21 -> -135540.75 | J34: =F34 -> -135540.75 | R34: 9 | S34: =J33-J34 -> 12300.514 | W34: 10 | X34: =Y34 -> 12300.514 | Y34: =S34 -> 12300.514 | Z34: 9 | AD34: =X34 -> 12300.514 | AE34: 10
B35: =E36-D36+1 -> 30 | C35: 2 | D35: =EDATE(D33,1) -> 43678 | E35: =EOMONTH(D35,0) -> 43708 | F35: =J34 -> -135540.75 | G35: =$F$9 -> 2000 | H35: =G35+I35 -> 983.44435 | I35: =(F35)*$F$7/12 -> -1016.5557 | J35: =SUM(F35,H35) -> -134557.31 | K35: =J35-J47 -> -12392.769 | L35: =J35-K35 -> -122164.54 | N35: =N33+S34 -> 136608.44 | O35: =IF(N35=0,0,O33-P35) -> -4553.6148 | P35: =($N$35/$F$22)+(($N$35/$F$22)-P33) -> 2481.816 | AD35: =AC40 -> 78.176689 | AE35: 12
B36: =E37-D37+1 -> 31 | C36: 3 | D36: =EDATE(D35,1) -> 43709 | E36: =EOMONTH(D36,0) -> 43738 | F36: =J35 -> -134557.31 | G36: =$F$9 -> 2000 | H36: =G36+I36 -> 990.82018 | I36: =(F36)*$F$7/12 -> -1009.1798 | J36: =SUM(F36,H36) -> -133566.49 | K36: =J36-J48 -> -12485.715 | L36: =J36-K36 -> -121080.77 | N36: =IF(C36>$F$18,0,$N$35) -> 136608.44 | O36: =IF(N36=0,0,O35-P36) -> -6830.4222 | P36: =($N$35/$F$22) -> 2276.8074
B37: =E38-D38+1 -> 30 | C37: 4 | D37: =EDATE(D36,1) -> 43739 | E37: =EOMONTH(D37,0) -> 43769 | F37: =J36 -> -133566.49 | G37: =$F$9 -> 2000 | H37: =G37+I37 -> 998.25133 | I37: =(F37)*$F$7/12 -> -1001.7487 | J37: =SUM(F37,H37) -> -132568.24 | K37: =J37-J49 -> -12579.358 | L37: =J37-K37 -> -119988.88 | N37: =IF(C37>$F$18,0,$N$35) -> 136608.44 | O37: =IF(N37=0,0,O36-P37) -> -9107.2296 | P37: =($N$35/$F$22) -> 2276.8074 | R37: Lease Interest (P&L) (706030) | W37: Lease Accrued interest (BS) (243040) | AB37: Lease ST Liability (243030)
B38: =E39-D39+1 -> 31 | C38: 5 | D38: =EDATE(D37,1) -> 43770 | E38: =EOMONTH(D38,0) -> 43799 | F38: =J37 -> -132568.24 | G38: =$F$9 -> 2000 | H38: =G38+I38 -> 1005.7382 | I38: =(F38)*$F$7/12 -> -994.26178 | J38: =SUM(F38,H38) -> -131562.5 | K38: =J38-J50 -> -12673.703 | L38: =J38-K38 -> -118888.8 | N38: =IF(C38>$F$18,0,$N$35) -> 136608.44 | O38: =IF(N38=0,0,O37-P38) -> -11384.037 | P38: =($N$35/$F$22) -> 2276.8074 | R38: 5 | S38: =-I33 -> 932.31 | W38: 3 | X38: =Y38 -> 932.31 | Y38: =S38 -> 932.31 | Z38: 5 | AB38: 3 | AC38: =H33 -> 1067.69 | AD38: =AC33 -> 14522.08 | AE38: 4
B39: =E40-D40+1 -> 31 | C39: 6 | D39: =EDATE(D38,1) -> 43800 | E39: =EOMONTH(D39,0) -> 43830 | F39: =J38 -> -131562.5 | G39: =$F$9 -> 2000 | H39: =G39+I39 -> 1013.2813 | I39: =(F39)*$F$7/12 -> -986.71875 | J39: =SUM(F39,H39) -> -130549.22 | K39: =J39-J51 -> -12768.756 | L39: =J39-K39 -> -117780.46 | N39: =IF(C39>$F$18,0,$N$35) -> 136608.44 | O39: =IF(N39=0,0,O38-P39) -> -13660.844 | P39: =($N$35/$F$22) -> 2276.8074 | R39: 13 | S39: =-I35 -> 1016.5557 | W39: 11 | X39: =Y39 -> 1016.5557 | Y39: =S39 -> 1016.5557 | Z39: 13 | AB39: 11 | AC39: =H35 -> 983.44435
B40: =E41-D41+1 -> 29 | C40: 7 | D40: =EDATE(D39,1) -> 43831 | E40: =EOMONTH(D40,0) -> 43861 | F40: =J39 -> -130549.22 | G40: =$F$9 -> 2000 | H40: =G40+I40 -> 1020.8809 | I40: =(F40)*$F$7/12 -> -979.11914 | J40: =SUM(F40,H40) -> -129528.34 | K40: =J40-J52 -> -12864.521 | L40: =J40-K40 -> -116663.82 | N40: =IF(C40>$F$18,0,$N$35) -> 136608.44 | O40: =IF(N40=0,0,O39-P40) -> -15937.652 | P40: =($N$35/$F$22) -> 2276.8074 | AB40: 12 | AC40: =(AD38-AC38)-SUM(H35:H47) -> 78.176689
B41: =E42-D42+1 -> 31 | C41: 8 | D41: =EDATE(D40,1) -> 43862 | E41: =EOMONTH(D41,0) -> 43890 | F41: =J40 -> -129528.34 | G41: =$F$9 -> 2000 | H41: =G41+I41 -> 1028.5375 | I41: =(F41)*$F$7/12 -> -971.46253 | J41: =SUM(F41,H41) -> -128499.8 | K41: =J41-J53 -> -12961.005 | L41: =J41-K41 -> -115538.79 | N41: =IF(C41>$F$18,0,$N$35) -> 136608.44 | O41: =IF(N41=0,0,O40-P41) -> -18214.459 | P41: =($N$35/$F$22) -> 2276.8074
B42: =E43-D43+1 -> 30 | C42: 9 | D42: =EDATE(D41,1) -> 43891 | E42: =EOMONTH(D42,0) -> 43921 | F42: =J41 -> -128499.8 | G42: =$F$9 -> 2000 | H42: =G42+I42 -> 1036.2515 | I42: =(F42)*$F$7/12 -> -963.7485 | J42: =SUM(F42,H42) -> -127463.55 | K42: =J42-J54 -> -13058.213 | L42: =J42-K42 -> -114405.34 | N42: =IF(C42>$F$18,0,$N$35) -> 136608.44 | O42: =IF(N42=0,0,O41-P42) -> -20491.267 | P42: =($N$35/$F$22) -> 2276.8074 | R42: Invoice Clearing Leasing (243031) | W42: Invoice Clearing Leasing - Technical (243032) | AB42: Accounts Payable*
B43: =E44-D44+1 -> 31 | C43: 10 | D43: =EDATE(D42,1) -> 43922 | E43: =EOMONTH(D43,0) -> 43951 | F43: =J42 -> -127463.55 | G43: =$F$9 -> 2000 | H43: =G43+I43 -> 1044.0234 | I43: =(F43)*$F$7/12 -> -955.97661 | J43: =SUM(F43,H43) -> -126419.53 | K43: =J43-J55 -> -13156.149 | L43: =J43-K43 -> -113263.38 | N43: =IF(C43>$F$18,0,$N$35) -> 136608.44 | O43: =IF(N43=0,0,O42-P43) -> -22768.074 | P43: =($N$35/$F$22) -> 2276.8074 | R43: 7 | S43: =AD43-AC48 -> 2000 | T43: =AC38+X38 -> 2000 | U43: 3 | W43: 6 | X43: 2000 | Y43: 2000 | Z43: 7 | AD43: =G33*1.2 -> 2400 | AE43: 6
B44: =E45-D45+1 -> 30 | C44: 11 | D44: =EDATE(D43,1) -> 43952 | E44: =EOMONTH(D44,0) -> 43982 | F44: =J43 -> -126419.53 | G44: =$F$9 -> 2000 | H44: =G44+I44 -> 1051.8536 | I44: =(F44)*$F$7/12 -> -948.14644 | J44: =SUM(F44,H44) -> -125367.67 | K44: =J44-J56 -> -13254.82 | L44: =J44-K44 -> -112112.85 | N44: =IF(C44>$F$18,0,$N$35) -> 136608.44 | O44: =IF(N44=0,0,O43-P44) -> -25044.881 | P44: =($N$35/$F$22) -> 2276.8074 | R44: 15 | S44: =AD44-AC49 -> 2000 | T44: =SUM(AC39,X39) -> 2000 | U44: 11 | W44: 14 | X44: 2000 | Y44: 2000 | Z44: 15 | AD44: =G35*1.2 -> 2400 | AE44: 14
B45: =E46-D46+1 -> 31 | C45: 12 | D45: =EDATE(D44,1) -> 43983 | E45: =EOMONTH(D45,0) -> 44012 | F45: =J44 -> -125367.67 | G45: =$F$9 -> 2000 | H45: =G45+I45 -> 1059.7425 | I45: =(F45)*$F$7/12 -> -940.25754 | J45: =SUM(F45,H45) -> -124307.93 | K45: =J45-J57 -> -13354.232 | L45: =J45-K45 -> -110953.7 | N45: =IF(C45>$F$18,0,$N$35) -> 136608.44 | O45: =IF(N45=0,0,O44-P45) -> -27321.689 | P45: =($N$35/$F$22) -> 2276.8074
B46: =E47-D47+1 -> 31 | C46: 13 | D46: =EDATE(D45,1) -> 44013 | E46: =EOMONTH(D46,0) -> 44043 | F46: =J45 -> -124307.93 | G46: =$F$9 -> 2000 | H46: =G46+I46 -> 1067.6905 | I46: =(F46)*$F$7/12 -> -932.30947 | J46: =SUM(F46,H46) -> -123240.24 | K46: =J46-J58 -> -13454.388 | L46: =J46-K46 -> -109785.85 | N46: =IF(C46>$F$18,0,$N$35) -> 136608.44 | O46: =IF(N46=0,0,O45-P46) -> -29598.496 | P46: =($N$35/$F$22) -> 2276.8074
B47: =E48-D48+1 -> 30 | C47: 14 | D47: =EDATE(D46,1) -> 44044 | E47: =EOMONTH(D47,0) -> 44074 | F47: =J46 -> -123240.24 | G47: =$F$9 -> 2000 | H47: =G47+I47 -> 1075.6982 | I47: =(F47)*$F$7/12 -> -924.30179 | J47: =SUM(F47,H47) -> -122164.54 | K47: =J47-J59 -> -13555.296 | L47: =J47-K47 -> -108609.24 | N47: =IF(C47>$F$18,0,$N$35) -> 136608.44 | O47: =IF(N47=0,0,O46-P47) -> -31875.304 | P47: =($N$35/$F$22) -> 2276.8074 | R47: Depreciation ROU Lease (P&L) (534080) | W47: ="Acc Depreciation ROU Vehicles "&RIGHT(O27,11) -> Acc Depreciation ROU Vehicles 211570 (BS) | AB47: Input VAT (example - different by entity)
B48: =E49-D49+1 -> 31 | C48: 15 | D48: =EDATE(D47,1) -> 44075 | E48: =EOMONTH(D48,0) -> 44104 | F48: =J47 -> -122164.54 | G48: =$F$9 -> 2000 | H48: =G48+I48 -> 1083.7659 | I48: =(F48)*$F$7/12 -> -916.23405 | J48: =SUM(F48,H48) -> -121080.77 | K48: =J48-J60 -> -13656.961 | L48: =J48-K48 -> -107423.81 | N48: =IF(C48>$F$18,0,$N$35) -> 136608.44 | O48: =IF(N48=0,0,O47-P48) -> -34152.111 | P48: =($N$35/$F$22) -> 2276.8074 | R48: 8 | S48: =P33 -> 2071.7988 | Y48: =S48 -> 2071.7988 | Z48: 8 | AB48: 6 | AC48: =AD43*20/120 -> 400
B49: =E50-D50+1 -> 30 | C49: 16 | D49: =EDATE(D48,1) -> 44105 | E49: =EOMONTH(D49,0) -> 44135 | F49: =J48 -> -121080.77 | G49: =$F$9 -> 2000 | H49: =G49+I49 -> 1091.8942 | I49: =(F49)*$F$7/12 -> -908.10581 | J49: =SUM(F49,H49) -> -119988.88 | K49: =J49-J61 -> -13759.388 | L49: =J49-K49 -> -106229.49 | N49: =IF(C49>$F$18,0,$N$35) -> 136608.44 | O49: =IF(N49=0,0,O48-P49) -> -36428.918 | P49: =($N$35/$F$22) -> 2276.8074 | R49: 16 | S49: =P35 -> 2481.816 | Y49: =S49 -> 2481.816 | Z49: 16 | AB49: 14 | AC49: =AD44*20/120 -> 400
B50: =E51-D51+1 -> 31 | C50: 17 | D50: =EDATE(D49,1) -> 44136 | E50: =EOMONTH(D50,0) -> 44165 | F50: =J49 -> -119988.88 | G50: =$F$9 -> 2000 | H50: =G50+I50 -> 1100.0834 | I50: =(F50)*$F$7/12 -> -899.9166 | J50: =SUM(F50,H50) -> -118888.8 | K50: =J50-J62 -> -13862.584 | L50: =J50-K50 -> -105026.21 | N50: =IF(C50>$F$18,0,$N$35) -> 136608.44 | O50: =IF(N50=0,0,O49-P50) -> -38705.726 | P50: =($N$35/$F$22) -> 2276.8074
B51: =E52-D52+1 -> 31 | C51: 18 | D51: =EDATE(D50,1) -> 44166 | E51: =EOMONTH(D51,0) -> 44196 | F51: =J50 -> -118888.8 | G51: =$F$9 -> 2000 | H51: =G51+I51 -> 1108.334 | I51: =(F51)*$F$7/12 -> -891.66598 | J51: =SUM(F51,H51) -> -117780.46 | K51: =J51-J63 -> -13966.553 | L51: =J51-K51 -> -103813.91 | N51: =IF(C51>$F$18,0,$N$35) -> 136608.44 | O51: =IF(N51=0,0,O50-P51) -> -40982.533 | P51: =($N$35/$F$22) -> 2276.8074
B52: =E53-D53+1 -> 28 | C52: 19 | D52: =EDATE(D51,1) -> 44197 | E52: =EOMONTH(D52,0) -> 44227 | F52: =J51 -> -117780.46 | G52: =$F$9 -> 2000 | H52: =G52+I52 -> 1116.6465 | I52: =(F52)*$F$7/12 -> -883.35347 | J52: =SUM(F52,H52) -> -116663.82 | K52: =J52-J64 -> -14071.302 | L52: =J52-K52 -> -102592.51 | N52: =IF(C52>$F$18,0,$N$35) -> 136608.44 | O52: =IF(N52=0,0,O51-P52) -> -43259.341 | P52: =($N$35/$F$22) -> 2276.8074
B53: =E54-D54+1 -> 31 | C53: 20 | D53: =EDATE(D52,1) -> 44228 | E53: =EOMONTH(D53,0) -> 44255 | F53: =J52 -> -116663.82 | G53: =$F$9 -> 2000 | H53: =G53+I53 -> 1125.0214 | I53: =(F53)*$F$7/12 -> -874.97862 | J53: =SUM(F53,H53) -> -115538.79 | K53: =J53-J65 -> -14176.837 | L53: =J53-K53 -> -101361.96 | N53: =IF(C53>$F$18,0,$N$35) -> 136608.44 | O53: =IF(N53=0,0,O52-P53) -> -45536.148 | P53: =($N$35/$F$22) -> 2276.8074 | R53: Accrual Approach
B54: =E55-D55+1 -> 30 | C54: 21 | D54: =EDATE(D53,1) -> 44256 | E54: =EOMONTH(D54,0) -> 44286 | F54: =J53 -> -115538.79 | G54: =$F$9 -> 2000 | H54: =G54+I54 -> 1133.459 | I54: =(F54)*$F$7/12 -> -866.54096 | J54: =SUM(F54,H54) -> -114405.34 | K54: =J54-J66 -> -14283.163 | L54: =J54-K54 -> -100122.17 | N54: =IF(C54>$F$18,0,$N$35) -> 136608.44 | O54: =IF(N54=0,0,O53-P54) -> -47812.955 | P54: =($N$35/$F$22) -> 2276.8074 | R54: Lease expense postings for Accrual Approach are triggered by LAT based on contract payment terms (posting performed when expense is incurred - similar to GR)
B55: =E56-D56+1 -> 31 | C55: 22 | D55: =EDATE(D54,1) -> 44287 | E55: =EOMONTH(D55,0) -> 44316 | F55: =J54 -> -114405.34 | G55: =$F$9 -> 2000 | H55: =G55+I55 -> 1141.96 | I55: =(F55)*$F$7/12 -> -858.04002 | J55: =SUM(F55,H55) -> -113263.38 | K55: =J55-J67 -> -14390.287 | L55: =J55-K55 -> -98873.089 | N55: =IF(C55>$F$18,0,$N$35) -> 136608.44 | O55: =IF(N55=0,0,O54-P55) -> -50089.763 | P55: =($N$35/$F$22) -> 2276.8074 | R55: All amounts below are in contract currency (DC)
B56: =E57-D57+1 -> 30 | C56: 23 | D56: =EDATE(D55,1) -> 44317 | E56: =EOMONTH(D56,0) -> 44347 | F56: =J55 -> -113263.38 | G56: =$F$9 -> 2000 | H56: =G56+I56 -> 1150.5247 | I56: =(F56)*$F$7/12 -> -849.47532 | J56: =SUM(F56,H56) -> -112112.85 | K56: =J56-J68 -> -14498.214 | L56: =J56-K56 -> -97614.637 | N56: =IF(C56>$F$18,0,$N$35) -> 136608.44 | O56: =IF(N56=0,0,O55-P56) -> -52366.57 | P56: =($N$35/$F$22) -> 2276.8074 | R56: Please check LC2, LC3 FX posting conversion where applicable | AB56: Asset class name | AD56: Vehicle
B57: =E58-D58+1 -> 31 | C57: 24 | D57: =EDATE(D56,1) -> 44348 | E57: =EOMONTH(D57,0) -> 44377 | F57: =J56 -> -112112.85 | G57: =$F$9 -> 2000 | H57: =G57+I57 -> 1159.1536 | I57: =(F57)*$F$7/12 -> -840.84638 | J57: =SUM(F57,H57) -> -110953.7 | K57: =J57-J69 -> -14606.951 | L57: =J57-K57 -> -96346.747 | N57: =IF(C57>$F$18,0,$N$35) -> 136608.44 | O57: =IF(N57=0,0,O56-P57) -> -54643.377 | P57: =($N$35/$F$22) -> 2276.8074 | W57: SAP Posting date | AB57: Asset class no. | AD57: 103070
B58: =E59-D59+1 -> 31 | C58: 25 | D58: =EDATE(D57,1) -> 44378 | E58: =EOMONTH(D58,0) -> 44408 | F58: =J57 -> -110953.7 | G58: =$F$9 -> 2000 | H58: =G58+I58 -> 1167.8473 | I58: =(F58)*$F$7/12 -> -832.15273 | J58: =SUM(F58,H58) -> -109785.85 | K58: =J58-J70 -> -14716.503 | L58: =J58-K58 -> -95069.348 | N58: =IF(C58>$F$18,0,$N$35) -> 136608.44 | O58: =IF(N58=0,0,O57-P58) -> -56920.185 | P58: =($N$35/$F$22) -> 2276.8074 | R58: Description | W58: P7 | Y58: P8 | AB58: Material group name | AD58: LeaseVehicle FixCost
B59: =E60-D60+1 -> 30 | C59: 26 | D59: =EDATE(D58,1) -> 44409 | E59: =EOMONTH(D59,0) -> 44439 | F59: =J58 -> -109785.85 | G59: =$F$9 -> 2000 | H59: =G59+I59 -> 1176.6061 | I59: =(F59)*$F$7/12 -> -823.39388 | J59: =SUM(F59,H59) -> -108609.24 | K59: =J59-J71 -> -14826.876 | L59: =J59-K59 -> -93782.368 | N59: =IF(C59>$F$18,0,$N$35) -> 136608.44 | O59: =IF(N59=0,0,O58-P59) -> -59196.992 | P59: =($N$35/$F$22) -> 2276.8074 | R59: Lease expense | V59: 1 | W59: 43678 | X59: 4 | Y59: 43708 | AB59: Mateial group no. | AD59: 95101110
B60: =E61-D61+1 -> 31 | C60: 27 | D60: =EDATE(D59,1) -> 44440 | E60: =EOMONTH(D60,0) -> 44469 | F60: =J59 -> -108609.24 | G60: =$F$9 -> 2000 | H60: =G60+I60 -> 1185.4307 | I60: =(F60)*$F$7/12 -> -814.56933 | J60: =SUM(F60,H60) -> -107423.81 | K60: =J60-J72 -> -14938.078 | L60: =J60-K60 -> -92485.736 | N60: =IF(C60>$F$18,0,$N$35) -> 136608.44 | O60: =IF(N60=0,0,O59-P60) -> -61473.8 | P60: =($N$35/$F$22) -> 2276.8074 | R60: AP: invoice booking | V60: 2 | W60: 43677 | X60: 5 | Y60: 43708 | AB60: Lease payment per period (excl. VAT) | AE60: 2000
B61: =E62-D62+1 -> 30 | C61: 28 | D61: =EDATE(D60,1) -> 44470 | E61: =EOMONTH(D61,0) -> 44500 | F61: =J60 -> -107423.81 | G61: =$F$9 -> 2000 | H61: =G61+I61 -> 1194.3214 | I61: =(F61)*$F$7/12 -> -805.6786 | J61: =SUM(F61,H61) -> -106229.49 | K61: =J61-J73 -> -15050.114 | L61: =J61-K61 -> -91179.379 | N61: =IF(C61>$F$18,0,$N$35) -> 136608.44 | O61: =IF(N61=0,0,O60-P61) -> -63750.607 | P61: =($N$35/$F$22) -> 2276.8074 | R61: Automated reposting of AP | V61: 3 | W61: 43677 | X61: 6 | Y61: 43708 | AB61: Payment frequency | AE61: Monthly
B62: =E63-D63+1 -> 31 | C62: 29 | D62: =EDATE(D61,1) -> 44501 | E62: =EOMONTH(D62,0) -> 44530 | F62: =J61 -> -106229.49 | G62: =$F$9 -> 2000 | H62: =G62+I62 -> 1203.2788 | I62: =(F62)*$F$7/12 -> -796.72119 | J62: =SUM(F62,H62) -> -105026.21 | K62: =J62-J74 -> -15162.989 | L62: =J62-K62 -> -89863.224 | N62: =IF(C62>$F$18,0,$N$35) -> 136608.44 | O62: =IF(N62=0,0,O61-P62) -> -66027.414 | P62: =($N$35/$F$22) -> 2276.8074 | AB62: Payment timing | AE62: Arrears
B63: =E64-D64+1 -> 31 | C63: 30 | D63: =EDATE(D62,1) -> 44531 | E63: =EOMONTH(D63,0) -> 44561 | F63: =J62 -> -105026.21 | G63: =$F$9 -> 2000 | H63: =G63+I63 -> 1212.3034 | I63: =(F63)*$F$7/12 -> -787.6966 | J63: =SUM(F63,H63) -> -103813.91 | K63: =J63-J75 -> -15276.712 | L63: =J63-K63 -> -88537.198 | N63: =IF(C63>$F$18,0,$N$35) -> 136608.44 | O63: =IF(N63=0,0,O62-P63) -> -68304.222 | P63: =($N$35/$F$22) -> 2276.8074 | AB63: Lease term (months) | AE63: 84
B64: =E65-D65+1 -> 28 | C64: 31 | D64: =EDATE(D63,1) -> 44562 | E64: =EOMONTH(D64,0) -> 44592 | F64: =J63 -> -103813.91 | G64: =$F$9 -> 2000 | H64: =G64+I64 -> 1221.3957 | I64: =(F64)*$F$7/12 -> -778.60432 | J64: =SUM(F64,H64) -> -102592.51 | K64: =J64-J76 -> -15391.287 | L64: =J64-K64 -> -87201.227 | N64: =IF(C64>$F$18,0,$N$35) -> 136608.44 | O64: =IF(N64=0,0,O63-P64) -> -70581.029 | P64: =($N$35/$F$22) -> 2276.8074 | AB64: Lease start date | AE64: 43647
B65: =E66-D66+1 -> 31 | C65: 32 | D65: =EDATE(D64,1) -> 44593 | E65: =EOMONTH(D65,0) -> 44620 | F65: =J64 -> -102592.51 | G65: =$F$9 -> 2000 | H65: =G65+I65 -> 1230.5561 | I65: =(F65)*$F$7/12 -> -769.44386 | J65: =SUM(F65,H65) -> -101361.96 | K65: =J65-J77 -> -15506.722 | L65: =J65-K65 -> -85855.236 | N65: =IF(C65>$F$18,0,$N$35) -> 136608.44 | O65: =IF(N65=0,0,O64-P65) -> -72857.837 | P65: =($N$35/$F$22) -> 2276.8074 | AB65: Lease end date | AE65: 46203
B66: =E67-D67+1 -> 30 | C66: 33 | D66: =EDATE(D65,1) -> 44621 | E66: =EOMONTH(D66,0) -> 44651 | F66: =J65 -> -101361.96 | G66: =$F$9 -> 2000 | H66: =G66+I66 -> 1239.7853 | I66: =(F66)*$F$7/12 -> -760.21469 | J66: =SUM(F66,H66) -> -100122.17 | K66: =J66-J78 -> -15623.022 | L66: =J66-K66 -> -84499.151 | N66: =IF(C66>$F$18,0,$N$35) -> 136608.44 | O66: =IF(N66=0,0,O65-P66) -> -75134.644 | P66: =($N$35/$F$22) -> 2276.8074 | AB66: Calculated NPV | AE66: =F16 -> -124307.93
B67: =E68-D68+1 -> 31 | C67: 34 | D67: =EDATE(D66,1) -> 44652 | E67: =EOMONTH(D67,0) -> 44681 | F67: =J66 -> -100122.17 | G67: =$F$9 -> 2000 | H67: =G67+I67 -> 1249.0837 | I67: =(F67)*$F$7/12 -> -750.9163 | J67: =SUM(F67,H67) -> -98873.089 | K67: =J67-J79 -> -15740.195 | L67: =J67-K67 -> -83132.894 | N67: =IF(C67>$F$18,0,$N$35) -> 136608.44 | O67: =IF(N67=0,0,O66-P67) -> -77411.451 | P67: =($N$35/$F$22) -> 2276.8074
B68: =E69-D69+1 -> 30 | C68: 35 | D68: =EDATE(D67,1) -> 44682 | E68: =EOMONTH(D68,0) -> 44712 | F68: =J67 -> -98873.089 | G68: =$F$9 -> 2000 | H68: =G68+I68 -> 1258.4518 | I68: =(F68)*$F$7/12 -> -741.54817 | J68: =SUM(F68,H68) -> -97614.637 | K68: =J68-J80 -> -15858.246 | L68: =J68-K68 -> -81756.391 | N68: =IF(C68>$F$18,0,$N$35) -> 136608.44 | O68: =IF(N68=0,0,O67-P68) -> -79688.259 | P68: =($N$35/$F$22) -> 2276.8074
B69: =E70-D70+1 -> 31 | C69: 36 | D69: =EDATE(D68,1) -> 44713 | E69: =EOMONTH(D69,0) -> 44742 | F69: =J68 -> -97614.637 | G69: =$F$9 -> 2000 | H69: =G69+I69 -> 1267.8902 | I69: =(F69)*$F$7/12 -> -732.10978 | J69: =SUM(F69,H69) -> -96346.747 | K69: =J69-J81 -> -15977.183 | L69: =J69-K69 -> -80369.564 | N69: =IF(C69>$F$18,0,$N$35) -> 136608.44 | O69: =IF(N69=0,0,O68-P69) -> -81965.066 | P69: =($N$35/$F$22) -> 2276.8074 | R69: Invoice Clearing Leasing (243031) | W69: Invoice Clearing Leasing - Technical (243032) | AB69: Accounts Payable*
B70: =E71-D71+1 -> 31 | C70: 37 | D70: =EDATE(D69,1) -> 44743 | E70: =EOMONTH(D70,0) -> 44773 | F70: =J69 -> -96346.747 | G70: =$F$9 -> 2000 | H70: =G70+I70 -> 1277.3994 | I70: =(F70)*$F$7/12 -> -722.6006 | J70: =SUM(F70,H70) -> -95069.348 | K70: =J70-J82 -> -16097.012 | L70: =J70-K70 -> -78972.335 | N70: =IF(C70>$F$18,0,$N$35) -> 136608.44 | O70: =IF(N70=0,0,O69-P70) -> -84241.874 | P70: =($N$35/$F$22) -> 2276.8074 | R70: 3 | S70: =G38 -> 2000 | T70: =G38 -> 2000 | U70: 1 | W70: 2 | X70: =AD70-AC76 -> 2000 | Y70: =S70 -> 2000 | Z70: 3 | AD70: 2400 | AE70: 2
B71: =E72-D72+1 -> 30 | C71: 38 | D71: =EDATE(D70,1) -> 44774 | E71: =EOMONTH(D71,0) -> 44804 | F71: =J70 -> -95069.348 | G71: =$F$9 -> 2000 | H71: =G71+I71 -> 1286.9799 | I71: =(F71)*$F$7/12 -> -713.02011 | J71: =SUM(F71,H71) -> -93782.368 | K71: =J71-J83 -> -16217.74 | L71: =J71-K71 -> -77564.628 | N71: =IF(C71>$F$18,0,$N$35) -> 136608.44 | O71: =IF(N71=0,0,O70-P71) -> -86518.681 | P71: =($N$35/$F$22) -> 2276.8074 | R71: 6 | S71: =G39 -> 2000 | T71: =G39 -> 2000 | U71: 4 | W71: 5 | X71: =AD71-AC77 -> 2000 | Y71: =S71 -> 2000 | Z71: 6 | AD71: 2400 | AE71: 5
B72: =E73-D73+1 -> 31 | C72: 39 | D72: =EDATE(D71,1) -> 44805 | E72: =EOMONTH(D72,0) -> 44834 | F72: =J71 -> -93782.368 | G72: =$F$9 -> 2000 | H72: =G72+I72 -> 1296.6322 | I72: =(F72)*$F$7/12 -> -703.36776 | J72: =SUM(F72,H72) -> -92485.736 | K72: =J72-J84 -> -16339.373 | L72: =J72-K72 -> -76146.363 | N72: =IF(C72>$F$18,0,$N$35) -> 136608.44 | O72: =IF(N72=0,0,O71-P72) -> -88795.488 | P72: =($N$35/$F$22) -> 2276.8074
B73: =E74-D74+1 -> 30 | C73: 40 | D73: =EDATE(D72,1) -> 44835 | E73: =EOMONTH(D73,0) -> 44865 | F73: =J72 -> -92485.736 | G73: =$F$9 -> 2000 | H73: =G73+I73 -> 1306.357 | I73: =(F73)*$F$7/12 -> -693.64302 | J73: =SUM(F73,H73) -> -91179.379 | K73: =J73-J85 -> -16461.918 | L73: =J73-K73 -> -74717.46 | N73: =IF(C73>$F$18,0,$N$35) -> 136608.44 | O73: =IF(N73=0,0,O72-P73) -> -91072.296 | P73: =($N$35/$F$22) -> 2276.8074
B74: =E75-D75+1 -> 31 | C74: 41 | D74: =EDATE(D73,1) -> 44866 | E74: =EOMONTH(D74,0) -> 44895 | F74: =J73 -> -91179.379 | G74: =$F$9 -> 2000 | H74: =G74+I74 -> 1316.1547 | I74: =(F74)*$F$7/12 -> -683.84534 | J74: =SUM(F74,H74) -> -89863.224 | K74: =J74-J86 -> -16585.382 | L74: =J74-K74 -> -73277.841 | N74: =IF(C74>$F$18,0,$N$35) -> 136608.44 | O74: =IF(N74=0,0,O73-P74) -> -93349.103 | P74: =($N$35/$F$22) -> 2276.8074
B75: =E76-D76+1 -> 31 | C75: 42 | D75: =EDATE(D74,1) -> 44896 | E75: =EOMONTH(D75,0) -> 44926 | F75: =J74 -> -89863.224 | G75: =$F$9 -> 2000 | H75: =G75+I75 -> 1326.0258 | I75: =(F75)*$F$7/12 -> -673.97418 | J75: =SUM(F75,H75) -> -88537.198 | K75: =J75-J87 -> -16709.773 | L75: =J75-K75 -> -71827.425 | N75: =IF(C75>$F$18,0,$N$35) -> 136608.44 | O75: =IF(N75=0,0,O74-P75) -> -95625.911 | P75: =($N$35/$F$22) -> 2276.8074 | R75: Lease expense - Vehicles Stat/Tax (534025) | AB75: Input VAT (example - different by entity)
B76: =E77-D77+1 -> 28 | C76: 43 | D76: =EDATE(D75,1) -> 44927 | E76: =EOMONTH(D76,0) -> 44957 | F76: =J75 -> -88537.198 | G76: =$F$9 -> 2000 | H76: =G76+I76 -> 1335.971 | I76: =(F76)*$F$7/12 -> -664.02899 | J76: =SUM(F76,H76) -> -87201.227 | K76: =J76-J88 -> -16835.096 | L76: =J76-K76 -> -70366.131 | N76: =IF(C76>$F$18,0,$N$35) -> 136608.44 | O76: =IF(N76=0,0,O75-P76) -> -97902.718 | P76: =($N$35/$F$22) -> 2276.8074 | R76: 1 | S76: =T70 -> 2000 | AB76: 2 | AC76: 400
B77: =E78-D78+1 -> 31 | C77: 44 | D77: =EDATE(D76,1) -> 44958 | E77: =EOMONTH(D77,0) -> 44985 | F77: =J76 -> -87201.227 | G77: =$F$9 -> 2000 | H77: =G77+I77 -> 1345.9908 | I77: =(F77)*$F$7/12 -> -654.0092 | J77: =SUM(F77,H77) -> -85855.236 | K77: =J77-J89 -> -16961.359 | L77: =J77-K77 -> -68893.877 | N77: =IF(C77>$F$18,0,$N$35) -> 136608.44 | O77: =IF(N77=0,0,O76-P77) -> -100179.53 | P77: =($N$35/$F$22) -> 2276.8074 | R77: 4 | S77: =T71 -> 2000 | AB77: 5 | AC77: 400
B78: =E79-D79+1 -> 30 | C78: 45 | D78: =EDATE(D77,1) -> 44986 | E78: =EOMONTH(D78,0) -> 45016 | F78: =J77 -> -85855.236 | G78: =$F$9 -> 2000 | H78: =G78+I78 -> 1356.0857 | I78: =(F78)*$F$7/12 -> -643.91427 | J78: =SUM(F78,H78) -> -84499.151 | K78: =J78-J90 -> -17088.57 | L78: =J78-K78 -> -67410.581 | N78: =IF(C78>$F$18,0,$N$35) -> 136608.44 | O78: =IF(N78=0,0,O77-P78) -> -102456.33 | P78: =($N$35/$F$22) -> 2276.8074
B79: =E80-D80+1 -> 31 | C79: 46 | D79: =EDATE(D78,1) -> 45017 | E79: =EOMONTH(D79,0) -> 45046 | F79: =J78 -> -84499.151 | G79: =$F$9 -> 2000 | H79: =G79+I79 -> 1366.2564 | I79: =(F79)*$F$7/12 -> -633.74363 | J79: =SUM(F79,H79) -> -83132.894 | K79: =J79-J91 -> -17216.734 | L79: =J79-K79 -> -65916.16 | N79: =IF(C79>$F$18,0,$N$35) -> 136608.44 | O79: =IF(N79=0,0,O78-P79) -> -104733.14 | P79: =($N$35/$F$22) -> 2276.8074
B80: =E81-D81+1 -> 30 | C80: 47 | D80: =EDATE(D79,1) -> 45047 | E80: =EOMONTH(D80,0) -> 45077 | F80: =J79 -> -83132.894 | G80: =$F$9 -> 2000 | H80: =G80+I80 -> 1376.5033 | I80: =(F80)*$F$7/12 -> -623.49671 | J80: =SUM(F80,H80) -> -81756.391 | K80: =J80-J92 -> -17345.859 | L80: =J80-K80 -> -64410.532 | N80: =IF(C80>$F$18,0,$N$35) -> 136608.44 | O80: =IF(N80=0,0,O79-P80) -> -107009.95 | P80: =($N$35/$F$22) -> 2276.8074
B81: =E82-D82+1 -> 31 | C81: 48 | D81: =EDATE(D80,1) -> 45078 | E81: =EOMONTH(D81,0) -> 45107 | F81: =J80 -> -81756.391 | G81: =$F$9 -> 2000 | H81: =G81+I81 -> 1386.8271 | I81: =(F81)*$F$7/12 -> -613.17293 | J81: =SUM(F81,H81) -> -80369.564 | K81: =J81-J93 -> -17475.953 | L81: =J81-K81 -> -62893.611 | N81: =IF(C81>$F$18,0,$N$35) -> 136608.44 | O81: =IF(N81=0,0,O80-P81) -> -109286.75 | P81: =($N$35/$F$22) -> 2276.8074
B82: =E83-D83+1 -> 31 | C82: 49 | D82: =EDATE(D81,1) -> 45108 | E82: =EOMONTH(D82,0) -> 45138 | F82: =J81 -> -80369.564 | G82: =$F$9 -> 2000 | H82: =G82+I82 -> 1397.2283 | I82: =(F82)*$F$7/12 -> -602.77173 | J82: =SUM(F82,H82) -> -78972.335 | K82: =J82-J94 -> -17607.023 | L82: =J82-K82 -> -61365.313 | N82: =IF(C82>$F$18,0,$N$35) -> 136608.44 | O82: =IF(N82=0,0,O81-P82) -> -111563.56 | P82: =($N$35/$F$22) -> 2276.8074 | R82: Invoice Receipt Approach
B83: =E84-D84+1 -> 30 | C83: 50 | D83: =EDATE(D82,1) -> 45139 | E83: =EOMONTH(D83,0) -> 45169 | F83: =J82 -> -78972.335 | G83: =$F$9 -> 2000 | H83: =G83+I83 -> 1407.7075 | I83: =(F83)*$F$7/12 -> -592.29252 | J83: =SUM(F83,H83) -> -77564.628 | K83: =J83-J95 -> -17739.076 | L83: =J83-K83 -> -59825.552 | N83: =IF(C83>$F$18,0,$N$35) -> 136608.44 | O83: =IF(N83=0,0,O82-P83) -> -113840.37 | P83: =($N$35/$F$22) -> 2276.8074 | R83: Lease expense recognition for IR approach is triggered by the invoice posting
B84: =E85-D85+1 -> 31 | C84: 51 | D84: =EDATE(D83,1) -> 45170 | E84: =EOMONTH(D84,0) -> 45199 | F84: =J83 -> -77564.628 | G84: =$F$9 -> 2000 | H84: =G84+I84 -> 1418.2653 | I84: =(F84)*$F$7/12 -> -581.73471 | J84: =SUM(F84,H84) -> -76146.363 | K84: =J84-J96 -> -17872.119 | L84: =J84-K84 -> -58274.244 | N84: =IF(C84>$F$18,0,$N$35) -> 136608.44 | O84: =IF(N84=0,0,O83-P84) -> -116117.18 | P84: =($N$35/$F$22) -> 2276.8074 | R84: All amounts below are in contract currency (DC)
B85: =E86-D86+1 -> 30 | C85: 52 | D85: =EDATE(D84,1) -> 45200 | E85: =EOMONTH(D85,0) -> 45230 | F85: =J84 -> -76146.363 | G85: =$F$9 -> 2000 | H85: =G85+I85 -> 1428.9023 | I85: =(F85)*$F$7/12 -> -571.09772 | J85: =SUM(F85,H85) -> -74717.46 | K85: =J85-J97 -> -18006.16 | L85: =J85-K85 -> -56711.301 | N85: =IF(C85>$F$18,0,$N$35) -> 136608.44 | O85: =IF(N85=0,0,O84-P85) -> -118393.98 | P85: =($N$35/$F$22) -> 2276.8074 | R85: Please check LC2, LC3 FX posting conversion where applicable | AB85: Asset class name | AD85: Vehicle
B86: =E87-D87+1 -> 31 | C86: 53 | D86: =EDATE(D85,1) -> 45231 | E86: =EOMONTH(D86,0) -> 45260 | F86: =J85 -> -74717.46 | G86: =$F$9 -> 2000 | H86: =G86+I86 -> 1439.619 | I86: =(F86)*$F$7/12 -> -560.38095 | J86: =SUM(F86,H86) -> -73277.841 | K86: =J86-J98 -> -18141.206 | L86: =J86-K86 -> -55136.636 | N86: =IF(C86>$F$18,0,$N$35) -> 136608.44 | O86: =IF(N86=0,0,O85-P86) -> -120670.79 | P86: =($N$35/$F$22) -> 2276.8074 | W86: SAP Posting date | AB86: Asset class no. | AD86: 103070
B87: =E88-D88+1 -> 31 | C87: 54 | D87: =EDATE(D86,1) -> 45261 | E87: =EOMONTH(D87,0) -> 45291 | F87: =J86 -> -73277.841 | G87: =$F$9 -> 2000 | H87: =G87+I87 -> 1450.4162 | I87: =(F87)*$F$7/12 -> -549.58381 | J87: =SUM(F87,H87) -> -71827.425 | K87: =J87-J99 -> -18277.265 | L87: =J87-K87 -> -53550.16 | N87: =IF(C87>$F$18,0,$N$35) -> 136608.44 | O87: =IF(N87=0,0,O86-P87) -> -122947.6 | P87: =($N$35/$F$22) -> 2276.8074 | R87: Description | W87: P7 | Y87: P8 | AB87: Material group name | AD87: LeaseVehicle FixCost
B88: =E89-D89+1 -> 29 | C88: 55 | D88: =EDATE(D87,1) -> 45292 | E88: =EOMONTH(D88,0) -> 45322 | F88: =J87 -> -71827.425 | G88: =$F$9 -> 2000 | H88: =G88+I88 -> 1461.2943 | I88: =(F88)*$F$7/12 -> -538.70569 | J88: =SUM(F88,H88) -> -70366.131 | K88: =J88-J100 -> -18414.344 | L88: =J88-K88 -> -51951.787 | N88: =IF(C88>$F$18,0,$N$35) -> 136608.44 | O88: =IF(N88=0,0,O87-P88) -> -125224.41 | P88: =($N$35/$F$22) -> 2276.8074 | R88: AP: invoice booking | V88: 1 | W88: 43677 | X88: 3 | Y88: 43708 | AB88: Mateial group no. | AD88: 95101110
B89: =E90-D90+1 -> 31 | C89: 56 | D89: =EDATE(D88,1) -> 45323 | E89: =EOMONTH(D89,0) -> 45351 | F89: =J88 -> -70366.131 | G89: =$F$9 -> 2000 | H89: =G89+I89 -> 1472.254 | I89: =(F89)*$F$7/12 -> -527.74598 | J89: =SUM(F89,H89) -> -68893.877 | K89: =J89-J101 -> -18552.452 | L89: =J89-K89 -> -50341.425 | N89: =IF(C89>$F$18,0,$N$35) -> 136608.44 | O89: =IF(N89=0,0,O88-P89) -> -127501.21 | P89: =($N$35/$F$22) -> 2276.8074 | R89: Automated reposting of Invoice to P&L | V89: 2 | W89: 43677 | X89: 4 | Y89: 43708 | AB89: Lease payment per period (excl. VAT) | AE89: 2000
B90: =E91-D91+1 -> 30 | C90: 57 | D90: =EDATE(D89,1) -> 45352 | E90: =EOMONTH(D90,0) -> 45382 | F90: =J89 -> -68893.877 | G90: =$F$9 -> 2000 | H90: =G90+I90 -> 1483.2959 | I90: =(F90)*$F$7/12 -> -516.70408 | J90: =SUM(F90,H90) -> -67410.581 | K90: =J90-J102 -> -18691.595 | L90: =J90-K90 -> -48718.986 | N90: =IF(C90>$F$18,0,$N$35) -> 136608.44 | O90: =IF(N90=0,0,O89-P90) -> -129778.02 | P90: =($N$35/$F$22) -> 2276.8074 | AB90: Payment frequency | AE90: Monthly
B91: =E92-D92+1 -> 31 | C91: 58 | D91: =EDATE(D90,1) -> 45383 | E91: =EOMONTH(D91,0) -> 45412 | F91: =J90 -> -67410.581 | G91: =$F$9 -> 2000 | H91: =G91+I91 -> 1494.4206 | I91: =(F91)*$F$7/12 -> -505.57936 | J91: =SUM(F91,H91) -> -65916.16 | K91: =J91-J103 -> -18831.782 | L91: =J91-K91 -> -47084.378 | N91: =IF(C91>$F$18,0,$N$35) -> 136608.44 | O91: =IF(N91=0,0,O90-P91) -> -132054.83 | P91: =($N$35/$F$22) -> 2276.8074 | AB91: Payment timing | AE91: Arrears
B92: =E93-D93+1 -> 30 | C92: 59 | D92: =EDATE(D91,1) -> 45413 | E92: =EOMONTH(D92,0) -> 45443 | F92: =J91 -> -65916.16 | G92: =$F$9 -> 2000 | H92: =G92+I92 -> 1505.6288 | I92: =(F92)*$F$7/12 -> -494.3712 | J92: =SUM(F92,H92) -> -64410.532 | K92: =J92-J104 -> -18973.021 | L92: =J92-K92 -> -45437.511 | N92: =IF(C92>$F$18,0,$N$35) -> 136608.44 | O92: =IF(N92=0,0,O91-P92) -> -134331.64 | P92: =($N$35/$F$22) -> 2276.8074 | AB92: Lease term (months) | AE92: 84
B93: =E94-D94+1 -> 31 | C93: 60 | D93: =EDATE(D92,1) -> 45444 | E93: =EOMONTH(D93,0) -> 45473 | F93: =J92 -> -64410.532 | G93: =$F$9 -> 2000 | H93: =G93+I93 -> 1516.921 | I93: =(F93)*$F$7/12 -> -483.07899 | J93: =SUM(F93,H93) -> -62893.611 | K93: =J93-J105 -> -19115.318 | L93: =J93-K93 -> -43778.292 | N93: =IF(C93>$F$18,0,$N$35) -> 136608.44 | O93: =IF(N93=0,0,O92-P93) -> -136608.44 | P93: =($N$35/$F$22) -> 2276.8074 | AB93: Lease start date | AE93: 43647
B94: =E95-D95+1 -> 31 | C94: 61 | D94: =EDATE(D93,1) -> 45474 | E94: =EOMONTH(D94,0) -> 45504 | F94: =J93 -> -62893.611 | G94: =$F$9 -> 2000 | H94: =G94+I94 -> 1528.2979 | I94: =(F94)*$F$7/12 -> -471.70208 | J94: =SUM(F94,H94) -> -61365.313 | K94: =J94-J106 -> -19258.683 | L94: =J94-K94 -> -42106.629 | N94: =IF(C94>$F$18,0,$N$35) -> 0 | O94: =IF(N94=0,0,O93-P94) -> 0 | AB94: Lease end date | AE94: 46203
B95: =E96-D96+1 -> 30 | C95: 62 | D95: =EDATE(D94,1) -> 45505 | E95: =EOMONTH(D95,0) -> 45535 | F95: =J94 -> -61365.313 | G95: =$F$9 -> 2000 | H95: =G95+I95 -> 1539.7602 | I95: =(F95)*$F$7/12 -> -460.23984 | J95: =SUM(F95,H95) -> -59825.552 | K95: =J95-J107 -> -19403.123 | L95: =J95-K95 -> -40422.429 | N95: =IF(C95>$F$18,0,$N$35) -> 0 | O95: =IF(N95=0,0,O94-P95) -> 0 | AB95: Calculated NPV | AE95: =F16 -> -124307.93
B96: =E97-D97+1 -> 31 | C96: 63 | D96: =EDATE(D95,1) -> 45536 | E96: =EOMONTH(D96,0) -> 45565 | F96: =J95 -> -59825.552 | G96: =$F$9 -> 2000 | H96: =G96+I96 -> 1551.3084 | I96: =(F96)*$F$7/12 -> -448.69164 | J96: =SUM(F96,H96) -> -58274.244 | K96: =J96-J108 -> -19548.647 | L96: =J96-K96 -> -38725.597 | N96: =IF(C96>$F$18,0,$N$35) -> 0 | O96: =IF(N96=0,0,O95-P96) -> 0
B97: =E98-D98+1 -> 30 | C97: 64 | D97: =EDATE(D96,1) -> 45566 | E97: =EOMONTH(D97,0) -> 45596 | F97: =J96 -> -58274.244 | G97: =$F$9 -> 2000 | H97: =G97+I97 -> 1562.9432 | I97: =(F97)*$F$7/12 -> -437.05683 | J97: =SUM(F97,H97) -> -56711.301 | K97: =J97-J109 -> -19695.262 | L97: =J97-K97 -> -37016.039 | N97: =IF(C97>$F$18,0,$N$35) -> 0 | O97: =IF(N97=0,0,O96-P97) -> 0 | R97: Lease expense - Vehicles Stat/Tax (534025) | W97: Invoice Clearing Leasing - Technical (243032) | AB97: Accounts Payable*
B98: =E99-D99+1 -> 31 | C98: 65 | D98: =EDATE(D97,1) -> 45597 | E98: =EOMONTH(D98,0) -> 45626 | F98: =J97 -> -56711.301 | G98: =$F$9 -> 2000 | H98: =G98+I98 -> 1574.6652 | I98: =(F98)*$F$7/12 -> -425.33476 | J98: =SUM(F98,H98) -> -55136.636 | K98: =J98-J110 -> -19842.976 | L98: =J98-K98 -> -35293.66 | N98: =IF(C98>$F$18,0,$N$35) -> 0 | O98: =IF(N98=0,0,O97-P98) -> 0 | R98: 2 | S98: =Y98 -> 2000 | W98: 1 | X98: =AD98-AC103 -> 2000 | Y98: =X98 -> 2000 | Z98: 2 | AD98: 2400 | AE98: 1
B99: =E100-D100+1 -> 31 | C99: 66 | D99: =EDATE(D98,1) -> 45627 | E99: =EOMONTH(D99,0) -> 45657 | F99: =J98 -> -55136.636 | G99: =$F$9 -> 2000 | H99: =G99+I99 -> 1586.4752 | I99: =(F99)*$F$7/12 -> -413.52477 | J99: =SUM(F99,H99) -> -53550.16 | K99: =J99-J111 -> -19991.798 | L99: =J99-K99 -> -33558.362 | N99: =IF(C99>$F$18,0,$N$35) -> 0 | O99: =IF(N99=0,0,O98-P99) -> 0 | R99: 4 | S99: =Y99 -> 2000 | W99: 3 | X99: =AD99-AC104 -> 2000 | Y99: =X99 -> 2000 | Z99: 4 | AD99: 2400 | AE99: 3
B100: =E101-D101+1 -> 28 | C100: 67 | D100: =EDATE(D99,1) -> 45658 | E100: =EOMONTH(D100,0) -> 45688 | F100: =J99 -> -53550.16 | G100: =$F$9 -> 2000 | H100: =G100+I100 -> 1598.3738 | I100: =(F100)*$F$7/12 -> -401.6262 | J100: =SUM(F100,H100) -> -51951.787 | K100: =J100-J112 -> -20141.737 | L100: =J100-K100 -> -31810.05 | N100: =IF(C100>$F$18,0,$N$35) -> 0 | O100: =IF(N100=0,0,O99-P100) -> 0
B101: =E102-D102+1 -> 31 | C101: 68 | D101: =EDATE(D100,1) -> 45689 | E101: =EOMONTH(D101,0) -> 45716 | F101: =J100 -> -51951.787 | G101: =$F$9 -> 2000 | H101: =G101+I101 -> 1610.3616 | I101: =(F101)*$F$7/12 -> -389.6384 | J101: =SUM(F101,H101) -> -50341.425 | K101: =J101-J113 -> -20292.8 | L101: =J101-K101 -> -30048.625 | N101: =IF(C101>$F$18,0,$N$35) -> 0 | O101: =IF(N101=0,0,O100-P101) -> 0
...

Sheet 6 - Contract Termination
C1: 6 - Contract Termination | BB1: Advance
BB2: Arrears
C3: Asset class name | E3: Hardware
C4: Asset class no. | E4: 103040
C5: Material group name | E5: =VLOOKUP(E6,'Material Groups'!$B:$C,2,0) -> Lease HW Fixed Cost | F5: =VLOOKUP(F6,'Material Groups'!$B:$C,2,0) -> #N/A
C6: Mateial group no. | E6: 95101116
C7: Shopping cart number
C8: PR number
C9: PO no.
C10: Vendor ID
C11: Invoice no.
C12: Annual interest rate | F12: 0.07
C13: Monthly interest rate | F13: =(1+F12)^(1/12)-1 -> 0.0056541454
C14: Lease payment per period (excl. VAT) | F14: 4000
C15: Payment frequency | F15: Monthly
C16: Payment timing | F16: Advance
C17: First payment Date | F17: 43647
C18: Lease term (months) | F18: 48
C19: Lease start date | F19: 43647
C20: Lease end date | F20: 45107 | R20: IFRS 16 Approach
C21: Calculated NPV | F21: -168015.21 | R21: All amounts below are in contract currency (DC)
C22: Useful life (UL) of the asset (years) | F22: 3 | R22: Please check LC2, LC3 FX posting conversion where applicable | AB22: Asset class name | AD22: Hardware
C23: Lower UL / contract duration (Months) | F23: =IF(F18<(F22*12),F18,F22*12) -> 36 | G23: for depreciation | W23: SAP Posting date | AB23: Asset class no. | AD23: 103040
R24: Description | W24: P7 | Y24: P8 | AB24: Material group name | AD24: Lease HW Fixed Cost
R25: Initial posting: recognition of assets | V25: 1 | W25: =$D$38 -> 43647 | AB25: Mateial group no. | AD25: 95101116
R26: Initial posting: recognition of liability | V26: 2 | W26: =$D$38 -> 43647 | AB26: Lease payment per period (excl. VAT) | AE26: 4000
R27: Payment by Nakisa | V27: 3 | W27: =$D$38 -> 43647 | AB27: Payment frequency | AE27: Monthly
I28: LEASE LIABILITY | N28: RIGHT OF USE ASSET | R28: LT liability to ST liability reclass | V28: 4 | W28: =$E$38 -> 43677 | AB28: Payment timing | AE28: Advance
